Workbook

Sheet Model Health
A1: RealGold Financial Model - FULLY DYNAMIC
A3: Version | B3: V2.3 - Fully Dynamic
A4: Updated | B4: 2025-11-26 15:13:12
A6: KEY FEATURE: Dynamic Date Management
A7: Instructions | B7: Change any date in 'Mine Inventory' Column B
B8: ALL data redistributes automatically across entire workbook
A10: Corrections Applied
A11: Item | B11: Change | C11: Status
A12: Unitization Fee | B12: 0.5% → 0.01% | C12: CRITICAL
A13: Courbet Mine | B13: Sep '25 → Dec '25 | C13: Updated
A14: Mine 2 | B14: Nov '25 → Jan '26 | C14: Updated
A15: Column AO | B15: MATCH formulas added | C15: DYNAMIC OFFSETS
A16: Resource Supply | B16: SUMIF/COUNTIF formulas | C16: DYNAMIC DATA
A17: All Headers | B17: XAUconfig references | C17: Dynamic timeline
A20: Live Validation
A21: Unitization Fee | B21: =IF(Inputs!B26=0.0001,"✓ PASS","✗ FAIL")
A22: Timeline Start | B22: =XAUconfig!B4 | C22: Should be: Dec '25
A23: Courbet Date | B23: ="Mine Inventory"!B2 | C23: Should be: Dec '25
A24: Courbet Offset (Dynamic) | B24: ="Mine Inventory"!AO2 | C24: Should be: 0 (if Courbet is Dec '25)

Sheet Overview
A1: RealGold Financial Model Workbook
A2: Welcome to the Financial Model Workbook for RealGold. This model is designed to provide a transparent, dynamic, and scenario-driven view of our economic design.
A3: It outlines the key assumptions, inputs, mechanisms, and projected outcomes that support the viability, sustainability, and scalability of RealGold.
A4: The model is modular and interactive — feel free to explore each section to understand how various parameters shape the financial architecture.
A6: Sheets
A7: Summaries | B7: Charts representing top level summaries including Resources under Management, Cash Position, Cashflows, Revenue, and Token Supply/Demand.
A8: Inputs | B8: Primary assumptions live here. This includes gold spot price, collateralization ratios, unlock schedules, fee percentages, and other model-wide variables. This sheet powers dynamic calculations across the workbook.
A9: Mine Inventory | B9: Holds our working list of registered mines (currently dummy data for testing). Each mine’s resource classification (Measured, Indicated, Inferred), Tripartite committment, and unlock rates are here.
A10: Resource Supply (5yr) | B10: Calculates the yearly market availability of RealGold units based on the Mine Inventory and Trust commitments. This is where unitizable resources become released to market over a 20–40 year time horizon.
A11: Token Supply (5yr) | B11: Projects the circulating and total RealGold token counts over five years, incorporating unlock schedules and treasury allocations to forecast market‑cap and liquidity trajectories.
A12: Token Demand (5yr) | B12: Models how RealGold units trade once released to the market. Includes transfer volume assumptions and projected on-chain activity, which feed into token economics and fee revenue projections.
A13: Cashflow (RA LLC) | B13: A traditional cash flow statement for the Regenerative Assets LLC, tracking income, expenditures, and net position over time.
A14: Cashflow (RAF) (5yr) | B14: A traditional cash flow statement for the Real Assets Foundation, tracking income, expenditures, and net position over time.
A15: Cashflow (RGT) | B15: A traditional cash flow statement for the Real Gold Treasury, tracking income, expenditures, and net position over time.
A16: Personnel | B16: Outlines all team roles, titles, stipends, and salaries. Used to forecast payroll and model team growth over time.
A17: Deferred Comp | B17: Tracks the team deferred compensation issuances, redemptions, and remaining balances, linking operational spending and capital raises to outstanding Keepon obligations for accurate liability accounting.
A18: Capital | B18: Defines the capital strategy. Models tranches of funding, investor return mechanics (e.g., “keepons”), and capital return timing.
... A21: Expenditures | B21: Captures actual costs to date, including operations, legal, tech development, and compliance. Informs Keepon accumulation for project expenses to date.
A27: Assumptions
B28: Gold price of $2707 as of December 31st, 2024 with a CAGR of 7.8%
B29: Paying back our capital raised within 4 years
B30: ~8 million assayed ounces of gold-in-ground registered over 4 years from 12 mines
B31: No new inventory after 4 years in order to gauge annual recurring revenue
B32: Sensitivity analysis uses gold price of of 12/31/2024 + CAGR and assumes consistent 15% underperformance.

Sheet Summaries
A1: Summaries | J1: e

Sheet Inputs
A1: Realgold Financial Model Inputs
A3: Project Qualification Level | B3: Resource Unlock % | C3: Resource Holdback % | D3: Max Initial Release | E3: Release Years | F3: Review Cycle | G3: Qualifications under review for ongoing time-released funds
A4: Mineral Estate Trust | B4: =1-C4 | C4: 0.8 | D4: 0.2 | E4: 40 | F4: 5 years | G4: Gold is protected. No active mining. Enviornmental remediation plan being fulfilled. Remediation metrics met (80%+)
A5: Mineral + Bio Estate Trusts | B5: =1-C5 | C5: 0.65 | D5: 0.2 | E5: 30 | F5: 5 years | G5: Regen land management plan being fulfilled. Targets met (80%+) (+mining reqs)
A6: Mineral + Bio + Social Estate Trusts | B6: =1-C6 | C6: 0.5 | D6: 0.2 | E6: 20 | F6: 3 years | G6: All three trusts operational with their regen plans being fulfilled.
A8: Mineral Prices & Units
A9: Price of Gold (oz) (as of Dec. 31, 2024) | B9: 2711.6
A10: Gold Spot Price (as of Aug. 9, 2025) | B10: 3779
A11: Silver Spot Price | B11: 38.16
A12: Silver/Gold Ratio | B12: =B10/B11
A13: Silver/Gold Conversion Ratio | B13: 120
A14: Gold CAGR (historical over 25 yrs) | B14: 0.078
A15: AISC (NatGold Index) | B15: 1481.32
A16: Intrinsic Value (price of gold - AISC) | B16: =B10-B15
A17: Intrinsic Value (%) | B17: =B16/B9
A19: Valuation of Types of Mineral Resources
A20: Measured | B20: 1
A21: Indicated | B21: 0.75
A22: Inferred | B22: 0.5
A24: RealGold Fee Structure
A25: Yearly Admin Fee (on authorized assets) | B25: 0.0001
A26: Unitization Fee (linked to unlocks) | B26: 0.0001
A27: Liquidity Reserve Fee | B27: 0.01
A28: RealGold Token Minting Fee | B28: 0.005
A29: RealGold Token Transfer Tax | B29: 0.003
A31: Token Supply Scenarios (Sale of RG by Trusts)
A32: Conservative sales | B32: 0.25
A33: Moderate sales | B33: 0.5
A34: Aggressive sales | B34: 1
A36: Liquidity Variables
A37: Impermanent Loss (average) | B37: 0.01
A38: DEX Swap Fees | B38: 0.003
A40: Market-Making Variables
A41: Buy Price | B41: 0.99
A42: Sell Price | B42: 1.02
A43: Spread per oz (minus transfer & swap fees) | B43: =1+(1*Inputs!B42)-(1*Inputs!B41)-(1*Inputs!B29)-(1*Inputs!B38)
A44: Volatility
A46: Compensation Multipliers
A47: Target 1 | B47: 1.5
A48: Target 2 | B48: 2
A50: Sensitivity Analysis
A51: Below XAU Spot | B51: 0.85
A52: Above XAU Spot | B52: 1.15
A54: Redemption Variables
A55: Cap on Redemption (% of Unlocked Token Supply) | B55: 0.02
A56: Redemption Premium

Sheet Mine Inventory
A1: Mine Inventory | C1: Mea. Au (oz) | D1: Ind. Au (oz) | E1: Inf. Au (oz) | F1: Assayed Au (oz) | G1: Mea. Ag (oz) | H1: Mea. Ag (oz) | I1: Mea. Ag (oz) | J1: Assayed Ag (oz) | K1: Ag->Au (oz) | L1: TTL Assayed Au (oz) | M1: Auth. Au (oz) | N1: Tripartite Level | O1: OCR Reserve (oz) | P1: Lifetime Release (oz) | Q1: Year 1 Unlock (oz) | R1: Liquidity Allocation (oz) | S1: Unitization Fee Pool (oz) | T1: Admin Units Pool (oz) | U1: Yearly Admin Fee (oz) | V1: Yearly Unitization Fee | W1: Yearly Unlock (oz) | X1: Grantor Comp ($) | Y1: Grantor Comp (oz) | Z1: Grantor Comp (%) | AA1: Comp Per Ounce | AB1: Lifetime Release ($) | AC1: 1st Year Release ($) | AD1: Yearly Release ($) | AE1: 1031 Allocation | AF1: Token Allocation | AG1: Supply Sales | AH1: 1st Yr Monthly Token Sales From Trusts | AI1: Monthly Sales from Trusts | AJ1: Total Yearly Fees (oz) | AK1: Yearly Reg Fee ($) | AL1: Yearly Release Fees ($) | AM1: Total Yearly Fees ($) | AO1: Month Offset (Dynamic)
A2: Courbet Mine | B2: Dec '25 | C2: 0 | D2: 0 | E2: 46310 | F2: =sum(C2:E2) | G2: 0 | H2: 0 | I2: 229600 | J2: =sum(G2:I2) | K2: =J2/Inputs!B13 | L2: =F2+K2 | M2: =(C2*Inputs!B20)+(D2*Inputs!B21)+(E2*Inputs!B22)+(K2*Inputs!B22) | N2: Mineral + Bio + Social Estate | O2: =M2-P2 | P2: =M2 * VALUE(SUBSTITUTE(VLOOKUP(N2, TTFconfig!A2:E4, 3, FALSE),, "")) | Q2: =M2 * VALUE(SUBSTITUTE(VLOOKUP(N2, TTFconfig!A2:E4, 4, FALSE),, "")) | R2: =M2*Inputs!$B$27 | S2: =M2*Inputs!$B$26 | T2: =M2*(Inputs!$B$25*50) | U2: =M2*Inputs!B25 | V2: =M2*Inputs!B26 | W2: =(P2-Q2-R2-S2-T2-Y2) / VALUE(SUBSTITUTE(VLOOKUP(N2, TTFconfig!A2:E4, 5, FALSE),, "")) | X2: 750000 | Y2: =X2/Inputs!$B$10 | Z2: =Y2/M2 | AA2: =X2/L2 | AB2: =P2*Inputs!B10 | AC2: =Q2*Inputs!B10 | AD2: =W2*Inputs!B10 | AE2: 1 | AF2: =1-AE2 | AG2: Aggressive sales | AH2: =(Q2-'Resource Supply (5yr)'!G10) * AF2 * VALUE(SUBSTITUTE(VLOOKUP(AG2, Inputs!A32:B34, 2, FALSE),, ""))/12 | AI2: =W2 * VALUE(SUBSTITUTE(VLOOKUP(AG2, Inputs!A32:B34, 2, FALSE),, ""))/12 | AJ2: =U2+#REF! | AM2: =AJ2*Inputs!B10 | AO2: =IFERROR(MATCH(B2,XAUconfig!$B$4:$BI$4,0)-1,"")
A3: Mine 2 | B3: Jan '26 | C3: 0 | D3: 150000 | E3: 200000 | F3: =sum(C3:E3) | M3: =(C3*Inputs!B20)+(D3*Inputs!B21)+(E3*Inputs!B22) | N3: Mineral + Bio Estate | O3: =M3-P3 | P3: =M3 * VALUE(SUBSTITUTE(VLOOKUP(N3, TTFconfig!A2:E4, 3, FALSE),, "")) | Q3: =M3 * VALUE(SUBSTITUTE(VLOOKUP(N3, TTFconfig!A2:E4, 4, FALSE),, "")) | R3: =M3*Inputs!$B$27 | S3: =M3*Inputs!$B$26 | T3: =M3*(Inputs!$B$25*50) | U3: =M3*Inputs!B25 | V3: =(M3*Inputs!$B$26) / VALUE(SUBSTITUTE(VLOOKUP(N3, TTFconfig!A2:E4, 5, FALSE),, "")) | W3: =(P3-Q3-R3-S3-T3-Y3) / VALUE(SUBSTITUTE(VLOOKUP(N3, TTFconfig!A2:E4, 5, FALSE),, "")) | Y3: =X3/Inputs!$B$10 | AB3: =P3*Inputs!B10 | AC3: =Q3*Inputs!B10 | AD3: =W3*Inputs!B10 | AE3: 0.5 | AF3: =1-AE3 | AG3: Aggressive sales | AH3: =(Q3-'Resource Supply (5yr)'!G10) * AF3 * VALUE(SUBSTITUTE(VLOOKUP(AG3, Inputs!A32:B34, 2, FALSE),, ""))/12 | AI3: =W3 * VALUE(SUBSTITUTE(VLOOKUP(AG3, Inputs!A32:B34, 2, FALSE),, ""))/12 | AJ3: =U3+#REF! | AO3: =IFERROR(MATCH(B3,XAUconfig!$B$4:$BI$4,0)-1,"")
A4: Mine 3 | B4: Jan '26 | C4: 100000 | D4: 800000 | E4: 100000 | F4: =sum(C4:E4) | M4: =(C4*Inputs!B20)+(D4*Inputs!B21)+(E4*Inputs!B22) | N4: Mineral Estate | O4: =M4-P4 | P4: =M4 * VALUE(SUBSTITUTE(VLOOKUP(N4, TTFconfig!A2:E4, 3, FALSE),, "")) | Q4: =M4 * VALUE(SUBSTITUTE(VLOOKUP(N4, TTFconfig!A2:E4, 4, FALSE),, "")) | R4: =M4*Inputs!$B$27 | S4: =M4*Inputs!$B$26 | T4: =M4*(Inputs!$B$25*50) | U4: =M4*Inputs!B25 | V4: =(M4*Inputs!$B$26) / VALUE(SUBSTITUTE(VLOOKUP(N4, TTFconfig!A2:E4, 5, FALSE),, "")) | W4: =(P4-Q4-R4-S4-T4-Y4) / VALUE(SUBSTITUTE(VLOOKUP(N3, TTFconfig!A2:E4, 5, FALSE),, "")) | Y4: =X4/Inputs!$B$10 | AB4: =P4*Inputs!B10 | AC4: =Q4*Inputs!B10 | AD4: =W4*Inputs!B10 | AE4: 0.5 | AF4: =1-AE4 | AG4: Moderate sales | AH4: =(Q4-'Resource Supply (5yr)'!G10) *AF4 * VALUE(SUBSTITUTE(VLOOKUP(AG4, Inputs!A32:B34, 2, FALSE),, ""))/12 | AI4: =W4 * VALUE(SUBSTITUTE(VLOOKUP(AG4, Inputs!A32:B34, 2, FALSE),, ""))/12 | AJ4: =U4+#REF! | AO4: =IFERROR(MATCH(B4,XAUconfig!$B$4:$BI$4,0)-1,"")
A5: Mine 4 | B5: Apr '26 | C5: 25000 | D5: 250000 | E5: 50000 | F5: =sum(C5:E5) | M5: =(C5*Inputs!B20)+(D5*Inputs!B21)+(E5*Inputs!B22) | N5: Mineral + Bio Estate | O5: =M5-P5 | P5: =M5 * VALUE(SUBSTITUTE(VLOOKUP(N5, TTFconfig!A2:E4, 3, FALSE),, "")) | Q5: =M5 * VALUE(SUBSTITUTE(VLOOKUP(N5, TTFconfig!A2:E4, 4, FALSE),, "")) | R5: =M5*Inputs!$B$27 | S5: =M5*Inputs!$B$26 | T5: =M5*(Inputs!$B$25*50) | U5: =M5*Inputs!B25 | V5: =(M5*Inputs!$B$26) / VALUE(SUBSTITUTE(VLOOKUP(N5, TTFconfig!A2:E4, 5, FALSE),, "")) | W5: =(P5-Q5-R5-S5-T5-Y5) / VALUE(SUBSTITUTE(VLOOKUP(N5, TTFconfig!A2:E4, 5, FALSE),, "")) | Y5: =X5/Inputs!$B$10 | AB5: =P5*Inputs!B10 | AC5: =Q5*Inputs!B10 | AD5: =W5*Inputs!B10 | AE5: 0.5 | AF5: =1-AE5 | AG5: Moderate sales | AH5: =(Q5-'Resource Supply (5yr)'!G10) * AF5 * VALUE(SUBSTITUTE(VLOOKUP(AG5, Inputs!A32:B34, 2, FALSE),, ""))/12 | AI5: =W5 * VALUE(SUBSTITUTE(VLOOKUP(AG5, Inputs!A32:B34, 2, FALSE),, ""))/12 | AJ5: =U5+#REF! | AO5: =IFERROR(MATCH(B5,XAUconfig!$B$4:$BI$4,0)-1,"")
A6: Mine 5 | B6: Jul '26 | C6: 50000 | D6: 490000 | E6: 170000 | F6: =sum(C6:E6) | M6: =(C6*Inputs!B20)+(D6*Inputs!B21)+(E6*Inputs!B22) | N6: Mineral + Bio + Social Estate | O6: =M6-P6 | P6: =M6 * VALUE(SUBSTITUTE(VLOOKUP(N6, TTFconfig!A2:E4, 3, FALSE),, "")) | Q6: =M6 * VALUE(SUBSTITUTE(VLOOKUP(N6, TTFconfig!A2:E4, 4, FALSE),, "")) | R6: =M6*Inputs!$B$27 | S6: =M6*Inputs!$B$26 | T6: =M6*(Inputs!$B$25*50) | U6: =M6*Inputs!B25 | V6: =(M6*Inputs!$B$26) / VALUE(SUBSTITUTE(VLOOKUP(N6, TTFconfig!A2:E4, 5, FALSE),, "")) | W6: =(P6-Q6-R6-S6-T6-Y6) / VALUE(SUBSTITUTE(VLOOKUP(N6, TTFconfig!A2:E4, 5, FALSE),, "")) | Y6: =X6/Inputs!$B$10 | AB6: =P6*Inputs!B10 | AC6: =Q6*Inputs!B9 | AD6: =W6*Inputs!B10 | AE6: 0.5 | AF6: =1-AE6 | AG6: Moderate sales | AH6: =(Q6-'Resource Supply (5yr)'!G10) * AF6 * VALUE(SUBSTITUTE(VLOOKUP(AG6, Inputs!A32:B34, 2, FALSE),, ""))/12 | AI6: =W6 * VALUE(SUBSTITUTE(VLOOKUP(AG6, Inputs!A32:B34, 2, FALSE),, ""))/12 | AJ6: =U6+#REF! | AO6: =IFERROR(MATCH(B6,XAUconfig!$B$4:$BI$4,0)-1,"")
A7: Mine 6 | B7: Dec '26 | C7: 10000 | D7: 50000 | E7: 40000 | F7: =sum(C7:E7) | M7: =(C7*Inputs!B20)+(D7*Inputs!B21)+(E7*Inputs!B22) | N7: Mineral + Bio + Social Estate | O7: =M7-P7 | P7: =M7 * VALUE(SUBSTITUTE(VLOOKUP(N7, TTFconfig!A2:E4, 3, FALSE),, "")) | Q7: =M7 * VALUE(SUBSTITUTE(VLOOKUP(N7, TTFconfig!A2:E4, 4, FALSE),, "")) | R7: =M7*Inputs!$B$27 | S7: =M7*Inputs!$B$26 | T7: =M7*(Inputs!$B$25*50) | U7: =M7*Inputs!B25 | V7: =(M7*Inputs!$B$26) / VALUE(SUBSTITUTE(VLOOKUP(N7, TTFconfig!A2:E4, 5, FALSE),, "")) | W7: =(P7-Q7-R7-S7-T7-Y7) / VALUE(SUBSTITUTE(VLOOKUP(N7, TTFconfig!A2:E4, 5, FALSE),, "")) | Y7: =X7/Inputs!$B$10 | AB7: =P7*Inputs!B10 | AC7: =Q7*Inputs!B10 | AD7: =W7*Inputs!B10 | AE7: 0.5 | AF7: =1-AE7 | AG7: Moderate sales | AH7: =(Q7-'Resource Supply (5yr)'!G10) *AF7* VALUE(SUBSTITUTE(VLOOKUP(AG7, Inputs!A32:B34, 2, FALSE),, ""))/12 | AI7: =W7 * VALUE(SUBSTITUTE(VLOOKUP(AG7, Inputs!A32:B34, 2, FALSE),, ""))/12 | AJ7: =U7+#REF! | AO7: =IFERROR(MATCH(B7,XAUconfig!$B$4:$BI$4,0)-1,"")
A8: Mine 7 | B8: Mar '27 | C8: 25000 | D8: 100000 | E8: 50000 | F8: =sum(C8:E8) | M8: =(C8*Inputs!B20)+(D8*Inputs!B21)+(E8*Inputs!B22) | N8: Mineral Estate | O8: =M8-P8 | P8: =M8 * VALUE(SUBSTITUTE(VLOOKUP(N8, TTFconfig!A2:E4, 3, FALSE),, "")) | Q8: =M8 * VALUE(SUBSTITUTE(VLOOKUP(N8, TTFconfig!A2:E4, 4, FALSE),, "")) | R8: =M8*Inputs!$B$27 | S8: =M8*Inputs!$B$26 | T8: =M8*(Inputs!$B$25*50) | U8: =M8*Inputs!B25 | V8: =(M8*Inputs!$B$26) / VALUE(SUBSTITUTE(VLOOKUP(N8, TTFconfig!A2:E4, 5, FALSE),, "")) | W8: =(P8-Q8-R8-S8-T8-Y8) / VALUE(SUBSTITUTE(VLOOKUP(N8, TTFconfig!A2:E4, 5, FALSE),, "")) | Y8: =X8/Inputs!$B$10 | AB8: =P8*Inputs!B10 | AC8: =Q8*Inputs!B10 | AD8: =W8*Inputs!B10 | AE8: 0.5 | AF8: =1-AE8 | AG8: Moderate sales | AH8: =(Q8-'Resource Supply (5yr)'!G10) *AF8 * VALUE(SUBSTITUTE(VLOOKUP(AG8, Inputs!A32:B34, 2, FALSE),, ""))/12 | AI8: =W8 * VALUE(SUBSTITUTE(VLOOKUP(AG8, Inputs!A32:B34, 2, FALSE),, ""))/12 | AJ8: =U8+#REF! | AO8: =IFERROR(MATCH(B8,XAUconfig!$B$4:$BI$4,0)-1,"")
A9: Mine 8 | B9: Jun '27 | C9: 200000 | D9: 1000000 | E9: 100000 | F9: =sum(C9:E9) | M9: =(C9*Inputs!B20)+(D9*Inputs!B21)+(E9*Inputs!B22) | N9: Mineral Estate | O9: =M9-P9 | P9: =M9 * VALUE(SUBSTITUTE(VLOOKUP(N9, TTFconfig!A2:E4, 3, FALSE),, "")) | Q9: =M9 * VALUE(SUBSTITUTE(VLOOKUP(N9, TTFconfig!A2:E4, 4, FALSE),, "")) | R9: =M9*Inputs!$B$27 | S9: =M9*Inputs!$B$26 | T9: =M9*(Inputs!$B$25*50) | U9: =M9*Inputs!B25 | V9: =(M9*Inputs!$B$26) / VALUE(SUBSTITUTE(VLOOKUP(N9, TTFconfig!A2:E4, 5, FALSE),, "")) | W9: =(P9-Q9-R9-S9-T9-Y9) / VALUE(SUBSTITUTE(VLOOKUP(N9, TTFconfig!A2:E4, 5, FALSE),, "")) | Y9: =X9/Inputs!$B$10 | AB9: =P9*Inputs!B10 | AC9: =Q9*Inputs!B10 | AD9: =W9*Inputs!B10 | AE9: 0.5 | AF9: =1-AE9 | AG9: Moderate sales | AH9: =(Q9-'Resource Supply (5yr)'!G10) * AF9 * VALUE(SUBSTITUTE(VLOOKUP(AG9, Inputs!A32:B34, 2, FALSE),, ""))/12 | AI9: =W9 * VALUE(SUBSTITUTE(VLOOKUP(AG9, Inputs!A32:B34, 2, FALSE),, ""))/12 | AJ9: =U9+#REF! | AO9: =IFERROR(MATCH(B9,XAUconfig!$B$4:$BI$4,0)-1,"")
A10: Mine 9 | B10: Aug '27 | C10: 50000 | D10: 490000 | E10: 170000 | F10: =sum(C10:E10) | M10: =(C10*Inputs!B20)+(D10*Inputs!B21)+(E10*Inputs!B22) | N10: Mineral + Bio Estate | O10: =M10-P10 | P10: =M10 * VALUE(SUBSTITUTE(VLOOKUP(N10, TTFconfig!A2:E4, 3, FALSE),, "")) | Q10: =M10 * VALUE(SUBSTITUTE(VLOOKUP(N10, TTFconfig!A2:E4, 4, FALSE),, "")) | R10: =M10*Inputs!$B$27 | S10: =M10*Inputs!$B$26 | T10: =M10*(Inputs!$B$25*50) | U10: =M10*Inputs!B25 | V10: =(M10*Inputs!$B$26) / VALUE(SUBSTITUTE(VLOOKUP(N10, TTFconfig!A2:E4, 5, FALSE),, "")) | W10: =(P10-Q10-R10-S10-T10-Y10) / VALUE(SUBSTITUTE(VLOOKUP(N10, TTFconfig!A2:E4, 5, FALSE),, "")) | Y10: =X10/Inputs!$B$10 | AB10: =P10*Inputs!B9 | AC10: =Q10*Inputs!B10 | AD10: =W10*Inputs!B10 | AE10: 0.5 | AF10: =1-AE10 | AG10: Moderate sales | AH10: =(Q10-'Resource Supply (5yr)'!G10) * AF10 * VALUE(SUBSTITUTE(VLOOKUP(AG10, Inputs!A32:B34, 2, FALSE),, ""))/12 | AI10: =W10 * VALUE(SUBSTITUTE(VLOOKUP(AG10, Inputs!A32:B34, 2, FALSE),, ""))/12 | AJ10: =U10+#REF! | AO10: =IFERROR(MATCH(B10,XAUconfig!$B$4:$BI$4,0)-1,"")
A11: Mine 10 | B11: Feb '28 | C11: 200000 | D11: 1000000 | E11: 100000 | F11: =sum(C11:E11) | M11: =(C11*Inputs!B20)+(D11*Inputs!B21)+(E11*Inputs!B22) | N11: Mineral Estate | O11: =M11-P11 | P11: =M11 * VALUE(SUBSTITUTE(VLOOKUP(N11, TTFconfig!A2:E4, 3, FALSE),, "")) | Q11: =M11 * VALUE(SUBSTITUTE(VLOOKUP(N11, TTFconfig!A2:E4, 4, FALSE),, "")) | R11: =M11*Inputs!$B$27 | S11: =M11*Inputs!$B$26 | T11: =M11*(Inputs!$B$25*50) | U11: =M11*Inputs!B25 | V11: =(M11*Inputs!$B$26) / VALUE(SUBSTITUTE(VLOOKUP(N11, TTFconfig!A2:E4, 5, FALSE),, "")) | W11: =(P11-Q11-R11-S11-T11-Y11) / VALUE(SUBSTITUTE(VLOOKUP(N11, TTFconfig!A2:E4, 5, FALSE),, "")) | Y11: =X11/Inputs!$B$10 | AB11: =P11*Inputs!B10 | AC11: =Q11*Inputs!B10 | AD11: =W11*Inputs!B10 | AE11: 0.5 | AF11: =1-AE11 | AG11: Conservative sales | AH11: =(Q11-'Resource Supply (5yr)'!G10) * AF11 * VALUE(SUBSTITUTE(VLOOKUP(AG11, Inputs!A32:B34, 2, FALSE),, ""))/12 | AI11: =W11 * VALUE(SUBSTITUTE(VLOOKUP(AG11, Inputs!A32:B34, 2, FALSE),, ""))/12 | AJ11: =U11+#REF! | AO11: =IFERROR(MATCH(B11,XAUconfig!$B$4:$BI$4,0)-1,"")
A12: Mine 11 | B12: May '28 | C12: 50000 | D12: 490000 | E12: 170000 | F12: =sum(C12:E12) | M12: =(C12*Inputs!B20)+(D12*Inputs!B21)+(E12*Inputs!B22) | N12: Mineral + Bio Estate | O12: =M12-P12 | P12: =M12 * VALUE(SUBSTITUTE(VLOOKUP(N12, TTFconfig!A2:E4, 3, FALSE),, "")) | Q12: =M12 * VALUE(SUBSTITUTE(VLOOKUP(N12, TTFconfig!A2:E4, 4, FALSE),, "")) | R12: =M12*Inputs!$B$27 | S12: =M12*Inputs!$B$26 | T12: =M12*(Inputs!$B$25*50) | U12: =M12*Inputs!B25 | V12: =(M12*Inputs!$B$26) / VALUE(SUBSTITUTE(VLOOKUP(N12, TTFconfig!A2:E4, 5, FALSE),, "")) | W12: =(P12-Q12-R12-S12-T12-Y12) / VALUE(SUBSTITUTE(VLOOKUP(N12, TTFconfig!A2:E4, 5, FALSE),, "")) | Y12: =X12/Inputs!$B$10 | AB12: =P12*Inputs!B10 | AC12: =Q12*Inputs!B10 | AD12: =W12*Inputs!B10 | AE12: 0.5 | AF12: =1-AE12 | AG12: Conservative sales | AH12: =(Q12-'Resource Supply (5yr)'!G10) * AF12 * VALUE(SUBSTITUTE(VLOOKUP(AG12, Inputs!A32:B34, 2, FALSE),, ""))/12 | AI12: =W12 * VALUE(SUBSTITUTE(VLOOKUP(AG12, Inputs!A32:B34, 2, FALSE),, ""))/12 | AJ12: =U12+#REF! | AO12: =IFERROR(MATCH(B12,XAUconfig!$B$4:$BI$4,0)-1,"")
A13: Mine 12 | B13: Oct '28 | C13: 50000 | D13: 490000 | E13: 170000 | F13: =sum(C13:E13) | M13: =(C13*Inputs!B20)+(D13*Inputs!B21)+(E13*Inputs!B22) | N13: Mineral + Bio + Social Estate | O13: =M13-P13 | P13: =M13 * VALUE(SUBSTITUTE(VLOOKUP(N13, TTFconfig!A2:E4, 3, FALSE),, "")) | Q13: =M13 * VALUE(SUBSTITUTE(VLOOKUP(N13, TTFconfig!A2:E4, 4, FALSE),, "")) | R13: =M13*Inputs!$B$27 | S13: =M13*Inputs!$B$26 | T13: =M13*(Inputs!$B$25*50) | U13: =M13*Inputs!B25 | V13: =(M13*Inputs!$B$26) / VALUE(SUBSTITUTE(VLOOKUP(N13, TTFconfig!A2:E4, 5, FALSE),, "")) | W13: =(P13-Q13-R13-S13-T13-Y13) / VALUE(SUBSTITUTE(VLOOKUP(N13, TTFconfig!A2:E4, 5, FALSE),, "")) | Y13: =X13/Inputs!$B$10 | AB13: =P13*Inputs!B10 | AC13: =Q13*Inputs!B10 | AD13: =W13*Inputs!B10 | AE13: 0.5 | AF13: =1-AE13 | AG13: Conservative sales | AH13: =(Q13-'Resource Supply (5yr)'!G10) * AF13 * VALUE(SUBSTITUTE(VLOOKUP(AG13, Inputs!A32:B34, 2, FALSE),, ""))/12 | AI13: =W13 * VALUE(SUBSTITUTE(VLOOKUP(AG13, Inputs!A32:B34, 2, FALSE),, ""))/12 | AJ13: =U13+#REF! | AO13: =IFERROR(MATCH(B13,XAUconfig!$B$4:$BI$4,0)-1,"")
A14: Totals | C14: =sum(C2:C13) | D14: =sum(D2:D13) | E14: =sum(E2:E13) | F14: =sum(C14:E14) | M14: =SUM(M2:M13) | P14: =SUM(P2:P13) | U14: =SUM(U2:U13) | W14: =SUM(W2:W13) | AB14: =SUM(AB2:AB13) | AD14: =SUM(AD2:AD13) | AJ14: =SUM(AJ2:AJ13)
G22: 20460 | H22: 115880
G23: 25850 | H23: 113720
G24: =sum(G22:G23) | H24: =sum(H22:H23)
G30: =sum(G27+I27)
L32: 228830 | M32: 145400
L34: =sum(L32,M32)
G37: =56*3300

Sheet Resource Supply (5yr)
A1: Resource Supply (5yr) | B1: =XAUconfig!B4 | C1: =XAUconfig!C4 | D1: =XAUconfig!D4 | E1: =XAUconfig!E4 | F1: =XAUconfig!F4 | G1: =XAUconfig!G4 | H1: =XAUconfig!H4 | I1: =XAUconfig!I4 | ... BI1: =XAUconfig!BI4
A2: Gold Resource Supply
A3: # of mines brought online | B3: =COUNTIF('Mine Inventory'!$AO$2:$AO$13,0) | C3: =COUNTIF('Mine Inventory'!$AO$2:$AO$13,1) | D3: =COUNTIF('Mine Inventory'!$AO$2:$AO$13,2) | E3: =COUNTIF('Mine Inventory'!$AO$2:$AO$13,3) | F3: =COUNTIF('Mine Inventory'!$AO$2:$AO$13,4) | G3: =COUNTIF('Mine Inventory'!$AO$2:$AO$13,5) | H3: =COUNTIF('Mine Inventory'!$AO$2:$AO$13,6) | I3: =COUNTIF('Mine Inventory'!$AO$2:$AO$13,7) | J3: =COUNTIF('Mine Inventory'!$AO$2:$AO$13,8) | K3: =COUNTIF('Mine Inventory'!$AO$2:$AO$13,9) | L3: =COUNTIF('Mine Inventory'!$AO$2:$AO$13,10) | M3: =COUNTIF('Mine Inventory'!$AO$2:$AO$13,11) | N3: =COUNTIF('Mine Inventory'!$AO$2:$AO$13,12) | O3: =COUNTIF('Mine Inventory'!$AO$2:$AO$13,13) | P3: =COUNTIF('Mine Inventory'!$AO$2:$AO$13,14) | Q3: =COUNTIF('Mine Inventory'!$AO$2:$AO$13,15) | R3: =COUNTIF('Mine Inventory'!$AO$2:$AO$13,16) | S3: =COUNTIF('Mine Inventory'!$AO$2:$AO$13,17) | T3: =COUNTIF('Mine Inventory'!$AO$2:$AO$13,18) | U3: =COUNTIF('Mine Inventory'!$AO$2:$AO$13,19) | V3: =COUNTIF('Mine Inventory'!$AO$2:$AO$13,20) | W3: =COUNTIF('Mine Inventory'!$AO$2:$AO$13,21) | X3: =COUNTIF('Mine Inventory'!$AO$2:$AO$13,22) | Y3: =COUNTIF('Mine Inventory'!$AO$2:$AO$13,23) | Z3: =COUNTIF('Mine Inventory'!$AO$2:$AO$13,24) | AA3: =COUNTIF('Mine Inventory'!$AO$2:$AO$13,25) | AB3: =COUNTIF('Mine Inventory'!$AO$2:$AO$13,26) | AC3: =COUNTIF('Mine Inventory'!$AO$2:$AO$13,27) | AD3: =COUNTIF('Mine Inventory'!$AO$2:$AO$13,28) | AE3: =COUNTIF('Mine Inventory'!$AO$2:$AO$13,29) | AF3: =COUNTIF('Mine Inventory'!$AO$2:$AO$13,30) | AG3: =COUNTIF('Mine Inventory'!$AO$2:$AO$13,31) | AH3: =COUNTIF('Mine Inventory'!$AO$2:$AO$13,32) | AI3: =COUNTIF('Mine Inventory'!$AO$2:$AO$13,33) | AJ3: =COUNTIF('Mine Inventory'!$AO$2:$AO$13,34) | AK3: =COUNTIF('Mine Inventory'!$AO$2:$AO$13,35) | AL3: =COUNTIF('Mine Inventory'!$AO$2:$AO$13,36) | AM3: =COUNTIF('Mine Inventory'!$AO$2:$AO$13,37) | AN3: =COUNTIF('Mine Inventory'!$AO$2:$AO$13,38) | AO3: =COUNTIF('Mine Inventory'!$AO$2:$AO$13,39) | AP3: =COUNTIF('Mine Inventory'!$AO$2:$AO$13,40) | AQ3: =COUNTIF('Mine Inventory'!$AO$2:$AO$13,41) | AR3: =COUNTIF('Mine Inventory'!$AO$2:$AO$13,42) | AS3: =COUNTIF('Mine Inventory'!$AO$2:$AO$13,43) | AT3: =COUNTIF('Mine Inventory'!$AO$2:$AO$13,44) | AU3: =COUNTIF('Mine Inventory'!$AO$2:$AO$13,45) | AV3: =COUNTIF('Mine Inventory'!$AO$2:$AO$13,46) | AW3: =COUNTIF('Mine Inventory'!$AO$2:$AO$13,47) | AX3: =COUNTIF('Mine Inventory'!$AO$2:$AO$13,48) | AY3: =COUNTIF('Mine Inventory'!$AO$2:$AO$13,49) | AZ3: =COUNTIF('Mine Inventory'!$AO$2:$AO$13,50) | BA3: =COUNTIF('Mine Inventory'!$AO$2:$AO$13,51) | BB3: =COUNTIF('Mine Inventory'!$AO$2:$AO$13,52) | BC3: =COUNTIF('Mine Inventory'!$AO$2:$AO$13,53) | BD3: =COUNTIF('Mine Inventory'!$AO$2:$AO$13,54) | BE3: =COUNTIF('Mine Inventory'!$AO$2:$AO$13,55) | BF3: =COUNTIF('Mine Inventory'!$AO$2:$AO$13,56) | BG3: =COUNTIF('Mine Inventory'!$AO$2:$AO$13,57) | BH3: =COUNTIF('Mine Inventory'!$AO$2:$AO$13,58) | BI3: =COUNTIF('Mine Inventory'!$AO$2:$AO$13,59)
A4: Registered Resources (oz) | B4: 0 | C4: 0 | D4: 0 | E4: 0 | F4: 0 | G4: 0 | H4: 0 | I4: 0 | J4: ='Mine Inventory'!F2 | K4: 0 | L4: ='Mine Inventory'!F3 | M4: 0 | N4: ='Mine Inventory'!F4 | O4: 0 | P4: 0 | Q4: ='Mine Inventory'!F5 | R4: 0 | S4: 0 | T4: ='Mine Inventory'!F6 | Y4: ='Mine Inventory'!F7 | Z4: 0 | AA4: 0 | AB4: ='Mine Inventory'!F8 | AC4: 0 | AD4: 0 | AE4: ='Mine Inventory'!F9 | AF4: 0 | AG4: ='Mine Inventory'!F10 | AH4: 0 | AI4: 0 | AJ4: 0 | AK4: 0 | AL4: 0 | AM4: ='Mine Inventory'!F11 | AN4: 0 | AO4: 0 | AP4: ='Mine Inventory'!F12 | AQ4: 0 | AR4: 0 | AS4: 0 | AT4: 0 | AU4: ='Mine Inventory'!F13 | AV4: 0 | AW4: 0 | AX4: 0 | AY4: 0 | AZ4: 0 | BA4: 0 | BB4: 0 | BC4: 0 | BD4: 0 | BE4: 0 | BF4: 0 | BG4: 0 | BH4: 0 | BI4: 0
A5: Authorized Resources (oz) | B5: =SUMIF('Mine Inventory'!$AO$2:$AO$13,0,'Mine Inventory'!$M$2:$M$13) | C5: =SUMIF('Mine Inventory'!$AO$2:$AO$13,1,'Mine Inventory'!$M$2:$M$13) | D5: =SUMIF('Mine Inventory'!$AO$2:$AO$13,2,'Mine Inventory'!$M$2:$M$13) | E5: =SUMIF('Mine Inventory'!$AO$2:$AO$13,3,'Mine Inventory'!$M$2:$M$13) | F5: =SUMIF('Mine Inventory'!$AO$2:$AO$13,4,'Mine Inventory'!$M$2:$M$13) | G5: =SUMIF('Mine Inventory'!$AO$2:$AO$13,5,'Mine Inventory'!$M$2:$M$13) | H5: =SUMIF('Mine Inventory'!$AO$2:$AO$13,6,'Mine Inventory'!$M$2:$M$13) | I5: =SUMIF('Mine Inventory'!$AO$2:$AO$13,7,'Mine Inventory'!$M$2:$M$13) | J5: =SUMIF('Mine Inventory'!$AO$2:$AO$13,8,'Mine Inventory'!$M$2:$M$13) | K5: =SUMIF('Mine Inventory'!$AO$2:$AO$13,9,'Mine Inventory'!$M$2:$M$13) | L5: =SUMIF('Mine Inventory'!$AO$2:$AO$13,10,'Mine Inventory'!$M$2:$M$13) | M5: =SUMIF('Mine Inventory'!$AO$2:$AO$13,11,'Mine Inventory'!$M$2:$M$13) | N5: =SUMIF('Mine Inventory'!$AO$2:$AO$13,12,'Mine Inventory'!$M$2:$M$13) | O5: =SUMIF('Mine Inventory'!$AO$2:$AO$13,13,'Mine Inventory'!$M$2:$M$13) | P5: =SUMIF('Mine Inventory'!$AO$2:$AO$13,14,'Mine Inventory'!$M$2:$M$13) | Q5: =SUMIF('Mine Inventory'!$AO$2:$AO$13,15,'Mine Inventory'!$M$2:$M$13) | R5: =SUMIF('Mine Inventory'!$AO$2:$AO$13,16,'Mine Inventory'!$M$2:$M$13) | S5: =SUMIF('Mine Inventory'!$AO$2:$AO$13,17,'Mine Inventory'!$M$2:$M$13) | T5: =SUMIF('Mine Inventory'!$AO$2:$AO$13,18,'Mine Inventory'!$M$2:$M$13) | U5: =SUMIF('Mine Inventory'!$AO$2:$AO$13,19,'Mine Inventory'!$M$2:$M$13) | V5: =SUMIF('Mine Inventory'!$AO$2:$AO$13,20,'Mine Inventory'!$M$2:$M$13) | W5: =SUMIF('Mine Inventory'!$AO$2:$AO$13,21,'Mine Inventory'!$M$2:$M$13) | X5: =SUMIF('Mine Inventory'!$AO$2:$AO$13,22,'Mine Inventory'!$M$2:$M$13) | Y5: =SUMIF('Mine Inventory'!$AO$2:$AO$13,23,'Mine Inventory'!$M$2:$M$13) | Z5: =SUMIF('Mine Inventory'!$AO$2:$AO$13,24,'Mine Inventory'!$M$2:$M$13) | AA5: =SUMIF('Mine Inventory'!$AO$2:$AO$13,25,'Mine Inventory'!$M$2:$M$13) | AB5: =SUMIF('Mine Inventory'!$AO$2:$AO$13,26,'Mine Inventory'!$M$2:$M$13) | AC5: =SUMIF('Mine Inventory'!$AO$2:$AO$13,27,'Mine Inventory'!$M$2:$M$13) | AD5: =SUMIF('Mine Inventory'!$AO$2:$AO$13,28,'Mine Inventory'!$M$2:$M$13) | AE5: =SUMIF('Mine Inventory'!$AO$2:$AO$13,29,'Mine Inventory'!$M$2:$M$13) | AF5: =SUMIF('Mine Inventory'!$AO$2:$AO$13,30,'Mine Inventory'!$M$2:$M$13) | AG5: =SUMIF('Mine Inventory'!$AO$2:$AO$13,31,'Mine Inventory'!$M$2:$M$13) | AH5: =SUMIF('Mine Inventory'!$AO$2:$AO$13,32,'Mine Inventory'!$M$2:$M$13) | AI5: =SUMIF('Mine Inventory'!$AO$2:$AO$13,33,'Mine Inventory'!$M$2:$M$13) | AJ5: =SUMIF('Mine Inventory'!$AO$2:$AO$13,34,'Mine Inventory'!$M$2:$M$13) | AK5: =SUMIF('Mine Inventory'!$AO$2:$AO$13,35,'Mine Inventory'!$M$2:$M$13) | AL5: =SUMIF('Mine Inventory'!$AO$2:$AO$13,36,'Mine Inventory'!$M$2:$M$13) | AM5: =SUMIF('Mine Inventory'!$AO$2:$AO$13,37,'Mine Inventory'!$M$2:$M$13) | AN5: =SUMIF('Mine Inventory'!$AO$2:$AO$13,38,'Mine Inventory'!$M$2:$M$13) | AO5: =SUMIF('Mine Inventory'!$AO$2:$AO$13,39,'Mine Inventory'!$M$2:$M$13) | AP5: =SUMIF('Mine Inventory'!$AO$2:$AO$13,40,'Mine Inventory'!$M$2:$M$13) | AQ5: =SUMIF('Mine Inventory'!$AO$2:$AO$13,41,'Mine Inventory'!$M$2:$M$13) | AR5: =SUMIF('Mine Inventory'!$AO$2:$AO$13,42,'Mine Inventory'!$M$2:$M$13) | AS5: =SUMIF('Mine Inventory'!$AO$2:$AO$13,43,'Mine Inventory'!$M$2:$M$13) | AT5: =SUMIF('Mine Inventory'!$AO$2:$AO$13,44,'Mine Inventory'!$M$2:$M$13) | AU5: =SUMIF('Mine Inventory'!$AO$2:$AO$13,45,'Mine Inventory'!$M$2:$M$13) | AV5: =SUMIF('Mine Inventory'!$AO$2:$AO$13,46,'Mine Inventory'!$M$2:$M$13) | AW5: =SUMIF('Mine Inventory'!$AO$2:$AO$13,47,'Mine Inventory'!$M$2:$M$13) | AX5: =SUMIF('Mine Inventory'!$AO$2:$AO$13,48,'Mine Inventory'!$M$2:$M$13) | AY5: =SUMIF('Mine Inventory'!$AO$2:$AO$13,49,'Mine Inventory'!$M$2:$M$13) | AZ5: =SUMIF('Mine Inventory'!$AO$2:$AO$13,50,'Mine Inventory'!$M$2:$M$13) | BA5: =SUMIF('Mine Inventory'!$AO$2:$AO$13,51,'Mine Inventory'!$M$2:$M$13) | BB5: =SUMIF('Mine Inventory'!$AO$2:$AO$13,52,'Mine Inventory'!$M$2:$M$13) | BC5: =SUMIF('Mine Inventory'!$AO$2:$AO$13,53,'Mine Inventory'!$M$2:$M$13) | BD5: =SUMIF('Mine Inventory'!$AO$2:$AO$13,54,'Mine Inventory'!$M$2:$M$13) | BE5: =SUMIF('Mine Inventory'!$AO$2:$AO$13,55,'Mine Inventory'!$M$2:$M$13) | BF5: =SUMIF('Mine Inventory'!$AO$2:$AO$13,56,'Mine Inventory'!$M$2:$M$13) | BG5: =SUMIF('Mine Inventory'!$AO$2:$AO$13,57,'Mine Inventory'!$M$2:$M$13) | BH5: =SUMIF('Mine Inventory'!$AO$2:$AO$13,58,'Mine Inventory'!$M$2:$M$13) | BI5: =SUMIF('Mine Inventory'!$AO$2:$AO$13,59,'Mine Inventory'!$M$2:$M$13)
A6: Releasable Resources (oz) | B6: 0 | C6: 0 | D6: 0 | E6: 0 | F6: 0 | G6: 0 | H6: 0 | I6: 0 | J6: ='Mine Inventory'!P2 | K6: 0 | L6: ='Mine Inventory'!$P$3 | M6: 0 | N6: ='Mine Inventory'!P4 | O6: 0 | P6: 0 | Q6: ='Mine Inventory'!P5 | R6: 0 | S6: 0 | T6: ='Mine Inventory'!P6 | U6: 0 | V6: 0 | W6: 0 | X6: 0 | Y6: ='Mine Inventory'!P7 | Z6: 0 | AA6: 0 | AB6: ='Mine Inventory'!P8 | AC6: 0 | AD6: 0 | AE6: ='Mine Inventory'!P9 | AF6: 0 | AG6: ='Mine Inventory'!P10 | AH6: 0 | AI6: 0 | AJ6: 0 | AK6: 0 | AL6: 0 | AM6: ='Mine Inventory'!P11 | AN6: 0 | AO6: 0 | AP6: ='Mine Inventory'!P12 | AQ6: 0 | AR6: 0 | AS6: 0 | AT6: 0 | AU6: ='Mine Inventory'!P13 | AV6: 0 | AW6: 0 | AX6: 0 | AY6: 0 | AZ6: 0 | BA6: 0 | BB6: 0 | BC6: 0 | BD6: 0 | BE6: 0 | BF6: 0 | BG6: 0 | BH6: 0 | BI6: 0
A7: Unlocked Resources (oz) | B7: 0 | C7: 0 | D7: 0 | E7: 0 | F7: 0 | G7: 0 | H7: =(H5*'Release Terms'!C2)*'Release Terms'!E2 | I7: 0 | J7: ='Mine Inventory'!Q2 | K7: 0 | L7: ='Mine Inventory'!$Q$3 | M7: 0 | N7: ='Mine Inventory'!Q4 | O7: 0 | P7: 0 | Q7: ='Mine Inventory'!Q5 | R7: 0 | S7: 0 | T7: ='Mine Inventory'!Q6 | U7: 0 | V7: ='Mine Inventory'!W2 | W7: 0 | X7: ='Mine Inventory'!$W$3 | Y7: ='Mine Inventory'!Q7 | Z7: ='Mine Inventory'!$W$4 | AA7: 0 | AB7: ='Mine Inventory'!Q8 | AC7: ='Mine Inventory'!$W$5 | AD7: 0 | AE7: ='Mine Inventory'!Q9 | AF7: ='Mine Inventory'!$W$6 | AG7: ='Mine Inventory'!Q10 | AH7: ='Mine Inventory'!$W$2 | AI7: 0 | AJ7: ='Mine Inventory'!$W$3 | AK7: ='Mine Inventory'!$W$7 | AL7: ='Mine Inventory'!$W$4 | AM7: ='Mine Inventory'!Q11 | AN7: ='Mine Inventory'!$W$8 | AO7: ='Mine Inventory'!$W$5 | AP7: ='Mine Inventory'!Q12 | AQ7: ='Mine Inventory'!$W$9 | AR7: ='Mine Inventory'!$W$6 | AS7: ='Mine Inventory'!$W$10 | AT7: ='Mine Inventory'!$W$2 | AU7: ='Mine Inventory'!Q13 | AV7: ='Mine Inventory'!$W$3 | AW7: ='Mine Inventory'!$W$7 | AX7: ='Mine Inventory'!$W$4 | AY7: ='Mine Inventory'!$W$11 | AZ7: ='Mine Inventory'!$W$8 | BA7: ='Mine Inventory'!$W$5 | BB7: ='Mine Inventory'!$W$12 | BC7: ='Mine Inventory'!$W$9 | BD7: ='Mine Inventory'!$W$6 | BE7: ='Mine Inventory'!$W$10 | BF7: ='Mine Inventory'!$W$2 | BG7: ='Mine Inventory'!$W$13 | BH7: ='Mine Inventory'!$W$3 | BI7: ='Mine Inventory'!$W$7
A8: Unitization Fees (oz) | B8: 0 | C8: 0 | D8: 0 | E8: 0 | F8: 0 | G8: =(G5*Inputs!B25) | H8: =(H5*Inputs!B25)/'Release Terms'!D2 | I8: 0 | J8: =(J5*0.5%) | K8: 0 | L8: =(L5*Inputs!$B$25) | M8: 0 | N8: =(N5*Inputs!$B$25) | O8: 0 | P8: 0 | Q8: ='Mine Inventory'!U5 | R8: 0 | S8: 0 | T8: ='Mine Inventory'!U6 | U8: 0 | V8: 0 | W8: 0 | X8: ='Mine Inventory'!$U$2 | Y8: ='Mine Inventory'!U7 | Z8: ='Mine Inventory'!$U$4 | AA8: 0 | AB8: ='Mine Inventory'!U8 | AC8: ='Mine Inventory'!$U$5 | AD8: 0 | AE8: ='Mine Inventory'!$U$9 | AF8: ='Mine Inventory'!$U$6 | AG8: ='Mine Inventory'!U10 | AH8: 0 | AI8: 0 | AJ8: ='Mine Inventory'!$U$2 | AK8: ='Mine Inventory'!$U$7 | AL8: ='Mine Inventory'!$U$4 | AM8: ='Mine Inventory'!U11 | AN8: ='Mine Inventory'!$U$8 | AO8: ='Mine Inventory'!$U$5 | AP8: ='Mine Inventory'!U12 | AQ8: ='Mine Inventory'!$U$9 | AR8: ='Mine Inventory'!$U$6 | AS8: ='Mine Inventory'!$U$10 | AT8: 0 | AU8: ='Mine Inventory'!U13 | AV8: ='Mine Inventory'!$U$2 | AW8: ='Mine Inventory'!$U$7 | AX8: ='Mine Inventory'!$U$4 | AY8: ='Mine Inventory'!$U$11 | AZ8: ='Mine Inventory'!$U$8 | BA8: ='Mine Inventory'!$U$5 | BB8: ='Mine Inventory'!$U$12 | BC8: ='Mine Inventory'!$U$9 | BD8: ='Mine Inventory'!$U$6 | BE8: ='Mine Inventory'!$U$10 | BF8: 0 | BG8: ='Mine Inventory'!$U$13 | BH8: ='Mine Inventory'!$U$2 | BI8: ='Mine Inventory'!$U$7
A9: Available 1031 units (oz) | B9: 0 | C9: 0 | D9: 0 | E9: 0 | F9: 0 | G9: 0 | H9: 0 | I9: 0 | J9: =(J7)*'Mine Inventory'!AE2 | K9: 0 | L9: =L7*'Mine Inventory'!$AE$3 | M9: 0 | N9: =N7*'Mine Inventory'!AE4 | O9: 0 | P9: 0 | Q9: =Q7*'Mine Inventory'!AE5 | R9: 0 | S9: 0 | T9: =T7*'Mine Inventory'!AE6 | U9: 0 | V9: =V7*'Mine Inventory'!$AE$2 | W9: 0 | X9: =X7*'Mine Inventory'!$AE$3 | Y9: =Y7*'Mine Inventory'!AE7 | Z9: =Z7*'Mine Inventory'!$AE$4 | AB9: =AB7*'Mine Inventory'!AE8 | AC9: =AC7*'Mine Inventory'!$AE$5 | AE9: =AE7*'Mine Inventory'!AE9 | AF9: =AF7*'Mine Inventory'!$AE$6 | AG9: =AG7*'Mine Inventory'!AE10 | AH9: =AH7*'Mine Inventory'!$AE$2 | AJ9: =AJ7*'Mine Inventory'!$AE$3 | AK9: =AK7*'Mine Inventory'!$AE$7 | AL9: =AL7*'Mine Inventory'!$AE$4 | AM9: =AM7*'Mine Inventory'!AE11 | AN9: =AN7*'Mine Inventory'!$AE$8 | AO9: =AO7*'Mine Inventory'!$AE$5 | AP9: =AP7*'Mine Inventory'!AE12 | AQ9: =AQ7*'Mine Inventory'!$AE$9 | AR9: =AR7*'Mine Inventory'!$AE$6 | AS9: =AS7*'Mine Inventory'!$AE$10 | AT9: =AT7*'Mine Inventory'!$AE$2 | AU9: =AU7*'Mine Inventory'!AE13 | AV9: =AV7*'Mine Inventory'!$AE$3 | AW9: =AW7*'Mine Inventory'!$AE$7 | AX9: =AX7*'Mine Inventory'!$AE$4 | AY9: =AY7*'Mine Inventory'!$AE$11 | AZ9: =AZ7*'Mine Inventory'!$AE$8 | BA9: =BA7*'Mine Inventory'!$AE$5 | BB9: =BB7*'Mine Inventory'!$AE$12 | BC9: =BC7*'Mine Inventory'!$AE$9 | BD9: =BD7*'Mine Inventory'!$AE$6 | BE9: =BE7*'Mine Inventory'!$AE$10 | BF9: =BF7*'Mine Inventory'!$AE$2 | BG9: =BG7*'Mine Inventory'!$AE$13 | BH9: =BH7*'Mine Inventory'!$AE$3 | BI9: =BI7*'Mine Inventory'!$AE$7
A10: Admin Fees (oz) | B10: 0 | C10: 0 | D10: 0 | E10: 0 | F10: 0 | G10: =G7*Inputs!B26 | H10: =H7*Inputs!B26 | I10: 0 | J10: =J7*Inputs!$B$26 | K10: =K7*Inputs!$B$26 | L10: =L7*Inputs!$B$26 | M10: =M7*Inputs!$B$26 | N10: =N9*Inputs!$B$26 | O10: =O9*Inputs!$B$26 | P10: =P9*Inputs!$B$26 | Q10: =Q9*Inputs!$B$26 | R10: =R9*Inputs!$B$26 | S10: =S9*Inputs!$B$26 | T10: =T9*Inputs!$B$26 | U10: =U9*Inputs!$B$26 | ... BI10: =BI9*Inputs!$B$26
A11: RGT Liquidity Fee (oz) | B11: 0 | C11: 0 | D11: 0 | E11: 0 | F11: 0 | G11: 0 | H11: 0 | I11: 0 | J11: ='Mine Inventory'!R2 | K11: 0 | L11: ='Mine Inventory'!R3 | M11: 0 | N11: ='Mine Inventory'!R4 | O11: 0 | P11: 0 | Q11: ='Mine Inventory'!R5 | R11: 0 | S11: 0 | T11: ='Mine Inventory'!R6 | U11: 0 | V11: 0 | W11: 0 | X11: 0 | Y11: ='Mine Inventory'!R7 | Z11: 0 | AA11: 0 | AB11: ='Mine Inventory'!R8 | AC11: 0 | AD11: 0 | AE11: ='Mine Inventory'!R9 | AF11: 0 | AG11: ='Mine Inventory'!R10 | AH11: 0 | AI11: 0 | AJ11: 0 | AK11: 0 | AL11: 0 | AM11: ='Mine Inventory'!R11 | AN11: 0 | AO11: 0 | AP11: ='Mine Inventory'!R12 | AQ11: 0 | AR11: 0 | AS11: 0 | AT11: 0 | AU11: ='Mine Inventory'!R13 | AV11: 0 | AW11: 0 | AX11: 0 | AY11: 0 | AZ11: 0 | BA11: 0 | BB11: 0 | BC11: 0 | BD11: 0 | BE11: 0 | BF11: 0 | BG11: 0 | BH11: 0 | BI11: 0
A12: New Allocation to RealGold Treasury (oz) | B12: 0 | C12: 0 | D12: 0 | E12: 0 | F12: 0 | G12: 0 | H12: 0 | I12: 0 | J12: =J11 + (J7*'Mine Inventory'!AF2) | K12: 0 | L12: =L11 + (L7*'Mine Inventory'!AF3) | M12: 0 | N12: =N11 + (N7*'Mine Inventory'!AF4) | O12: 0 | P12: 0 | Q12: =Q11 + (Q7*'Mine Inventory'!AF5) | R12: 0 | S12: 0 | T12: =T11 + (T7*'Mine Inventory'!AF6) | U12: 0 | V12: =V7*'Mine Inventory'!$AF$2 | W12: 0 | X12: =X7*'Mine Inventory'!$AF$3 | Y12: =Y11 + (Y7*'Mine Inventory'!AF7) | Z12: =Z7*'Mine Inventory'!$AF$4 | AB12: =AB11 + (AB7*'Mine Inventory'!AF8) | AC12: =AC7*'Mine Inventory'!$AF$5 | AE12: =AE11 + (AE7*'Mine Inventory'!AF9) | AF12: =AF7*'Mine Inventory'!$AF$6 | AG12: =AG11 + (AG7*'Mine Inventory'!AF10) | AH12: =AH7*'Mine Inventory'!$AF$2 | AI12: 0 | AJ12: =AJ7*'Mine Inventory'!$AF$3 | AK12: =AK7*'Mine Inventory'!$AF$7 | AL12: =AL7*'Mine Inventory'!$AF$4 | AM12: =AM11 + (AM7*'Mine Inventory'!AF11) | AN12: =AN7*'Mine Inventory'!$AF$8 | AO12: =AO7*'Mine Inventory'!$AF$5 | AP12: =AP11 + (AP7*'Mine Inventory'!AF12) | AQ12: =AQ7*'Mine Inventory'!$AF$9 | AR12: =AR7*'Mine Inventory'!$AF$6 | AS12: =AS7*'Mine Inventory'!$AF$10 | AT12: =AT7*'Mine Inventory'!$AF$2 | AU12: =AU11 + (AU7*'Mine Inventory'!AF13) | AV12: =AV7*'Mine Inventory'!$AF$3 | AW12: =AW7*'Mine Inventory'!$AF$7 | AX12: =AX7*'Mine Inventory'!$AF$4 | AY12: =AY7*'Mine Inventory'!$AF$10 | AZ12: =AZ7*'Mine Inventory'!$AF$8 | BA12: =BA7*'Mine Inventory'!$AF$5 | BB12: =BB7*'Mine Inventory'!$AF$12 | BC12: =BC7*'Mine Inventory'!$AF$9 | BD12: =BD7*'Mine Inventory'!$AF$6 | BE12: =BE7*'Mine Inventory'!$AF$10 | BF12: =BF7*'Mine Inventory'!$AF$2 | BG12: =BG7*'Mine Inventory'!$AF$13 | BH12: =BH7*'Mine Inventory'!$AF$3 | BI12: =BI7*'Mine Inventory'!$AF$7
A13: RealGold Token Minting Fees (oz) | B13: 0 | C13: 0 | D13: 0 | E13: 0 | F13: 0 | G13: 0 | H13: 0 | I13: 0 | J13: =J12*Inputs!$B$26 | K13: =K12*Inputs!$B$26 | L13: =L12*Inputs!$B$26 | M13: =M12*Inputs!$B$26 | N13: =N12*Inputs!$B$26 | O13: =O12*Inputs!$B$26 | P13: =P12*Inputs!$B$26 | Q13: =Q12*Inputs!$B$26 | ... BI13: =BI12*Inputs!$B$26
A14: Total Admin & Unit Fee Rev RAF (oz) | B14: 0 | C14: 0 | D14: 0 | E14: 0 | F14: 0 | G14: =sum(G8:G12) | H14: =sum(H8:H12) | I14: 0 | J14: =sum(J8+J10) | K14: 0 | L14: =sum(L8+L10) | M14: =sum(M8+M10) | N14: =sum(N8+N10) | O14: =sum(O8+O10) | P14: =sum(P8+P10) | Q14: =sum(Q8+Q10) | R14: =sum(R8+R10) | S14: =sum(S8+S10) | ... V14: =sum(V8+V10) | W14: 0 | X14: =sum(X8+X10) | Y14: =sum(Y8+Y10) | Z14: =sum(Z8+Z10) | AA14: =sum(AA8+AA10) | AB14: =sum(AB8+AB10) | AC14: =sum(AC8+AC10) | AD14: =sum(AD8+AD10) | AE14: =sum(AE8+AE10) | ... BI14: =sum(BI8+BI10)
A15: Allocation to 1031 by Trusts (oz) | B15: 0 | C15: 0 | D15: 0 | E15: 0 | F15: 0 | G15: =(G7-G10)*'Mine Inventory'!AE2 | H15: =(H7-H10)*'Mine Inventory'!AF2 | I15: 0 | J15: =(J9-J10) | K15: =(K9-K10) | L15: =(L9-L10) | M15: =(M9-M10) | N15: =(N9-N10) | O15: =(O9-O10) | P15: =(P9-P10) | Q15: =(Q9-Q10) | ... BI15: =(BI9-BI10)
A16: Allocation to RealGold Treasury by Trusts (oz) | B16: 0 | C16: 0 | D16: 0 | E16: 0 | F16: 0 | G16: 0 | H16: 0 | I16: 0 | J16: =J12-J13 | K16: =K12-K13 | L16: =L12-L13 | M16: =M12-M13 | N16: =N12-N13 | O16: =O12-O13 | P16: =P12-P13 | Q16: =Q12-Q13 | ... BI16: =BI12-BI13
A18: Registered Resources ($) | B18: 0 | C18: 0 | D18: 0 | E18: 0 | F18: 0 | G18: =G4*XAUconfig!G3 | H18: =H4*XAUconfig!H3 | I18: =I4*XAUconfig!N3 | J18: =J4*XAUconfig!J3 | K18: =K4*XAUconfig!K3 | L18: =L4*XAUconfig!L3 | M18: 0 | N18: =N4*XAUconfig!N3 | O18: 0 | P18: 0 | Q18: =Q4*XAUconfig!Q3 | R18: 0 | S18: 0 | T18: =T4*XAUconfig!T3 | U18: 0 | V18: 0 | W18: 0 | X18: =X4*XAUconfig!Y3 | Y18: =Y4*XAUconfig!Y3 | Z18: 0 | AA18: 0 | AB18: =AB4*XAUconfig!AB3 | AC18: 0 | AD18: 0 | AE18: 0 | AF18: 0 | AG18: =AG4*XAUconfig!AG3 | AH18: 0 | AI18: 0 | AJ18: =AJ4*XAUconfig!AJ3 | AK18: 0 | AL18: 0 | AM18: =AM4*XAUconfig!AM3 | AN18: 0 | AO18: 0 | AP18: =AP4*XAUconfig!AP3 | AQ18: 0 | AR18: 0 | AS18: 0 | AT18: 0 | AU18: =AU4*XAUconfig!AU3 | AV18: 0 | AW18: 0 | AX18: 0 | AY18: 0 | AZ18: 0 | BA18: 0 | BB18: 0 | BC18: 0 | BD18: 0 | BE18: 0 | BF18: 0 | BG18: 0 | BH18: 0 | BI18: 0
A19: Authorized Resources ($) | B19: 0 | C19: 0 | D19: 0 | E19: 0 | F19: 0 | G19: =G5*XAUconfig!G3 | H19: =H5*XAUconfig!H3 | I19: =I5*XAUconfig!N3 | J19: =J5*XAUconfig!J3 | K19: =K5*XAUconfig!K3 | L19: =L5*XAUconfig!L3 | M19: 0 | N19: =N5*XAUconfig!N3 | O19: 0 | P19: 0 | Q19: =Q5*XAUconfig!Q3 | R19: 0 | S19: 0 | T19: =T5*XAUconfig!T3 | U19: 0 | V19: 0 | W19: 0 | X19: =X5*XAUconfig!X3 | Y19: =Y5*XAUconfig!Y3 | Z19: =Z5*Inputs!B9 | AA19: 0 | AB19: =AB5*XAUconfig!AB3 | AC19: =AC5*Inputs!B9 | AD19: 0 | AE19: =AE5*Inputs!B9 | AF19: =AF5*Inputs!B9 | AG19: =AG5*XAUconfig!AG3 | AH19: =AH5*Inputs!B9 | AI19: =AI5*Inputs!B9 | AJ19: =AJ5*XAUconfig!AJ3 | AK19: =AK5*Inputs!B9 | AL19: =AL5*Inputs!B9 | AM19: =AM5*XAUconfig!AM3 | AN19: =AN5*Inputs!B9 | AO19: =AO5*Inputs!B9 | AP19: =AP5*XAUconfig!AP3 | AQ19: =AQ5*Inputs!B9 | AR19: =AR5*Inputs!B9 | AS19: =AS5*Inputs!B9 | AT19: =AT5*Inputs!B9 | AU19: =AU5*XAUconfig!AU3 | AV19: =AV5*Inputs!B9 | AW19: =AW5*Inputs!B9 | AX19: =AX5*Inputs!B9 | AY19: =AY5*Inputs!B9 | AZ19: =AZ5*Inputs!B9 | BA19: =BA5*Inputs!B9 | BB19: =BB5*Inputs!B9 | BC19: =BC5*Inputs!B9 | BD19: =BD5*Inputs!B9 | BE19: =BE5*Inputs!B9 | BF19: =BF5*Inputs!B9 | BG19: =BG5*Inputs!B9 | BH19: =BH5*Inputs!B9 | BI19: =BI5*Inputs!B9
A20: Releasable Resources ($) | B20: 0 | C20: 0 | D20: 0 | E20: 0 | F20: 0 | G20: =G6*XAUconfig!G3 | H20: =H6*XAUconfig!H3 | I20: =I6*Inputs!B9 | J20: =J6*XAUconfig!J3 | K20: =K6*Inputs!B9 | L20: =L6*XAUconfig!L3 | M20: =M6*Inputs!B9 | N20: =N6*XAUconfig!N3 | O20: =O6*Inputs!B9 | P20: =P6*Inputs!B9 | Q20: =Q6*XAUconfig!Q3 | R20: =R6*Inputs!B9 | S20: =S6*XAUconfig!S3 | T20: =T6*XAUconfig!T3 | U20: =U6*Inputs!B9 | V20: =V6*XAUconfig!V3 | W20: =W6*Inputs!B9 | X20: =X6*XAUconfig!X3 | Y20: =Y6*XAUconfig!Y3 | Z20: =Z6*Inputs!B9 | AA20: =AA6*Inputs!B9 | AB20: =AB6*XAUconfig!AB3 | AC20: =AC6*Inputs!B9 | AD20: =AD6*Inputs!B9 | AE20: =AE6*Inputs!B9 | AF20: 0 | AG20: =AG6*XAUconfig!AG3 | AH20: =AH6*Inputs!B9 | AI20: =AI6*Inputs!B9 | AJ20: =AJ6*XAUconfig!AJ3 | AK20: =AK6*Inputs!B9 | AL20: =AL6*Inputs!B9 | AM20: =AM6*XAUconfig!AM3 | AN20: =AN6*Inputs!B9 | AO20: =AO6*Inputs!B9 | AP20: =AP6*XAUconfig!AP3 | AQ20: =AQ6*Inputs!B9 | AR20: =AR6*Inputs!B9 | AS20: =AS6*Inputs!B9 | AT20: =AT6*Inputs!B9 | AU20: =AU6*XAUconfig!AU3 | AV20: =AV6*Inputs!B9 | AW20: =AW6*Inputs!B9 | AX20: =AX6*Inputs!B9 | AY20: =AY6*Inputs!B9 | AZ20: =AZ6*Inputs!B9 | BA20: =BA6*Inputs!B9 | BB20: =BB6*Inputs!B9 | BC20: =BC6*Inputs!B9 | BD20: =BD6*Inputs!B9 | BE20: =BE6*Inputs!B9 | BF20: =BF6*Inputs!B9 | BG20: =BG6*Inputs!B9 | BH20: =BH6*Inputs!B9 | BI20: =BI6*Inputs!B9
A21: Unlocked Resources ($) | B21: 0 | C21: 0 | D21: 0 | E21: 0 | F21: 0 | G21: =G7*XAUconfig!G3 | H21: =H7*XAUconfig!H3 | I21: =I7*XAUconfig!N3 | J21: =J7*XAUconfig!J3 | K21: =K7*XAUconfig!K3 | L21: =L7*XAUconfig!L3 | M21: 0 | N21: =N7*XAUconfig!N3 | O21: 0 | P21: 0 | Q21: =Q7*XAUconfig!Q3 | R21: 0 | S21: =S7*XAUconfig!S3 | T21: =T7*XAUconfig!T3 | U21: 0 | V21: =V7*XAUconfig!V3 | W21: =W7*XAUconfig!W3 | X21: =X7*XAUconfig!X3 | Y21: =Y7*XAUconfig!Y3 | Z21: =Z7*XAUconfig!Z3 | AA21: 0 | AB21: =AB7*XAUconfig!AB3 | AC21: =AC7*XAUconfig!AC3 | AD21: 0 | AE21: =AE7*XAUconfig!AE3 | AF21: =AF7*XAUconfig!AF3 | AG21: =AG7*XAUconfig!AG3 | AH21: =AH7*XAUconfig!AH3 | AI21: =AI7*Inputs!B9 | AJ21: =AJ7*XAUconfig!AJ3 | AK21: =AK7*XAUconfig!AK3 | AL21: =AL7*XAUconfig!AL3 | AM21: =AM7*XAUconfig!AM3 | AN21: =AN7*XAUconfig!AN3 | AO21: =AO7*XAUconfig!AO3 | AP21: =AP7*XAUconfig!AP3 | AQ21: =AQ7*XAUconfig!AQ3 | ... BI21: =BI7*XAUconfig!BI3
A22: Registration Fees ($) | B22: 0 | C22: 0 | D22: 0 | E22: 0 | F22: 0 | G22: =G8*XAUconfig!G3 | H22: =H8*XAUconfig!H3 | I22: =I8*XAUconfig!N3 | J22: =J8*XAUconfig!J3 | K22: =K8*XAUconfig!K3 | L22: =L8*XAUconfig!L3 | M22: 0 | N22: =N8*XAUconfig!N3 | O22: 0 | P22: 0 | Q22: =Q8*XAUconfig!Q3 | R22: 0 | S22: =S8*XAUconfig!S3 | T22: =T8*XAUconfig!T3 | U22: 0 | V22: =V8*XAUconfig!V3 | W22: 0 | X22: =X8*XAUconfig!X3 | Y22: =Y8*XAUconfig!Y3 | Z22: =Z8*XAUconfig!Z3 | AA22: 0 | AB22: =AB8*XAUconfig!AB3 | AC22: =AC8*XAUconfig!AC3 | AD22: 0 | AE22: =AE8*XAUconfig!AE3 | AF22: =AF8*XAUconfig!AF3 | AG22: =AG8*XAUconfig!AG3 | AH22: =AH8*XAUconfig!AH3 | AI22: =AI8*Inputs!B9 | AJ22: =AJ8*XAUconfig!AJ3 | AK22: =AK8*XAUconfig!AK3 | AL22: =AL8*XAUconfig!AL3 | AM22: =AM8*XAUconfig!AM3 | AN22: =AN8*XAUconfig!AN3 | AO22: =AO8*XAUconfig!AO3 | AP22: =AP8*XAUconfig!AP3 | AQ22: =AQ8*XAUconfig!AQ3 | ... BI22: =BI8*XAUconfig!BI3
A23: Unitization Fees ($) | B23: 0 | C23: 0 | D23: 0 | E23: 0 | F23: 0 | G23: =G10*XAUconfig!G3 | H23: =H10*XAUconfig!H3 | I23: =I10*XAUconfig!I3 | J23: =J10*XAUconfig!J3 | K23: =K10*XAUconfig!K3 | L23: =L10*XAUconfig!L3 | M23: 0 | N23: =N10*XAUconfig!N3 | O23: 0 | P23: 0 | Q23: =Q10*XAUconfig!Q3 | R23: 0 | S23: =S10*XAUconfig!S3 | T23: =T10*Inputs!B9 | U23: 0 | V23: =V10*XAUconfig!V3 | W23: 0 | X23: =X10*XAUconfig!X3 | Y23: =Y10*XAUconfig!Y3 | Z23: =Z10*XAUconfig!Z3 | AA23: 0 | AB23: =AB10*XAUconfig!AB3 | AC23: =AC10*XAUconfig!AC3 | AD23: 0 | AE23: =AE10*XAUconfig!AE3 | AF23: =AF10*XAUconfig!AF3 | AG23: =AG10*XAUconfig!AG3 | AH23: =AH10*XAUconfig!AH3 | AI23: =AI10*Inputs!B9 | AJ23: =AJ10*XAUconfig!AJ3 | AK23: =AK10*XAUconfig!AK3 | AL23: =AL10*XAUconfig!AL3 | AM23: =AM10*XAUconfig!AM3 | AN23: =AN10*XAUconfig!AN3 | AO23: =AO10*XAUconfig!AO3 | AP23: =AP10*XAUconfig!AP3 | AQ23: =AQ10*XAUconfig!AQ3 | ... BI23: =BI10*XAUconfig!BI3
A24: RealGold Token Minting Fees ($) | B24: 0 | C24: 0 | D24: 0 | E24: 0 | F24: 0 | G24: 0 | H24: 0 | I24: 0 | J24: =J13*XAUconfig!J3 | K24: =K13*XAUconfig!K3 | L24: =L13*XAUconfig!L3 | M24: =M13*XAUconfig!M3 | N24: =N13*XAUconfig!N3 | O24: =O13*XAUconfig!O3 | P24: =P13*XAUconfig!P3 | Q24: =Q13*XAUconfig!Q3 | ... BI24: =BI13*XAUconfig!BI3
A25: Total Reg & Unit Fee Rev ($) | B25: 0 | C25: 0 | D25: 0 | E25: 0 | F25: 0 | G25: =G22+G23 | H25: =H22+H23 | I25: =I22+I23 | J25: =J22+J23 | K25: =K22+K23 | L25: =L22+L23 | M25: 0 | N25: =N22+N23 | O25: 0 | P25: 0 | Q25: =Q22+Q23 | R25: 0 | S25: =S22+S23 | T25: =T22+T23 | U25: 0 | V25: =V22+V23 | W25: 0 | X25: =X22+X23 | Y25: =Y22+Y23 | Z25: =Z22+Z23 | AA25: 0 | AB25: =AB22+AB23 | AC25: =AC22+AC23 | AD25: =AD22+AD23 | AE25: =AE22+AE23 | AF25: =AF22+AF23 | AG25: =AG22+AG23 | AH25: =AH22+AH23 | AI25: =AI22+AI23 | ... BI25: =BI22+BI23
A26: Allocation to 1031 ($) | B26: 0 | C26: 0 | D26: 0 | E26: 0 | F26: 0 | G26: =G15*XAUconfig!G3 | H26: =H15*XAUconfig!H3 | I26: =I15*XAUconfig!I3 | J26: =J15*XAUconfig!J3 | K26: =K15*XAUconfig!K3 | L26: =L15*XAUconfig!L3 | M26: 0 | N26: =N15*XAUconfig!N3 | O26: 0 | P26: 0 | Q26: =Q15*XAUconfig!Q3 | R26: 0 | S26: =S15*XAUconfig!S3 | T26: =T15*XAUconfig!T3 | U26: 0 | V26: =V15*XAUconfig!V3 | W26: 0 | X26: =X15*XAUconfig!X3 | Y26: =Y15*XAUconfig!Y3 | Z26: =Z15*XAUconfig!Z3 | AA26: 0 | AB26: =AB15*XAUconfig!AB3 | AC26: =AC15*XAUconfig!AC3 | AD26: 0 | AE26: =AE15*XAUconfig!AE3 | AF26: =AF15*XAUconfig!AF3 | AG26: =AG15*XAUconfig!AG3 | AH26: =AH15*XAUconfig!AH3 | AI26: =AI15*Inputs!B9 | AJ26: =AJ15*XAUconfig!AJ3 | AK26: =AK15*XAUconfig!AK3 | AL26: =AL15*XAUconfig!AL3 | AM26: =AM15*XAUconfig!AM3 | AN26: =AN15*XAUconfig!AN3 | AO26: =AO15*XAUconfig!AO3 | AP26: =AP15*XAUconfig!AP3 | AQ26: =AQ15*XAUconfig!AQ3 | ... BI26: =BI15*XAUconfig!BI3
A27: Allocation to RealGold Treasury ($) | B27: 0 | C27: 0 | D27: 0 | E27: 0 | F27: 0 | G27: =G16*XAUconfig!G3 | H27: =H16*XAUconfig!H3 | I27: =I16*XAUconfig!I3 | J27: =J16*XAUconfig!J3 | K27: =K16*XAUconfig!K3 | L27: =L16*XAUconfig!L3 | M27: =M16*XAUconfig!M3 | N27: =N16*XAUconfig!N3 | O27: 0 | P27: 0 | Q27: =Q16*XAUconfig!Q3 | R27: 0 | S27: =S16*XAUconfig!S3 | T27: =T16*XAUconfig!T3 | U27: 0 | V27: =V16*XAUconfig!V3 | W27: 0 | X27: =X16*XAUconfig!X3 | Y27: =Y16*XAUconfig!Y3 | Z27: =Z16*XAUconfig!Z3 | AA27: 0 | AB27: =AB16*XAUconfig!AB3 | AC27: =AC16*XAUconfig!AC3 | AD27: 0 | AE27: =AE16*XAUconfig!AE3 | AF27: =AF16*XAUconfig!AF3 | AG27: =AG16*XAUconfig!AG3 | AH27: =AH16*XAUconfig!AH3 | AI27: =AI16*Inputs!B9 | AJ27: =AJ16*XAUconfig!AJ3 | AK27: =AK16*XAUconfig!AK3 | AL27: =AL16*XAUconfig!AL3 | AM27: =AM16*XAUconfig!AM3 | AN27: =AN16*XAUconfig!AN3 | AO27: =AO16*XAUconfig!AO3 | AP27: =AP16*XAUconfig!AP3 | AQ27: =AQ16*XAUconfig!AQ3 | ... BI27: =BI16*XAUconfig!BI3
A29: Resource Supply Cumulative Totals
A30: Cumulative Registered Resources (oz) | B30: 0 | C30: 0 | D30: 0 | E30: 0 | F30: 0 | G30: =sum(B4:G4) | H30: =sum(B4:H4) | I30: =sum(C4:I4) | J30: =sum(D4:J4) | K30: =sum(E4:K4) | L30: =sum(F4:L4) | M30: =sum(B4:M4) | N30: =sum(B4:N4) | O30: =sum(B4:O4) | P30: =sum(B4:P4) | Q30: =sum(B4:Q4) | R30: =sum(B4:R4) | S30: =sum(B4:S4) | T30: =sum(B4:T4) | U30: =sum(B4:U4) | V30: =sum(B4:V4) | W30: =sum(B4:W4) | X30: =sum(B4:X4) | Y30: =sum(B4:Y4) | Z30: =sum(B4:Z4) | AA30: =sum(B4:AA4) | AB30: =sum(B4:AB4) | AC30: =sum(B4:AC4) | AD30: =sum(B4:AD4) | AE30: =sum(B4:AE4) | AF30: =sum(B4:AF4) | AG30: =sum(B4:AG4) | AH30: =sum(B4:AH4) | AI30: =sum(B4:AI4) | AJ30: =sum(B4:AJ4) | AK30: =sum(B4:AK4) | AL30: =sum(B4:AL4) | AM30: =sum(B4:AM4) | AN30: =sum(B4:AN4) | AO30: =sum(B4:AO4) | AP30: =sum(B4:AP4) | AQ30: =sum(B4:AQ4) | AR30: =sum(B4:AR4) | AS30: =sum(B4:AS4) | AT30: =sum(B4:AT4) | AU30: =sum(B4:AU4) | AV30: =sum(B4:AV4) | AW30: =sum(B4:AW4) | AX30: =sum(B4:AX4) | AY30: =sum(B4:AY4) | AZ30: =sum(B4:AZ4) | BA30: =sum(B4:BA4) | BB30: =sum(B4:BB4) | BC30: =sum(B4:BC4) | BD30: =sum(B4:BD4) | BE30: =sum(B4:BE4) | BF30: =sum(B4:BF4) | BG30: =sum(B4:BG4) | BH30: =sum(B4:BH4) | BI30: =sum(B4:BI4)
A31: Cumulative Authorized Resources (oz) | B31: 0 | C31: 0 | D31: 0 | E31: 0 | F31: 0 | G31: =sum(B5:G5) | H31: =sum(B5:H5) | I31: =sum(B5:I5) | J31: =sum(B5:J5) | K31: =sum(B5:K5) | L31: =sum(B5:L5) | M31: =sum(B5:M5) | N31: =sum(M31,N5) | O31: =sum(N31,O5) | P31: =sum(O31,P5) | Q31: =sum(P31,Q5) | R31: =sum(Q31,R5) | S31: =sum(R31,S5) | T31: =sum(S31,T5) | U31: =sum(T31,U5) | ... BI31: =sum(BH31,BI5)
A32: Cumulative Releaseable Resources (oz) | B32: 0 | C32: 0 | D32: 0 | E32: 0 | F32: 0 | G32: =sum(B6:G6)/2 | H32: =sum(B6:H6)/2 | I32: =sum(B6:I6)/2 | J32: =sum(B6:J6) | K32: =sum(B6:K6) | L32: =sum(B6:L6) | M32: =sum(B6:M6) | N32: =sum(B6:N6) | O32: =sum(B6:O6) | P32: =sum(B6:P6) | Q32: =sum(B6:Q6) | R32: =sum(B6:R6) | S32: =sum(B6:S6) | T32: =sum(B6:T6) | U32: =sum(B6:U6) | V32: =sum(B6:V6) | W32: =sum(B6:W6) | X32: =sum(B6:X6) | Y32: =sum(B6:Y6) | Z32: =sum(B6:Z6) | AA32: =sum(B6:AA6) | AB32: =sum(B6:AB6) | AC32: =sum(B6:AC6) | AD32: =sum(B6:AD6) | AE32: =sum(B6:AE6) | AF32: =sum(B6:AF6) | AG32: =sum(B6:AG6) | AH32: =sum(B6:AH6) | AI32: =sum(B6:AI6) | AJ32: =sum(B6:AJ6) | AK32: =sum(B6:AK6) | AL32: =sum(B6:AL6) | AM32: =sum(B6:AM6) | AN32: =sum(B6:AN6) | AO32: =sum(B6:AO6) | AP32: =sum(B6:AP6) | AQ32: =sum(B6:AQ6) | AR32: =sum(B6:AR6) | AS32: =sum(B6:AS6) | AT32: =sum(B6:AT6) | AU32: =sum(B6:AU6) | AV32: =sum(B6:AV6) | AW32: =sum(B6:AW6) | AX32: =sum(B6:AX6) | AY32: =sum(B6:AY6) | AZ32: =sum(B6:AZ6) | BA32: =sum(B6:BA6) | BB32: =sum(B6:BB6) | BC32: =sum(B6:BC6) | BD32: =sum(B6:BD6) | BE32: =sum(B6:BE6) | BF32: =sum(B6:BF6) | BG32: =sum(B6:BG6) | BH32: =sum(B6:BH6) | BI32: =sum(B6:BI6)
A33: Cumulative Unlocked to Markets (oz) | B33: 0 | C33: 0 | D33: 0 | E33: 0 | F33: 0 | G33: =sum(G7:G8)/2 | H33: =sum(G7:H8)/2 | I33: =sum(G7:I8)/2 | J33: =sum(G7:J8)/2 | K33: =sum(G7:K8) | L33: =sum(G7:L8) | M33: =sum(G7:M8) | N33: =sum(G7:N8) | O33: =sum(G7:O8) | P33: =sum(G7:P8) | Q33: =sum(G7:Q8) | R33: =sum(G7:R8) | S33: =sum(G7:S8) | T33: =sum(B7:T8) | U33: =sum(G7:U8) | V33: =sum(G7:V8) | W33: =sum(G7:W8) | X33: =sum(G7:X8) | Y33: =sum(G7:Y8) | Z33: =sum(G7:Z8) | AA33: =sum(G7:AA8) | AB33: =sum(G7:AB8) | AC33: =sum(G7:AC8) | AD33: =sum(G7:AD8) | AE33: =sum(G7:AE8) | AF33: =sum(G7:AF8) | AG33: =sum(G7:AG8) | AH33: =sum(G7:AH8) | AI33: =sum(G7:AI8) | AJ33: =sum(G7:AJ8) | AK33: =sum(G7:AK8) | AL33: =sum(G7:AL8) | AM33: =sum(G7:AM8) | AN33: =sum(G7:AN8) | AO33: =sum(G7:AO8) | AP33: =sum(G7:AP8) | AQ33: =sum(G7:AQ8) | AR33: =sum(G7:AR8) | AS33: =sum(G7:AS8) | AT33: =sum(G7:AT8) | AU33: =sum(G7:AU8) | AV33: =sum(G7:AV8) | AW33: =sum(G7:AW8) | AX33: =sum(G7:AX8) | AY33: =sum(G7:AY8) | AZ33: =sum(G7:AZ8) | BA33: =sum(G7:BA8) | BB33: =sum(G7:BB8) | BC33: =sum(G7:BC8) | BD33: =sum(G7:BD8) | BE33: =sum(G7:BE8) | BF33: =sum(G7:BF8) | BG33: =sum(G7:BG8) | BH33: =sum(G7:BH8) | BI33: =sum(G7:BI8)
A34: Cumulative Allocation to RealGold Treasury (oz) | B34: 0 | C34: 0 | D34: 0 | E34: 0 | F34: 0 | G34: =sum(B16:G16) | H34: =sum(B16:H16) | I34: =sum(B16:I16) | J34: =sum(B16:J16) | K34: =sum(B16:K16) | L34: =sum(B16:L16) | M34: =sum(B16:M16) | N34: =sum(B16:N16) | O34: =sum(B16:O16) | P34: =sum(B16:P16) | Q34: =sum(B16:Q16) | R34: =sum(B16:R16) | S34: =sum(B16:S16) | T34: =sum(B16:T16) | U34: =sum(B16:U16) | V34: =sum(B16:V16) | W34: =sum(B16:W16) | X34: =sum(B16:X16) | Y34: =sum(B16:Y16) | Z34: =sum(B16:Z16) | AA34: =sum(B16:AA16) | AB34: =sum(B16:AB16) | AC34: =sum(B16:AC16) | AD34: =sum(B16:AD16) | AE34: =sum(B16:AE16) | AF34: =sum(B16:AF16) | AG34: =sum(B16:AG16) | AH34: =sum(B16:AH16) | AI34: =sum(B16:AI16) | AJ34: =sum(B16:AJ16) | AK34: =sum(B16:AK16) | AL34: =sum(B16:AL16) | AM34: =sum(B16:AM16) | AN34: =sum(B16:AN16) | AO34: =sum(B16:AO16) | AP34: =sum(B16:AP16) | AQ34: =sum(B16:AQ16) | AR34: =sum(B16:AR16) | AS34: =sum(B16:AS16) | AT34: =sum(B16:AT16) | AU34: =sum(B16:AU16) | AV34: =sum(B16:AV16) | AW34: =sum(B16:AW16) | AX34: =sum(B16:AX16) | AY34: =sum(B16:AY16) | AZ34: =sum(B16:AZ16) | BA34: =sum(B16:BA16) | BB34: =sum(B16:BB16) | BC34: =sum(B16:BC16) | BD34: =sum(B16:BD16) | BE34: =sum(B16:BE16) | BF34: =sum(B16:BF16) | BG34: =sum(B16:BG16) | BH34: =sum(B16:BH16) | BI34: =sum(B16:BI16)
A36: Cumulative Registered Resources ($) | B36: 0 | C36: 0 | D36: 0 | E36: 0 | F36: 0 | G36: =G18 | H36: =sum(B18:H18) | I36: =sum(B18:I18) | J36: =sum(B18:J18) | K36: =sum(B18:K18) | L36: =sum(B18:L18) | M36: =sum(B18:M18) | N36: =sum(B18:N18) | O36: =sum(B18:O18) | P36: =sum(B18:P18) | Q36: =sum(B18:Q18) | R36: =sum(B18:R18) | S36: =sum(B18:S18) | T36: =sum(B18:T18) | U36: =sum(B18:U18) | V36: =sum(B18:V18) | W36: =sum(B18:W18) | X36: =sum(B18:X18) | Y36: =sum(B18:Y18) | Z36: =sum(B18:Z18) | AA36: =sum(B18:AA18) | AB36: =sum(B18:AB18) | AC36: =sum(B18:AC18) | AD36: =sum(B18:AD18) | AE36: =sum(B18:AE18) | AF36: =sum(B18:AF18) | AG36: =sum(B18:AG18) | AH36: =sum(B18:AH18) | AI36: =sum(B18:AI18) | AJ36: =sum(B18:AJ18) | AK36: =sum(B18:AK18) | AL36: =sum(B18:AL18) | AM36: =sum(B18:AM18) | AN36: =sum(B18:AN18) | AO36: =sum(B18:AO18) | AP36: =sum(B18:AP18) | AQ36: =sum(B18:AQ18) | AR36: =sum(B18:AR18) | AS36: =sum(B18:AS18) | AT36: =sum(B18:AT18) | AU36: =sum(B18:AU18) | AV36: =sum(B18:AV18) | AW36: =sum(B18:AW18) | AX36: =sum(B18:AX18) | AY36: =sum(B18:AY18) | AZ36: =sum(B18:AZ18) | BA36: =sum(B18:BA18) | BB36: =sum(B18:BB18) | BC36: =sum(B18:BC18) | BD36: =sum(B18:BD18) | BE36: =sum(B18:BE18) | BF36: =sum(B18:BF18) | BG36: =sum(B18:BG18) | BH36: =sum(B18:BH18) | BI36: =sum(B18:BI18)
A37: Cumulative Authorized Resources ($) | B37: 0 | C37: 0 | D37: 0 | E37: 0 | F37: 0 | G37: =sum(B19:G19) | H37: =sum(C19:H19) | I37: =sum(D19:I19) | J37: =sum(E19:J19) | K37: =sum(B19:K19) | L37: =sum(B19:L19) | M37: =sum(B19:M19) | N37: =sum(B19:N19) | O37: =sum(B19:O19) | P37: =sum(B19:P19) | Q37: =sum(B19:Q19) | R37: =sum(B19:R19) | S37: =sum(B19:S19) | T37: =sum(B19:T19) | U37: =sum(B19:U19) | V37: =sum(B19:V19) | W37: =sum(B19:W19) | X37: =sum(B19:X19) | Y37: =sum(B19:Y19) | Z37: =sum(B19:Z19) | AA37: =sum(B19:AA19) | AB37: =sum(B19:AB19) | AC37: =sum(B19:AC19) | AD37: =sum(B19:AD19) | AE37: =sum(B19:AE19) | AF37: =sum(B19:AF19) | AG37: =sum(B19:AG19) | AH37: =sum(B19:AH19) | AI37: =sum(B19:AI19) | AJ37: =sum(B19:AJ19) | AK37: =sum(B19:AK19) | AL37: =sum(B19:AL19) | AM37: =sum(B19:AM19) | AN37: =sum(B19:AN19) | AO37: =sum(B19:AO19) | AP37: =sum(B19:AP19) | AQ37: =sum(B19:AQ19) | AR37: =sum(B19:AR19) | AS37: =sum(B19:AS19) | AT37: =sum(B19:AT19) | AU37: =sum(B19:AU19) | AV37: =sum(B19:AV19) | AW37: =sum(B19:AW19) | AX37: =sum(B19:AX19) | AY37: =sum(B19:AY19) | AZ37: =sum(B19:AZ19) | BA37: =sum(B19:BA19) | BB37: =sum(B19:BB19) | BC37: =sum(B19:BC19) | BD37: =sum(B19:BD19) | BE37: =sum(B19:BE19) | BF37: =sum(B19:BF19) | BG37: =sum(B19:BG19) | BH37: =sum(B19:BH19) | BI37: =sum(B19:BI19)
A38: Cumulative Releasable Resources ($) | B38: 0 | C38: 0 | D38: 0 | E38: 0 | F38: 0 | G38: =sum(B20:G20) | H38: =sum(C20:H20) | I38: =sum(D20:I20) | J38: =sum(E20:J20) | K38: =sum(B20:K20) | L38: =sum(B20:L20) | M38: =sum(B20:M20) | N38: =sum(B20:N20) | O38: =sum(B20:O20) | P38: =sum(B20:P20) | Q38: =sum(B20:Q20) | R38: =sum(B20:R20) | S38: =sum(B20:S20) | T38: =sum(B20:T20) | U38: =sum(B20:U20) | V38: =sum(B20:V20) | W38: =sum(B20:W20) | X38: =sum(B20:X20) | Y38: =sum(B20:Y20) | Z38: =sum(B20:Z20) | AA38: =sum(B20:AA20) | AB38: =sum(B20:AB20) | AC38: =sum(B20:AC20) | AD38: =sum(B20:AD20) | AE38: =sum(B20:AE20) | AF38: =sum(B20:AF20) | AG38: =sum(B20:AG20) | AH38: =sum(B20:AH20) | AI38: =sum(B20:AI20) | AJ38: =sum(B20:AJ20) | AK38: =sum(B20:AK20) | AL38: =sum(B20:AL20) | AM38: =sum(B20:AM20) | AN38: =sum(B20:AN20) | AO38: =sum(B20:AO20) | AP38: =sum(B20:AP20) | AQ38: =sum(B20:AQ20) | AR38: =sum(B20:AR20) | AS38: =sum(B20:AS20) | AT38: =sum(B20:AT20) | AU38: =sum(B20:AU20) | AV38: =sum(B20:AV20) | AW38: =sum(B20:AW20) | AX38: =sum(B20:AX20) | AY38: =sum(B20:AY20) | AZ38: =sum(B20:AZ20) | BA38: =sum(B20:BA20) | BB38: =sum(B20:BB20) | BC38: =sum(B20:BC20) | BD38: =sum(B20:BD20) | BE38: =sum(B20:BE20) | BF38: =sum(B20:BF20) | BG38: =sum(B20:BG20) | BH38: =sum(B20:BH20) | BI38: =sum(B20:BI20)
A39: Cumulative Unlocked Resources ($) | B39: 0 | C39: 0 | D39: 0 | E39: 0 | F39: 0 | G39: =G33*XAUconfig!G3 | H39: =H33*XAUconfig!H3 | I39: =I33*XAUconfig!I3 | J39: =J33*XAUconfig!J3 | K39: =K33*XAUconfig!K3 | L39: =L33*XAUconfig!L3 | M39: =M33*XAUconfig!M3 | N39: =N33*XAUconfig!N3 | ... AE39: =AE33*XAUconfig!AE3 | AF39: =AF33*Inputs!B9 | AG39: =AG33*XAUconfig!AG3 | AH39: =AH33*XAUconfig!AH3 | AI39: =AI33*XAUconfig!AI3 | AJ39: =AJ33*XAUconfig!AJ3 | AK39: =AK33*XAUconfig!AK3 | AL39: =AL33*XAUconfig!AL3 | AM39: =AM33*XAUconfig!AM3 | AN39: =AN33*XAUconfig!AN3 | ... BI39: =BI33*XAUconfig!BI3
A40: Cumulative Allocation to RealGold Treasury ($) | B40: 0 | C40: 0 | D40: 0 | E40: 0 | F40: 0 | G40: =G34*XAUconfig!G3 | H40: =H34*XAUconfig!H3 | I40: =I34*XAUconfig!I3 | J40: =J34*XAUconfig!J3 | K40: =K34*XAUconfig!K3 | L40: =L34*XAUconfig!L3 | M40: =M34*XAUconfig!M3 | N40: =N34*XAUconfig!N3 | ... BI40: =BI34*XAUconfig!BI3
A42: Annual Summaries | G42: 2025 | H42: 2026 | I42: 2027 | J42: 2028 | K42: 2029 | L42: Cumulative
A43: # of mines brought online | G43: =sum(B3:M3) | H43: =sum(N3:Y3) | I43: =sum(Z3:AK3) | J43: =sum(AL3:AW3) | K43: =sum(AV3:BI3) | L43: =SUM(G43:K43)
A44: Assayed Resources ($) | G44: =sum(B18:M18) | H44: =sum(N18:Y18) | I44: =sum(Z18:AK18) | J44: =sum(AL18:AW18) | K44: =sum(AV18:BI18) | L44: =SUM(G44:K44)
A45: Authorized Resources ($) | G45: =sum(B19:M19) | H45: =sum(N19:Y19) | I45: =sum(Z19:AK19) | J45: =sum(AL19:AW19) | K45: =sum(AV19:BI19) | L45: =SUM(G45:K45)
A46: Releasable Resources ($) | G46: =sum(B20:M20) | H46: =sum(N20:Y20) | I46: =sum(Z20:AK20) | J46: =sum(AL20:AW20) | K46: =sum(AV20:BI20) | L46: =SUM(G46:K46)
A47: Released Resources ($) | G47: =sum(B21:M21) | H47: =sum(N21:Y21) | I47: =sum(Z21:AK21) | J47: =sum(AL21:AW21) | K47: =sum(AV21:BI21) | L47: =SUM(G47:K47)
A48: Registration Fees ($) | G48: =sum(B22:M22) | H48: =sum(N22:Y22) | I48: =sum(Z22:AK22) | J48: =sum(AL22:AW22) | K48: =sum(AV22:BI22) | L48: =SUM(G48:K48)
A49: Market Placement Fee ($) | G49: =sum(B23:M23) | H49: =sum(N23:Y23) | I49: =sum(Z23:AK23) | J49: =sum(AL23:AW23) | K49: =sum(AV23:BI23) | L49: =SUM(G49:K49)
A50: Total Fee Revenue ($) | G50: =sum(B25:M25) | H50: =sum(N25:Y25) | I50: =sum(Z25:AK25) | J50: =sum(AL25:AW25) | K50: =sum(AV25:BI25) | L50: =SUM(G50:K50)
A51: Total Allocation to 1031 ($) | G51: =sum(B26:M26) | H51: =sum(N26:Y26) | I51: =sum(Z26:AK26) | J51: =sum(AL26:AW26) | K51: =sum(AV26:BI26) | L51: =SUM(G51:K51)
A52: Total Allocation to RealGold Treasury ($) | G52: =sum(B27:M27) | H52: =sum(N27:Y27) | I52: =sum(Z27:AK27) | J52: =sum(AL27:AW27) | K52: =sum(AV27:BI27) | L52: =SUM(G52:K52)
A54: Assayed Resources (oz) | G54: =SUM(B4:M4) | H54: =sum(N4:Y4) | I54: =sum(Z4:AK4) | J54: =sum(AL4:AW4) | K54: =sum(AV4:BI4) | L54: =sum(G54:K54)
A55: Registered Resources (oz) | G55: =SUM(B5:M5) | H55: =sum(N5:Y5) | I55: =sum(Z5:AK5) | J55: =sum(AL5:AW5) | K55: =sum(AV5:BI5) | L55: =sum(G55:K55)
A56: Releasable Resources (oz) | G56: =SUM(B6:M6) | H56: =sum(N6:Y6) | I56: =sum(Z6:AK6) | J56: =sum(AL6:AW6) | K56: =sum(AV6:BI6) | L56: =sum(G56:K56)
A57: Released Resources (oz) | G57: =sum(B7:M7) | H57: =sum(N7:Y7) | I57: =sum(Z7:AK7) | J57: =sum(AL7:AW7) | K57: =sum(AV7:BI7) | L57: =sum(G57:K57)
A58: Registration Fees (oz) | G58: =sum(G8+J8) | H58: =sum(N8:Y8) | I58: =sum(Z8:AK8) | J58: =sum(AL8:AW8) | K58: =sum(AV8:BI8) | L58: =sum(G58:K58)
A59: Market Placement Fee (oz) | G59: =SUM(B10:M10) | H59: =sum(N10:Y10) | I59: =sum(Z10:AK10) | J59: =sum(AL10:AW10) | K59: =sum(AV10:BI10) | L59: =sum(G59:K59)
A60: Allocation to RealGold Treasury (oz) | G60: =SUM(B15:M15) | H60: =sum(N16:Y16) | I60: =sum(Z16:AK16) | J60: =sum(AL16:AW16) | K60: =sum(AV16:BI16) | L60: =sum(G60:K60)
A61: Total Fee Revenue (oz) | G61: =G58+G59 | H61: =H58+H59 | I61: =I58+I59 | J61: =J58+J59 | K61: =K58+K59 | L61: =sum(G61:K61)
A62: Total Allocation to 1031 (oz) | G62: =sum(B15:M15) | H62: =sum(N15:Y15) | I62: =sum(Z15:AK15) | J62: =sum(AL15:AW15) | K62: =sum(AV15:BI15) | L62: =sum(G62:K62)
A63: Total Allocation to RealGold Treasury (oz) | G63: =SUM(B15:M15) | H63: =SUM(N15:Y15) | I63: =SUM(Z15:AK15) | J63: =SUM(AL15:AW15) | K63: =SUM(AV15:BI15) | L63: =sum(G63:K63)
A65: Overcollateralization Ratio | L65: =L55/(L57+L58+L59)

Sheet Token Supply (5yr)
A1: Token Supply (5yr) | B1: =XAUconfig!B4 | C1: =XAUconfig!C4 | D1: =XAUconfig!D4 | E1: =XAUconfig!E4 | F1: =XAUconfig!F4 | G1: =XAUconfig!G4 | H1: =XAUconfig!H4 | I1: =XAUconfig!I4 | ... BI1: =XAUconfig!BI4
A2: Unlocked Supply
A3: RealGold Treasury | B3: 0 | C3: 0 | D3: 0 | E3: 0 | F3: 0 | G3: ='Resource Supply (5yr)'!G14 | H3: ='Resource Supply (5yr)'!H14 | I3: 0 | J3: ='Resource Supply (5yr)'!J11 | K3: 0 | L3: ='Resource Supply (5yr)'!L11 | M3: ='Resource Supply (5yr)'!M14 | N3: ='Resource Supply (5yr)'!N14 | O3: ='Resource Supply (5yr)'!O14 | P3: ='Resource Supply (5yr)'!P14 | Q3: ='Resource Supply (5yr)'!Q14 | R3: ='Resource Supply (5yr)'!R14 | S3: ='Resource Supply (5yr)'!S14 | T3: ='Resource Supply (5yr)'!T14 | ... BI3: ='Resource Supply (5yr)'!BI14
A4: Courbet Mine | B4: 0 | C4: 0 | D4: 0 | E4: 0 | F4: 0 | G4: =('Resource Supply (5yr)'!G7-'Resource Supply (5yr)'!G10)*'Mine Inventory'!AF2 | H4: 0 | I4: 0 | J4: 0 | K4: 0 | L4: 0 | M4: 0 | N4: 0 | O4: 0 | P4: 0 | Q4: 0 | R4: 0 | S4: =('Resource Supply (5yr)'!S7-'Resource Supply (5yr)'!S10)*'Mine Inventory'!AF2 | T4: 0 | U4: 0 | V4: 0 | W4: 0 | X4: 0 | Y4: 0 | Z4: 0 | AA4: 0 | AB4: 0 | AC4: 0 | AD4: 0 | AE4: =('Resource Supply (5yr)'!S7-'Resource Supply (5yr)'!S10)*'Mine Inventory'!AF2 | AF4: 0 | AG4: 0 | AH4: 0 | AI4: 0 | AJ4: 0 | AK4: 0 | AL4: 0 | AM4: 0 | AN4: 0 | AO4: 0 | AP4: 0 | AQ4: =('Resource Supply (5yr)'!S7-'Resource Supply (5yr)'!S10)*'Mine Inventory'!AF2 | AR4: 0 | AS4: 0 | AT4: 0 | AU4: 0 | AV4: 0 | AW4: 0 | AX4: 0 | AY4: 0 | AZ4: 0 | BA4: 0 | BB4: 0 | BC4: =('Resource Supply (5yr)'!S7-'Resource Supply (5yr)'!S10)*'Mine Inventory'!AF2 | BD4: 0 | BE4: 0 | BF4: 0 | BG4: 0 | BH4: 0 | BI4: 0
A5: Mine 2 | B5: 0 | C5: 0 | D5: 0 | E5: 0 | F5: 0 | G5: 0 | H5: 0 | I5: 0 | J5: =('Resource Supply (5yr)'!J7-'Resource Supply (5yr)'!J10)*'Mine Inventory'!AF2 | K5: 0 | L5: 0 | M5: 0 | N5: 0 | O5: 0 | P5: 0 | Q5: 0 | R5: 0 | S5: 0 | T5: 0 | U5: 0 | V5: =('Mine Inventory'!W3-'Resource Supply (5yr)'!V10)*'Mine Inventory'!AF3 | W5: 0 | X5: 0 | Y5: 0 | Z5: 0 | AA5: 0 | AB5: 0 | AC5: 0 | AD5: 0 | AE5: 0 | AF5: 0 | AG5: 0 | AH5: =('Mine Inventory'!W3-'Resource Supply (5yr)'!V10)*'Mine Inventory'!AF3 | AI5: 0 | AJ5: 0 | AK5: 0 | AL5: 0 | AM5: 0 | AN5: 0 | AO5: 0 | AP5: 0 | AQ5: 0 | AR5: 0 | AS5: 0 | AT5: =('Mine Inventory'!W3-'Resource Supply (5yr)'!V10)*'Mine Inventory'!AF3 | AU5: 0 | AV5: 0 | AW5: 0 | AX5: 0 | AY5: 0 | AZ5: 0 | BA5: 0 | BB5: 0 | BC5: 0 | BD5: 0 | BE5: 0 | BF5: =('Mine Inventory'!W3-'Resource Supply (5yr)'!V10)*'Mine Inventory'!AF3 | BG5: 0 | BH5: 0 | BI5: 0
A6: Mine 3 | B6: 0 | C6: 0 | D6: 0 | E6: 0 | F6: 0 | G6: 0 | H6: 0 | I6: 0 | J6: 0 | K6: 0 | L6: 0 | M6: 0 | N6: ='Resource Supply (5yr)'!L16+('Resource Supply (5yr)'!N7-'Resource Supply (5yr)'!N10)*'Mine Inventory'!AF4 | O6: 0 | P6: 0 | Q6: 0 | R6: 0 | S6: 0 | T6: 0 | U6: 0 | V6: 0 | W6: 0 | X6: 0 | Y6: 0 | Z6: =('Resource Supply (5yr)'!Z7-'Resource Supply (5yr)'!Z10)*'Mine Inventory'!AF4 | AA6: 0 | AB6: 0 | AC6: 0 | AD6: 0 | AE6: 0 | AF6: 0 | AG6: 0 | AH6: 0 | AI6: 0 | AJ6: 0 | AK6: 0 | AL6: =('Resource Supply (5yr)'!AL7-'Resource Supply (5yr)'!AL10)*'Mine Inventory'!AF4 | AM6: 0 | AN6: 0 | AO6: 0 | AP6: 0 | AQ6: 0 | AR6: 0 | AS6: 0 | AT6: 0 | AU6: 0 | AV6: 0 | AW6: 0 | AX6: =('Resource Supply (5yr)'!AX7-'Resource Supply (5yr)'!AX10)*'Mine Inventory'!AF4 | AY6: 0 | AZ6: 0 | BA6: 0 | BB6: 0 | BC6: 0 | BD6: 0 | BE6: 0 | BF6: 0 | BG6: 0 | BH6: 0 | BI6: 0
A7: Mine 4 | B7: 0 | C7: 0 | D7: 0 | E7: 0 | F7: 0 | G7: 0 | H7: 0 | I7: 0 | J7: 0 | K7: 0 | L7: 0 | M7: 0 | N7: 0 | O7: 0 | P7: 0 | Q7: =('Resource Supply (5yr)'!Q7-'Resource Supply (5yr)'!Q10)*'Mine Inventory'!AF5 | R7: 0 | S7: 0 | T7: 0 | U7: 0 | V7: 0 | W7: 0 | X7: 0 | Y7: 0 | Z7: 0 | AA7: 0 | AB7: 0 | AC7: =('Resource Supply (5yr)'!AC7-'Resource Supply (5yr)'!AC10)*'Mine Inventory'!AF5 | AD7: 0 | AE7: 0 | AF7: 0 | AG7: 0 | AH7: 0 | AI7: 0 | AJ7: 0 | AK7: 0 | AL7: 0 | AM7: 0 | AN7: 0 | AO7: =('Resource Supply (5yr)'!AO7-'Resource Supply (5yr)'!AO10)*'Mine Inventory'!AF5 | AP7: 0 | AQ7: 0 | AR7: 0 | AS7: 0 | AT7: 0 | AU7: 0 | AV7: 0 | AW7: 0 | AX7: 0 | AY7: 0 | AZ7: 0 | BA7: =('Resource Supply (5yr)'!BA7-'Resource Supply (5yr)'!BA10)*'Mine Inventory'!AF5 | BB7: 0 | BC7: 0 | BD7: 0 | BE7: 0 | BF7: 0 | BG7: 0 | BH7: 0 | BI7: 0
A8: Mine 5 | B8: 0 | C8: 0 | D8: 0 | E8: 0 | F8: 0 | G8: 0 | H8: 0 | I8: 0 | J8: 0 | K8: 0 | L8: 0 | M8: 0 | N8: 0 | O8: 0 | P8: 0 | Q8: 0 | R8: 0 | S8: 0 | T8: =('Resource Supply (5yr)'!T7-'Resource Supply (5yr)'!T10)*'Mine Inventory'!AF6 | U8: 0 | V8: 0 | W8: 0 | X8: 0 | Y8: 0 | Z8: 0 | AA8: 0 | AB8: 0 | AC8: 0 | AD8: 0 | AE8: 0 | AF8: =('Resource Supply (5yr)'!AF7-'Resource Supply (5yr)'!AF10)*'Mine Inventory'!AF6 | AG8: 0 | AH8: 0 | AI8: 0 | AJ8: 0 | AK8: 0 | AL8: 0 | AM8: 0 | AN8: 0 | AO8: 0 | AP8: 0 | AQ8: 0 | AR8: =('Resource Supply (5yr)'!AR7-'Resource Supply (5yr)'!AR10)*'Mine Inventory'!AF6 | AS8: 0 | AT8: 0 | AU8: 0 | AV8: 0 | AW8: 0 | AX8: 0 | AY8: 0 | AZ8: 0 | BA8: 0 | BB8: 0 | BC8: 0 | BD8: =('Resource Supply (5yr)'!BD7-'Resource Supply (5yr)'!BD10)*'Mine Inventory'!AF6 | BE8: 0 | BF8: 0 | BG8: 0 | BH8: 0 | BI8: 0
A9: Mine 6 | B9: 0 | C9: 0 | D9: 0 | E9: 0 | F9: 0 | G9: 0 | H9: 0 | I9: 0 | J9: 0 | K9: 0 | L9: 0 | M9: 0 | N9: 0 | O9: 0 | P9: 0 | Q9: 0 | R9: 0 | S9: 0 | T9: 0 | U9: 0 | V9: 0 | W9: 0 | X9: 0 | Y9: =('Resource Supply (5yr)'!Y7-'Resource Supply (5yr)'!Y10)*'Mine Inventory'!AF7 | Z9: 0 | AA9: 0 | AB9: 0 | AC9: 0 | AD9: 0 | AE9: 0 | AF9: 0 | AG9: 0 | AH9: 0 | AI9: 0 | AJ9: 0 | AK9: =('Resource Supply (5yr)'!AK7-'Resource Supply (5yr)'!AK10)*'Mine Inventory'!AF7 | AL9: 0 | AM9: 0 | AN9: 0 | AO9: 0 | AP9: 0 | AQ9: 0 | AR9: 0 | AS9: 0 | AT9: 0 | AU9: 0 | AV9: 0 | AW9: =('Resource Supply (5yr)'!AW7-'Resource Supply (5yr)'!AW10)*'Mine Inventory'!AF7 | AX9: 0 | AY9: 0 | AZ9: 0 | BA9: 0 | BB9: 0 | BC9: 0 | BD9: 0 | BE9: 0 | BF9: 0 | BG9: 0 | BH9: 0 | BI9: =('Resource Supply (5yr)'!BI7-'Resource Supply (5yr)'!BI10)*'Mine Inventory'!AF7
A10: Mine 7 | B10: 0 | C10: 0 | D10: 0 | E10: 0 | F10: 0 | G10: 0 | H10: 0 | I10: 0 | J10: 0 | K10: 0 | L10: 0 | M10: 0 | N10: 0 | O10: 0 | P10: 0 | Q10: 0 | R10: 0 | S10: 0 | T10: 0 | U10: 0 | V10: 0 | W10: 0 | X10: 0 | Y10: 0 | Z10: 0 | AA10: 0 | AB10: =('Resource Supply (5yr)'!AB7-'Resource Supply (5yr)'!AB10)*'Mine Inventory'!AF8 | AC10: 0 | AD10: 0 | AE10: 0 | AF10: 0 | AG10: 0 | AH10: 0 | AI10: 0 | AJ10: 0 | AK10: 0 | AL10: 0 | AM10: 0 | AN10: =('Resource Supply (5yr)'!AN7-'Resource Supply (5yr)'!AN10)*'Mine Inventory'!AF8 | AO10: 0 | AP10: 0 | AQ10: 0 | AR10: 0 | AS10: 0 | AT10: 0 | AU10: 0 | AV10: 0 | AW10: 0 | AX10: 0 | AY10: 0 | AZ10: =('Resource Supply (5yr)'!AZ7-'Resource Supply (5yr)'!AZ10)*'Mine Inventory'!AF8 | BA10: 0 | BB10: 0 | BC10: 0 | BD10: 0 | BE10: 0 | BF10: 0 | BG10: 0 | BH10: 0 | BI10: 0
A11: Mine 8 | B11: 0 | C11: 0 | D11: 0 | E11: 0 | F11: 0 | G11: 0 | H11: 0 | I11: 0 | J11: 0 | K11: 0 | L11: 0 | M11: 0 | N11: 0 | O11: 0 | P11: 0 | Q11: 0 | R11: 0 | S11: 0 | T11: 0 | U11: 0 | V11: 0 | W11: 0 | X11: 0 | Y11: 0 | Z11: 0 | AA11: 0 | AB11: 0 | AC11: 0 | AD11: 0 | AE11: 0 | AF11: 0 | AG11: =('Resource Supply (5yr)'!AG7-'Resource Supply (5yr)'!AG10)*'Mine Inventory'!AF10 | AH11: 0 | AI11: 0 | AJ11: 0 | AK11: 0 | AL11: 0 | AM11: 0 | AN11: 0 | AO11: 0 | AP11: 0 | AQ11: 0 | AR11: 0 | AS11: =('Resource Supply (5yr)'!AS7-'Resource Supply (5yr)'!AS10)*'Mine Inventory'!AF10 | AT11: 0 | AU11: 0 | AV11: 0 | AW11: 0 | AX11: 0 | AY11: 0 | AZ11: 0 | BA11: 0 | BB11: 0 | BC11: 0 | BD11: 0 | BE11: =('Resource Supply (5yr)'!BE7-'Resource Supply (5yr)'!BE10)*'Mine Inventory'!AF10 | BF11: 0 | BG11: 0 | BH11: 0 | BI11: 0
A12: Mine 9 | B12: 0 | C12: 0 | D12: 0 | E12: 0 | F12: 0 | G12: 0 | H12: 0 | I12: 0 | J12: 0 | K12: 0 | L12: 0 | M12: 0 | N12: 0 | O12: 0 | P12: 0 | Q12: 0 | R12: 0 | S12: 0 | T12: 0 | U12: 0 | V12: 0 | W12: 0 | X12: 0 | Y12: 0 | Z12: 0 | AA12: 0 | AB12: 0 | AC12: 0 | AD12: 0 | AE12: 0 | AF12: 0 | AG12: 0 | AH12: 0 | AI12: 0 | AJ12: =('Resource Supply (5yr)'!AJ7-'Resource Supply (5yr)'!AJ10)*'Mine Inventory'!AF9 | AK12: 0 | AL12: 0 | AM12: 0 | AN12: 0 | AO12: 0 | AP12: 0 | AQ12: 0 | AR12: 0 | AS12: 0 | AT12: 0 | AU12: 0 | AV12: =('Resource Supply (5yr)'!AV7-'Resource Supply (5yr)'!AV10)*'Mine Inventory'!AF9 | AW12: 0 | AX12: 0 | AY12: 0 | AZ12: 0 | BA12: 0 | BB12: 0 | BC12: 0 | BD12: 0 | BE12: 0 | BF12: 0 | BG12: 0 | BH12: =('Resource Supply (5yr)'!BH7-'Resource Supply (5yr)'!BH10)*'Mine Inventory'!AF9 | BI12: 0
A13: Mine 10 | B13: 0 | C13: 0 | D13: 0 | E13: 0 | F13: 0 | G13: 0 | H13: 0 | I13: 0 | J13: 0 | K13: 0 | L13: 0 | M13: 0 | N13: 0 | O13: 0 | P13: 0 | Q13: 0 | R13: 0 | S13: 0 | T13: 0 | U13: 0 | V13: 0 | W13: 0 | X13: 0 | Y13: 0 | Z13: 0 | AA13: 0 | AB13: 0 | AC13: 0 | AD13: 0 | AE13: 0 | AF13: 0 | AG13: 0 | AH13: 0 | AI13: 0 | AJ13: 0 | AK13: 0 | AL13: 0 | AM13: =('Resource Supply (5yr)'!AM7-'Resource Supply (5yr)'!AM10)*'Mine Inventory'!AF11 | AN13: 0 | AO13: 0 | AP13: 0 | AQ13: 0 | AR13: 0 | AS13: 0 | AT13: 0 | AU13: 0 | AV13: 0 | AW13: 0 | AX13: 0 | AY13: =('Resource Supply (5yr)'!AY7-'Resource Supply (5yr)'!AY10)*'Mine Inventory'!AF11 | AZ13: 0 | BA13: 0 | BB13: 0 | BC13: 0 | BD13: 0 | BE13: 0 | BF13: 0 | BG13: 0 | BH13: 0 | BI13: 0
A14: Mine 11 | B14: 0 | C14: 0 | D14: 0 | E14: 0 | F14: 0 | G14: 0 | H14: 0 | I14: 0 | J14: 0 | K14: 0 | L14: 0 | M14: 0 | N14: 0 | O14: 0 | P14: 0 | Q14: 0 | R14: 0 | S14: 0 | T14: 0 | U14: 0 | V14: 0 | W14: 0 | X14: 0 | Y14: 0 | Z14: 0 | AA14: 0 | AB14: 0 | AC14: 0 | AD14: 0 | AE14: 0 | AF14: 0 | AG14: 0 | AH14: 0 | AI14: 0 | AJ14: 0 | AK14: 0 | AL14: 0 | AM14: 0 | AN14: 0 | AO14: 0 | AP14: =('Resource Supply (5yr)'!AP7-'Resource Supply (5yr)'!AP10)*'Mine Inventory'!AF12 | AQ14: 0 | AR14: 0 | AS14: 0 | AT14: 0 | AU14: 0 | AV14: 0 | AW14: 0 | AX14: 0 | AY14: 0 | AZ14: 0 | BA14: 0 | BB14: =('Resource Supply (5yr)'!BB7-'Resource Supply (5yr)'!BB10)*'Mine Inventory'!AF12 | BC14: 0 | BD14: 0 | BE14: 0 | BF14: 0 | BG14: 0 | BH14: 0 | BI14: 0
A15: Mine 12 | B15: 0 | C15: 0 | D15: 0 | E15: 0 | F15: 0 | G15: 0 | H15: 0 | I15: 0 | J15: 0 | K15: 0 | L15: 0 | M15: 0 | N15: 0 | O15: 0 | P15: 0 | Q15: 0 | R15: 0 | S15: 0 | T15: 0 | U15: 0 | V15: 0 | W15: 0 | X15: 0 | Y15: 0 | Z15: 0 | AA15: 0 | AB15: 0 | AC15: 0 | AD15: 0 | AE15: 0 | AF15: 0 | AG15: 0 | AH15: 0 | AI15: 0 | AJ15: 0 | AK15: 0 | AL15: 0 | AM15: 0 | AN15: 0 | AO15: 0 | AP15: 0 | AQ15: 0 | AR15: 0 | AS15: 0 | AT15: 0 | AU15: =('Resource Supply (5yr)'!AU7-'Resource Supply (5yr)'!AU10)*'Mine Inventory'!AF13 | AV15: 0 | AW15: 0 | AX15: 0 | AY15: 0 | AZ15: 0 | BA15: 0 | BB15: 0 | BC15: 0 | BD15: 0 | BE15: 0 | BF15: 0 | BG15: =('Resource Supply (5yr)'!BG7-'Resource Supply (5yr)'!BG10)*'Mine Inventory'!AF13 | BH15: 0 | BI15: 0
A16: Monthly Unlocked Supply | B16: 0 | C16: 0 | D16: 0 | E16: 0 | F16: 0 | G16: =SUM(G3:G15) | H16: =SUM(H3:H15) | I16: =SUM(I3:I15) | J16: =SUM(J3:J15) | K16: =SUM(K3:K15) | L16: =SUM(L3:L15) | M16: =SUM(M3:M15) | N16: =SUM(N3:N15) | ... BI16: =SUM(BI3:BI15)
A18: Circulating Supply
A19: RealGold Reg & Market Fees | B19: 0 | C19: 0 | D19: 0 | E19: 0 | F19: 0 | G19: 0 | H19: 0 | I19: 0 | J19: 0 | K19: =sum(G3:J3) | L19: =L3 | M19: =M3 | N19: =N3 | O19: =O3 | P19: =P3 | Q19: =Q3 | R19: =R3 | S19: =S3 | ... BI19: =BI3
A20: Courbet Mine | B20: 0 | C20: 0 | D20: 0 | E20: 0 | F20: 0 | G20: 0 | H20: 0 | I20: 0 | J20: 0 | K20: ='Mine Inventory'!AH2*5 | L20: ='Mine Inventory'!AH2 | M20: ='Mine Inventory'!AH2 | N20: ='Mine Inventory'!AH2 | O20: ='Mine Inventory'!AH2 | P20: ='Mine Inventory'!AH2 | Q20: ='Mine Inventory'!AH2 | R20: ='Mine Inventory'!AH2 | S20: ='Mine Inventory'!AI2 | T20: ='Mine Inventory'!AI2 | U20: ='Mine Inventory'!AI2 | V20: ='Mine Inventory'!AI2 | W20: ='Mine Inventory'!AI2 | X20: ='Mine Inventory'!AI2 | Y20: ='Mine Inventory'!AI2 | Z20: ='Mine Inventory'!AI2 | AA20: ='Mine Inventory'!AI2 | AB20: ='Mine Inventory'!AI2 | AC20: ='Mine Inventory'!AI2 | AD20: ='Mine Inventory'!AI2 | AE20: ='Mine Inventory'!AI2 | AF20: ='Mine Inventory'!AI2 | AG20: ='Mine Inventory'!AI2 | AH20: ='Mine Inventory'!AI2 | AI20: ='Mine Inventory'!AI2 | AJ20: ='Mine Inventory'!AI2 | AK20: ='Mine Inventory'!AI2 | AL20: ='Mine Inventory'!AI2 | AM20: ='Mine Inventory'!AI2 | AN20: ='Mine Inventory'!AI2 | AO20: ='Mine Inventory'!AI2 | AP20: ='Mine Inventory'!AI2 | AQ20: ='Mine Inventory'!AI2 | AR20: ='Mine Inventory'!AI2 | AS20: ='Mine Inventory'!AI2 | AT20: ='Mine Inventory'!AI2 | AU20: ='Mine Inventory'!AI2 | AV20: ='Mine Inventory'!AI2 | AW20: ='Mine Inventory'!AI2 | AX20: ='Mine Inventory'!AI2 | AY20: ='Mine Inventory'!AI2 | AZ20: ='Mine Inventory'!AI2 | BA20: ='Mine Inventory'!AI2 | BB20: ='Mine Inventory'!AI2 | BC20: ='Mine Inventory'!AI2 | BD20: ='Mine Inventory'!AI2 | BE20: ='Mine Inventory'!AI2 | BF20: ='Mine Inventory'!AI2 | BG20: ='Mine Inventory'!AI2 | BH20: ='Mine Inventory'!AI2 | BI20: ='Mine Inventory'!AI2
A21: Mine 2 | B21: 0 | C21: 0 | D21: 0 | E21: 0 | F21: 0 | G21: 0 | H21: 0 | I21: 0 | J21: 0 | K21: 0 | L21: 0 | M21: 0 | N21: ='Mine Inventory'!AH3 | O21: ='Mine Inventory'!AH3 | P21: ='Mine Inventory'!AH3 | Q21: ='Mine Inventory'!AH3 | R21: ='Mine Inventory'!AH3 | S21: ='Mine Inventory'!AH3 | T21: ='Mine Inventory'!AH3 | U21: ='Mine Inventory'!AH3 | V21: ='Mine Inventory'!AI3 | W21: ='Mine Inventory'!AI3 | X21: ='Mine Inventory'!AI3 | Y21: ='Mine Inventory'!AI3 | Z21: ='Mine Inventory'!AI3 | AA21: ='Mine Inventory'!AI3 | AB21: ='Mine Inventory'!AI3 | AC21: ='Mine Inventory'!AI3 | AD21: ='Mine Inventory'!AI3 | AE21: ='Mine Inventory'!AI3 | AF21: ='Mine Inventory'!AI3 | AG21: ='Mine Inventory'!AI3 | AH21: ='Mine Inventory'!AI3 | AI21: ='Mine Inventory'!AI3 | AJ21: ='Mine Inventory'!AI3 | AK21: ='Mine Inventory'!AI3 | AL21: ='Mine Inventory'!AI3 | AM21: ='Mine Inventory'!AI3 | AN21: ='Mine Inventory'!AI3 | AO21: ='Mine Inventory'!AI3 | AP21: ='Mine Inventory'!AI3 | AQ21: ='Mine Inventory'!AI3 | AR21: ='Mine Inventory'!AI3 | AS21: ='Mine Inventory'!AI3 | AT21: ='Mine Inventory'!AI3 | AU21: ='Mine Inventory'!AI3 | AV21: ='Mine Inventory'!AI3 | AW21: ='Mine Inventory'!AI3 | AX21: ='Mine Inventory'!AI3 | AY21: ='Mine Inventory'!AI3 | AZ21: ='Mine Inventory'!AI3 | BA21: ='Mine Inventory'!AI3 | BB21: ='Mine Inventory'!AI3 | BC21: ='Mine Inventory'!AI3 | BD21: ='Mine Inventory'!AI3 | BE21: ='Mine Inventory'!AI3 | BF21: ='Mine Inventory'!AI3 | BG21: ='Mine Inventory'!AI3 | BH21: ='Mine Inventory'!AI3 | BI21: ='Mine Inventory'!AI3
A22: Mine 3 | B22: 0 | C22: 0 | D22: 0 | E22: 0 | F22: 0 | G22: 0 | H22: 0 | I22: 0 | J22: 0 | K22: 0 | L22: 0 | M22: 0 | N22: ='Mine Inventory'!AH4 | O22: ='Mine Inventory'!AH4 | P22: ='Mine Inventory'!AH4 | Q22: ='Mine Inventory'!AH4 | R22: ='Mine Inventory'!AH4 | S22: ='Mine Inventory'!AH4 | T22: ='Mine Inventory'!AH4 | U22: ='Mine Inventory'!AH4 | V22: ='Mine Inventory'!AH4 | W22: ='Mine Inventory'!AH4 | X22: ='Mine Inventory'!AH4 | Y22: ='Mine Inventory'!AH4 | Z22: ='Mine Inventory'!AI4 | AA22: ='Mine Inventory'!AI4 | AB22: ='Mine Inventory'!AI4 | AC22: ='Mine Inventory'!AI4 | AD22: ='Mine Inventory'!AI4 | AE22: ='Mine Inventory'!AI4 | AF22: ='Mine Inventory'!AI4 | AG22: ='Mine Inventory'!AI4 | AH22: ='Mine Inventory'!AI4 | AI22: ='Mine Inventory'!AI4 | AJ22: ='Mine Inventory'!AI4 | AK22: ='Mine Inventory'!AI4 | AL22: ='Mine Inventory'!AI4 | AM22: ='Mine Inventory'!AI4 | AN22: ='Mine Inventory'!AI4 | AO22: ='Mine Inventory'!AI4 | AP22: ='Mine Inventory'!AI4 | AQ22: ='Mine Inventory'!AI4 | AR22: ='Mine Inventory'!AI4 | AS22: ='Mine Inventory'!AI4 | AT22: ='Mine Inventory'!AI4 | AU22: ='Mine Inventory'!AI4 | AV22: ='Mine Inventory'!AI4 | AW22: ='Mine Inventory'!AI4 | AX22: ='Mine Inventory'!AI4 | AY22: ='Mine Inventory'!AI4 | AZ22: ='Mine Inventory'!AI4 | BA22: ='Mine Inventory'!AI4 | BB22: ='Mine Inventory'!AI4 | BC22: ='Mine Inventory'!AI4 | BD22: ='Mine Inventory'!AI4 | BE22: ='Mine Inventory'!AI4 | BF22: ='Mine Inventory'!AI4 | BG22: ='Mine Inventory'!AI4 | BH22: ='Mine Inventory'!AI4 | BI22: ='Mine Inventory'!AI4
A23: Mine 4 | B23: 0 | C23: 0 | D23: 0 | E23: 0 | F23: 0 | G23: 0 | H23: 0 | I23: 0 | J23: 0 | K23: 0 | L23: 0 | M23: 0 | N23: 0 | O23: 0 | P23: 0 | Q23: ='Mine Inventory'!AH5 | R23: ='Mine Inventory'!AH5 | S23: ='Mine Inventory'!AH5 | T23: ='Mine Inventory'!AH5 | U23: ='Mine Inventory'!AH5 | V23: ='Mine Inventory'!AH5 | W23: ='Mine Inventory'!AH5 | X23: ='Mine Inventory'!AH5 | Y23: ='Mine Inventory'!AH5 | Z23: ='Mine Inventory'!AH5 | AA23: ='Mine Inventory'!AH5 | AB23: ='Mine Inventory'!AH5 | AC23: ='Mine Inventory'!AI5 | AD23: ='Mine Inventory'!AI5 | AE23: ='Mine Inventory'!AI5 | AF23: ='Mine Inventory'!AI5 | AG23: ='Mine Inventory'!AI5 | AH23: ='Mine Inventory'!AI5 | AI23: ='Mine Inventory'!AI5 | AJ23: ='Mine Inventory'!AI5 | AK23: ='Mine Inventory'!AI5 | AL23: ='Mine Inventory'!AI5 | AM23: ='Mine Inventory'!AI5 | AN23: ='Mine Inventory'!AI5 | AO23: ='Mine Inventory'!AI5 | AP23: ='Mine Inventory'!AI5 | AQ23: ='Mine Inventory'!AI5 | AR23: ='Mine Inventory'!AI5 | AS23: ='Mine Inventory'!AI5 | AT23: ='Mine Inventory'!AI5 | AU23: ='Mine Inventory'!AI5 | AV23: ='Mine Inventory'!AI5 | AW23: ='Mine Inventory'!AI5 | AX23: ='Mine Inventory'!AI5 | AY23: ='Mine Inventory'!AI5 | AZ23: ='Mine Inventory'!AI5 | BA23: ='Mine Inventory'!AI5 | BB23: ='Mine Inventory'!AI5 | BC23: ='Mine Inventory'!AI5 | BD23: ='Mine Inventory'!AI5 | BE23: ='Mine Inventory'!AI5 | BF23: ='Mine Inventory'!AI5 | BG23: ='Mine Inventory'!AI5 | BH23: ='Mine Inventory'!AI5 | BI23: ='Mine Inventory'!AI5
A24: Mine 5 | B24: 0 | C24: 0 | D24: 0 | E24: 0 | F24: 0 | G24: 0 | H24: 0 | I24: 0 | J24: 0 | K24: 0 | L24: 0 | M24: 0 | N24: 0 | O24: 0 | P24: 0 | Q24: 0 | R24: 0 | S24: 0 | T24: ='Mine Inventory'!AH6 | U24: ='Mine Inventory'!AH6 | V24: ='Mine Inventory'!AH6 | W24: ='Mine Inventory'!AH6 | X24: ='Mine Inventory'!AH6 | Y24: ='Mine Inventory'!AH6 | Z24: ='Mine Inventory'!AH6 | AA24: ='Mine Inventory'!AH6 | AB24: ='Mine Inventory'!AH6 | AC24: ='Mine Inventory'!AH6 | AD24: ='Mine Inventory'!AH6 | AE24: ='Mine Inventory'!AH6 | AF24: ='Mine Inventory'!AI6 | AG24: ='Mine Inventory'!AI6 | AH24: ='Mine Inventory'!AI6 | AI24: ='Mine Inventory'!AI6 | AJ24: ='Mine Inventory'!AI6 | AK24: ='Mine Inventory'!AI6 | AL24: ='Mine Inventory'!AI6 | AM24: ='Mine Inventory'!AI6 | AN24: ='Mine Inventory'!AI6 | AO24: ='Mine Inventory'!AI6 | AP24: ='Mine Inventory'!AI6 | AQ24: ='Mine Inventory'!AI6 | AR24: ='Mine Inventory'!AI6 | AS24: ='Mine Inventory'!AI6 | AT24: ='Mine Inventory'!AI6 | AU24: ='Mine Inventory'!AI6 | AV24: ='Mine Inventory'!AI6 | AW24: ='Mine Inventory'!AI6 | AX24: ='Mine Inventory'!AI6 | AY24: ='Mine Inventory'!AI6 | AZ24: ='Mine Inventory'!AI6 | BA24: ='Mine Inventory'!AI6 | BB24: ='Mine Inventory'!AI6 | BC24: ='Mine Inventory'!AI6 | BD24: ='Mine Inventory'!AI6 | BE24: ='Mine Inventory'!AI6 | BF24: ='Mine Inventory'!AI6 | BG24: ='Mine Inventory'!AI6 | BH24: ='Mine Inventory'!AI6 | BI24: ='Mine Inventory'!AI6
A25: Mine 6 | B25: 0 | C25: 0 | D25: 0 | E25: 0 | F25: 0 | G25: 0 | H25: 0 | I25: 0 | J25: 0 | K25: 0 | L25: 0 | M25: 0 | N25: 0 | O25: 0 | P25: 0 | Q25: 0 | R25: 0 | S25: 0 | T25: 0 | U25: 0 | V25: 0 | W25: 0 | X25: 0 | Y25: ='Mine Inventory'!AH7 | Z25: ='Mine Inventory'!AH7 | AA25: ='Mine Inventory'!AH7 | AB25: ='Mine Inventory'!AH7 | AC25: ='Mine Inventory'!AH7 | AD25: ='Mine Inventory'!AH7 | AE25: ='Mine Inventory'!AH7 | AF25: ='Mine Inventory'!AH7 | AG25: ='Mine Inventory'!AH7 | AH25: ='Mine Inventory'!AH7 | AI25: ='Mine Inventory'!AH7 | AJ25: ='Mine Inventory'!AH7 | AK25: ='Mine Inventory'!AI7 | AL25: ='Mine Inventory'!AI7 | AM25: ='Mine Inventory'!AI7 | AN25: ='Mine Inventory'!AI7 | AO25: ='Mine Inventory'!AI7 | AP25: ='Mine Inventory'!AI7 | AQ25: ='Mine Inventory'!AI7 | AR25: ='Mine Inventory'!AI7 | AS25: ='Mine Inventory'!AI7 | AT25: ='Mine Inventory'!AI7 | AU25: ='Mine Inventory'!AI7 | AV25: ='Mine Inventory'!AI7 | AW25: ='Mine Inventory'!AI7 | AX25: ='Mine Inventory'!AI7 | AY25: ='Mine Inventory'!AI7 | AZ25: ='Mine Inventory'!AI7 | BA25: ='Mine Inventory'!AI7 | BB25: ='Mine Inventory'!AI7 | BC25: ='Mine Inventory'!AI7 | BD25: ='Mine Inventory'!AI7 | BE25: ='Mine Inventory'!AI7 | BF25: ='Mine Inventory'!AI7 | BG25: ='Mine Inventory'!AI7 | BH25: ='Mine Inventory'!AI7 | BI25: ='Mine Inventory'!AI7
A26: Mine 7 | B26: 0 | C26: 0 | D26: 0 | E26: 0 | F26: 0 | G26: 0 | H26: 0 | I26: 0 | J26: 0 | K26: 0 | L26: 0 | M26: 0 | N26: 0 | O26: 0 | P26: 0 | Q26: 0 | R26: 0 | S26: 0 | T26: 0 | U26: 0 | V26: 0 | W26: 0 | X26: 0 | Y26: 0 | Z26: 0 | AA26: 0 | AB26: ='Mine Inventory'!AH8 | AC26: ='Mine Inventory'!AH8 | AD26: ='Mine Inventory'!AH8 | AE26: ='Mine Inventory'!AH8 | AF26: ='Mine Inventory'!AH8 | AG26: ='Mine Inventory'!AH8 | AH26: ='Mine Inventory'!AH8 | AI26: ='Mine Inventory'!AH8 | AJ26: ='Mine Inventory'!AH8 | AK26: ='Mine Inventory'!AH8 | AL26: ='Mine Inventory'!AH8 | AM26: ='Mine Inventory'!AH8 | AN26: ='Mine Inventory'!AI8 | AO26: ='Mine Inventory'!AI8 | AP26: ='Mine Inventory'!AI8 | AQ26: ='Mine Inventory'!AI8 | AR26: ='Mine Inventory'!AI8 | AS26: ='Mine Inventory'!AI8 | AT26: ='Mine Inventory'!AI8 | AU26: ='Mine Inventory'!AI8 | AV26: ='Mine Inventory'!AI8 | AW26: ='Mine Inventory'!AI8 | AX26: ='Mine Inventory'!AI8 | AY26: ='Mine Inventory'!AI8 | AZ26: ='Mine Inventory'!AI8 | BA26: ='Mine Inventory'!AI8 | BB26: ='Mine Inventory'!AI8 | BC26: ='Mine Inventory'!AI8 | BD26: ='Mine Inventory'!AI8 | BE26: ='Mine Inventory'!AI8 | BF26: ='Mine Inventory'!AI8 | BG26: ='Mine Inventory'!AI8 | BH26: ='Mine Inventory'!AI8 | BI26: ='Mine Inventory'!AI8
A27: Mine 8 | B27: 0 | C27: 0 | D27: 0 | E27: 0 | F27: 0 | G27: 0 | H27: 0 | I27: 0 | J27: 0 | K27: 0 | L27: 0 | M27: 0 | N27: 0 | O27: 0 | P27: 0 | Q27: 0 | R27: 0 | S27: 0 | T27: 0 | U27: 0 | V27: 0 | W27: 0 | X27: 0 | Y27: 0 | Z27: 0 | AA27: 0 | AB27: 0 | AC27: 0 | AD27: 0 | AE27: 0 | AF27: ='Mine Inventory'!AH10 | AG27: ='Mine Inventory'!AH10 | AH27: ='Mine Inventory'!AH10 | AI27: ='Mine Inventory'!AH10 | AJ27: ='Mine Inventory'!AH10 | AK27: ='Mine Inventory'!AH10 | AL27: ='Mine Inventory'!AH10 | AM27: ='Mine Inventory'!AH10 | AN27: ='Mine Inventory'!AH10 | AO27: ='Mine Inventory'!AH10 | AP27: ='Mine Inventory'!AH10 | AQ27: ='Mine Inventory'!AH10 | AR27: ='Mine Inventory'!AI10 | AS27: ='Mine Inventory'!AI10 | AT27: ='Mine Inventory'!AI10 | AU27: ='Mine Inventory'!AI10 | AV27: ='Mine Inventory'!AI10 | AW27: ='Mine Inventory'!AI10 | AX27: ='Mine Inventory'!AI10 | AY27: ='Mine Inventory'!AI10 | AZ27: ='Mine Inventory'!AI10 | BA27: ='Mine Inventory'!AI10 | BB27: ='Mine Inventory'!AI10 | BC27: ='Mine Inventory'!AI10 | BD27: ='Mine Inventory'!AI10 | BE27: ='Mine Inventory'!AI10 | BF27: ='Mine Inventory'!AI10 | BG27: ='Mine Inventory'!AI10 | BH27: ='Mine Inventory'!AI10 | BI27: ='Mine Inventory'!AI10
A28: Mine 9 | B28: 0 | C28: 0 | D28: 0 | E28: 0 | F28: 0 | G28: 0 | H28: 0 | I28: 0 | J28: 0 | K28: 0 | L28: 0 | M28: 0 | N28: 0 | O28: 0 | P28: 0 | Q28: 0 | R28: 0 | S28: 0 | T28: 0 | U28: 0 | V28: 0 | W28: 0 | X28: 0 | Y28: 0 | Z28: 0 | AA28: 0 | AB28: 0 | AC28: 0 | AD28: 0 | AE28: 0 | AF28: 0 | AG28: 0 | AH28: 0 | AI28: 0 | AJ28: ='Mine Inventory'!AH9 | AK28: ='Mine Inventory'!AH9 | AL28: ='Mine Inventory'!AH9 | AM28: ='Mine Inventory'!AH9 | AN28: ='Mine Inventory'!AH9 | AO28: ='Mine Inventory'!AH9 | AP28: ='Mine Inventory'!AH9 | AQ28: ='Mine Inventory'!AH9 | AR28: ='Mine Inventory'!AH9 | AS28: ='Mine Inventory'!AH9 | AT28: ='Mine Inventory'!AH9 | AU28: ='Mine Inventory'!AH9 | AV28: ='Mine Inventory'!AI9 | AW28: ='Mine Inventory'!AI9 | AX28: ='Mine Inventory'!AI9 | AY28: ='Mine Inventory'!AI9 | AZ28: ='Mine Inventory'!AI9 | BA28: ='Mine Inventory'!AI9 | BB28: ='Mine Inventory'!AI9 | BC28: ='Mine Inventory'!AI9 | BD28: ='Mine Inventory'!AI9 | BE28: ='Mine Inventory'!AI9 | BF28: ='Mine Inventory'!AI9 | BG28: ='Mine Inventory'!AI9 | BH28: ='Mine Inventory'!AI9 | BI28: ='Mine Inventory'!AI9
A29: Mine 10 | B29: 0 | C29: 0 | D29: 0 | E29: 0 | F29: 0 | G29: 0 | H29: 0 | I29: 0 | J29: 0 | K29: 0 | L29: 0 | M29: 0 | N29: 0 | O29: 0 | P29: 0 | Q29: 0 | R29: 0 | S29: 0 | T29: 0 | U29: 0 | V29: 0 | W29: 0 | X29: 0 | Y29: 0 | Z29: 0 | AA29: 0 | AB29: 0 | AC29: 0 | AD29: 0 | AE29: 0 | AF29: 0 | AG29: 0 | AH29: 0 | AI29: 0 | AJ29: 0 | AK29: 0 | AL29: 0 | AM29: ='Mine Inventory'!AH11 | AN29: ='Mine Inventory'!AH11 | AO29: ='Mine Inventory'!AH11 | AP29: ='Mine Inventory'!AH11 | AQ29: ='Mine Inventory'!AH11 | AR29: ='Mine Inventory'!AH11 | AS29: ='Mine Inventory'!AH11 | AT29: ='Mine Inventory'!AH11 | AU29: ='Mine Inventory'!AH11 | AV29: ='Mine Inventory'!AH11 | AW29: ='Mine Inventory'!AH11 | AX29: ='Mine Inventory'!AH11 | AY29: ='Mine Inventory'!AI11 | AZ29: ='Mine Inventory'!AI11 | BA29: ='Mine Inventory'!AI11 | BB29: ='Mine Inventory'!AI11 | BC29: ='Mine Inventory'!AI11 | BD29: ='Mine Inventory'!AI11 | BE29: ='Mine Inventory'!AI11 | BF29: ='Mine Inventory'!AI11 | BG29: ='Mine Inventory'!AI11 | BH29: ='Mine Inventory'!AI11 | BI29: ='Mine Inventory'!AI11
A30: Mine 11 | B30: 0 | C30: 0 | D30: 0 | E30: 0 | F30: 0 | G30: 0 | H30: 0 | I30: 0 | J30: 0 | K30: 0 | L30: 0 | M30: 0 | N30: 0 | O30: 0 | P30: 0 | Q30: 0 | R30: 0 | S30: 0 | T30: 0 | U30: 0 | V30: 0 | W30: 0 | X30: 0 | Y30: 0 | Z30: 0 | AA30: 0 | AB30: 0 | AC30: 0 | AD30: 0 | AE30: 0 | AF30: 0 | AG30: 0 | AH30: 0 | AI30: 0 | AJ30: 0 | AK30: 0 | AL30: 0 | AM30: 0 | AN30: 0 | AO30: 0 | AP30: ='Mine Inventory'!AH12 | AQ30: ='Mine Inventory'!AH12 | AR30: ='Mine Inventory'!AH12 | AS30: ='Mine Inventory'!AH12 | AT30: ='Mine Inventory'!AH12 | AU30: ='Mine Inventory'!AH12 | AV30: ='Mine Inventory'!AH12 | AW30: ='Mine Inventory'!AH12 | AX30: ='Mine Inventory'!AH12 | AY30: ='Mine Inventory'!AH12 | AZ30: ='Mine Inventory'!AH12 | BA30: ='Mine Inventory'!AH12 | BB30: ='Mine Inventory'!AI12 | BC30: ='Mine Inventory'!AI12 | BD30: ='Mine Inventory'!AI12 | BE30: ='Mine Inventory'!AI12 | BF30: ='Mine Inventory'!AI12 | BG30: ='Mine Inventory'!AI12 | BH30: ='Mine Inventory'!AI12 | BI30: ='Mine Inventory'!AI12
A31: Mine 12 | B31: 0 | C31: 0 | D31: 0 | E31: 0 | F31: 0 | G31: 0 | H31: 0 | I31: 0 | J31: 0 | K31: 0 | L31: 0 | M31: 0 | N31: 0 | O31: 0 | P31: 0 | Q31: 0 | R31: 0 | S31: 0 | T31: 0 | U31: 0 | V31: 0 | W31: 0 | X31: 0 | Y31: 0 | Z31: 0 | AA31: 0 | AB31: 0 | AC31: 0 | AD31: 0 | AE31: 0 | AF31: 0 | AG31: 0 | AH31: 0 | AI31: 0 | AJ31: 0 | AK31: 0 | AL31: 0 | AM31: 0 | AN31: 0 | AO31: 0 | AP31: 0 | AQ31: 0 | AR31: 0 | AS31: 0 | AT31: 0 | AU31: ='Mine Inventory'!AH13 | AV31: ='Mine Inventory'!AH13 | AW31: ='Mine Inventory'!AH13 | AX31: ='Mine Inventory'!AH13 | AY31: ='Mine Inventory'!AH13 | AZ31: ='Mine Inventory'!AH13 | BA31: ='Mine Inventory'!AH13 | BB31: ='Mine Inventory'!AH13 | BC31: ='Mine Inventory'!AH13 | BD31: ='Mine Inventory'!AH13 | BE31: ='Mine Inventory'!AH13 | BF31: ='Mine Inventory'!AH13 | BG31: ='Mine Inventory'!AI13 | BH31: ='Mine Inventory'!AI13 | BI31: ='Mine Inventory'!AI13
A32: Monthly Change | B32: 0 | C32: 0 | D32: 0 | E32: 0 | F32: 0 | G32: =SUM(G17:G31) | H32: =SUM(H17:H31) | I32: =SUM(I17:I31) | J32: =SUM(J17:J31) | K32: =SUM(K17:K31) | L32: =SUM(L17:L31) | M32: =SUM(M17:M31) | N32: =SUM(N17:N31) | ... BI32: =SUM(BI17:BI31)
A34: Supply Summary
A35: Cumulative Unlocked Supply (oz) | B35: 0 | C35: 0 | D35: 0 | E35: 0 | F35: 0 | G35: =G16 | H35: =sum(B16:H16) | I35: =sum(B16:I16) | J35: =sum(B16:J16) | K35: =sum(B16:K16) | L35: =sum(B16:L16) | M35: =sum(B16:M16) | N35: =sum(B16:N16) | O35: =sum(B16:O16) | P35: =sum(B16:P16) | Q35: =sum(B16:Q16) | R35: =sum(B16:R16) | S35: =sum(B16:S16) | T35: =sum(B16:T16) | U35: =sum(B16:U16) | V35: =sum(B16:V16) | W35: =sum(B16:W16) | X35: =sum(B16:X16) | Y35: =sum(B16:Y16) | Z35: =sum(B16:Z16) | AA35: =sum(B16:AA16) | AB35: =sum(B16:AB16) | AC35: =sum(B16:AC16) | AD35: =sum(B16:AD16) | AE35: =sum(B16:AE16) | AF35: =sum(B16:AF16) | AG35: =sum(B16:AG16) | AH35: =sum(B16:AH16) | AI35: =sum(B16:AI16) | AJ35: =sum(B16:AJ16) | AK35: =sum(B16:AK16) | AL35: =sum(B16:AL16) | AM35: =sum(B16:AM16) | AN35: =sum(B16:AN16) | AO35: =sum(B16:AO16) | AP35: =sum(B16:AP16) | AQ35: =sum(B16:AQ16) | AR35: =sum(B16:AR16) | AS35: =sum(B16:AS16) | AT35: =sum(B16:AT16) | AU35: =sum(B16:AU16) | AV35: =sum(B16:AV16) | AW35: =sum(B16:AW16) | AX35: =sum(B16:AX16) | AY35: =sum(B16:AY16) | AZ35: =sum(B16:AZ16) | BA35: =sum(B16:BA16) | BB35: =sum(B16:BB16) | BC35: =sum(B16:BC16) | BD35: =sum(B16:BD16) | BE35: =sum(B16:BE16) | BF35: =sum(B16:BF16) | BG35: =sum(B16:BG16) | BH35: =sum(B16:BH16) | BI35: =sum(B16:BI16)
A36: Cumulative Circulating Supply (oz) | B36: 0 | C36: 0 | D36: 0 | E36: 0 | F36: 0 | G36: =sum(B32:G32) | H36: =sum(B32:H32) | I36: =sum(B32:I32) | J36: =sum(B32:J32) | K36: =sum(B32:K32) | L36: =sum(B32:L32) | M36: =sum(B32:M32) | N36: =sum(B32:N32) | O36: =sum(B32:O32) | P36: =sum(B32:P32) | Q36: =sum(B32:Q32) | R36: =sum(B32:R32) | S36: =sum(B32:S32) | T36: =sum(B32:T32) | U36: =sum(B32:U32) | V36: =sum(B32:V32) | W36: =sum(B32:W32) | X36: =sum(B32:X32) | Y36: =sum(B32:Y32) | Z36: =sum(B32:Z32) | AA36: =sum(B32:AA32) | AB36: =sum(B32:AB32) | AC36: =sum(B32:AC32) | AD36: =sum(B32:AD32) | AE36: =sum(B32:AE32) | AF36: =sum(B32:AF32) | AG36: =sum(B32:AG32) | AH36: =sum(B32:AH32) | AI36: =sum(B32:AI32) | AJ36: =sum(B32:AJ32) | AK36: =sum(B32:AK32) | AL36: =sum(B32:AL32) | AM36: =sum(B32:AM32) | AN36: =sum(B32:AN32) | AO36: =sum(B32:AO32) | AP36: =sum(B32:AP32) | AQ36: =sum(B32:AQ32) | AR36: =sum(B32:AR32) | AS36: =sum(B32:AS32) | AT36: =sum(B32:AT32) | AU36: =sum(B32:AU32) | AV36: =sum(B32:AV32) | AW36: =sum(B32:AW32) | AX36: =sum(B32:AX32) | AY36: =sum(B32:AY32) | AZ36: =sum(B32:AZ32) | BA36: =sum(B32:BA32) | BB36: =sum(B32:BB32) | BC36: =sum(B32:BC32) | BD36: =sum(B32:BD32) | BE36: =sum(B32:BE32) | BF36: =sum(B32:BF32) | BG36: =sum(B32:BG32) | BH36: =sum(B32:BH32) | BI36: =sum(B32:BI32)
A37: Cumulative Unlocked Supply ($) | B37: =B35*XAUconfig!B3 | C37: =C35*XAUconfig!C3 | D37: =D35*XAUconfig!D3 | E37: =E35*XAUconfig!E3 | F37: =F35*XAUconfig!F3 | G37: =G35*XAUconfig!G3 | H37: =H35*XAUconfig!H3 | I37: =I35*XAUconfig!I3 | ... BI37: =BI35*XAUconfig!BI3
A38: Cumulative Circulating Supply ($) | B38: =B36*XAUconfig!B3 | C38: =C36*XAUconfig!C3 | D38: =D36*XAUconfig!D3 | E38: =E36*XAUconfig!E3 | F38: =F36*XAUconfig!F3 | G38: =G36*XAUconfig!G3 | H38: =H36*XAUconfig!H3 | I38: =I36*XAUconfig!I3 | ... BI38: =BI36*XAUconfig!BI3
A39: Circulating Supply / Market Cap | B39: N/A | C39: N/A | D39: N/A | E39: N/A | F39: N/A | G39: N/A | H39: N/A | I39: N/A | J39: N/A | K39: N/A | L39: N/A | M39: N/A | N39: =N36/N35 | O39: =O36/O35 | P39: =P36/P35 | Q39: =Q36/Q35 | R39: =R36/R35 | S39: =S36/S35 | T39: =T36/T35 | U39: =U36/U35 | ... BI39: =BI36/BI35
A41: Bullion Redemption
A42: Cumulative Redemption Cap (oz) | B42: 0 | C42: 0 | D42: 0 | E42: 0 | F42: 0 | G42: 0 | H42: 0 | I42: 0 | J42: 0 | K42: =K35*Inputs!B55 | L42: =L35*Inputs!B55 | M42: =M35*Inputs!B55 | N42: =N35*Inputs!B55 | O42: =O35*Inputs!B55 | P42: =P35*Inputs!B55 | Q42: =Q35*Inputs!B55 | R42: =R35*Inputs!B55 | S42: =S35*Inputs!B55 | T42: =T35*Inputs!B55 | U42: =U35*Inputs!B55 | V42: =V35*Inputs!B55 | W42: =W35*Inputs!B55 | X42: =X35*Inputs!B55 | Y42: =Y35*Inputs!B55 | Z42: =Z35*Inputs!B55 | AA42: =AA35*Inputs!B55 | AB42: =AB35*Inputs!B55 | AC42: =AC35*Inputs!B55 | AD42: =AD35*Inputs!B55 | AE42: =AE35*Inputs!B55 | AF42: =AF35*Inputs!B55 | AG42: =AG35*Inputs!B55 | AH42: =AH35*Inputs!B55 | AI42: =AI35*Inputs!B55 | AJ42: =AJ35*Inputs!B55 | AK42: =AK35*Inputs!B55 | AL42: =AL35*Inputs!B55 | AM42: =AM35*Inputs!B55 | AN42: =AN35*Inputs!B55 | AO42: =AO35*Inputs!B55 | AP42: =AP35*Inputs!B55 | AQ42: =AQ35*Inputs!B55 | AR42: =AR35*Inputs!B55 | AS42: =AS35*Inputs!B55 | AT42: =AT35*Inputs!B55 | AU42: =AU35*Inputs!B55 | AV42: =AV35*Inputs!B55 | AW42: =AW35*Inputs!B55 | AX42: =AX35*Inputs!B55 | AY42: =AY35*Inputs!B55 | AZ42: =AZ35*Inputs!B55 | BA42: =BA35*Inputs!B55 | BB42: =BB35*Inputs!B55 | BC42: =BC35*Inputs!B55 | BD42: =BD35*Inputs!B55 | BE42: =BE35*Inputs!B55 | BF42: =BF35*Inputs!B55 | BG42: =BG35*Inputs!B55 | BH42: =BH35*Inputs!B55 | BI42: =BI35*Inputs!B55
A43: Cumulative Redemption Cap ($) | B43: =B42*XAUconfig!B3 | C43: =C42*XAUconfig!C3 | D43: =D42*XAUconfig!D3 | E43: =E42*XAUconfig!E3 | F43: =F42*XAUconfig!F3 | G43: =G42*XAUconfig!G3 | H43: =H42*XAUconfig!H3 | I43: =I42*XAUconfig!I3 | ... BI43: =BI42*XAUconfig!BI3
A44: Fulfilled Redemptions (oz) | B44: 0 | C44: 0 | D44: 0 | E44: 0 | F44: 0 | G44: 0 | H44: 0 | I44: 0 | J44: 0 | K44: 0 | L44: 0 | M44: 0 | N44: 10 | O44: 10 | P44: 10 | Q44: 10 | R44: 10 | S44: 10 | T44: 10 | U44: 10 | V44: 10 | W44: 10 | X44: 10 | Y44: 10 | Z44: 25 | AA44: 25 | AB44: 25 | AC44: 25 | AD44: 25 | AE44: 25 | AF44: 25 | AG44: 25 | AH44: 25 | AI44: 25 | AJ44: 25 | AK44: 25 | AL44: 100 | AM44: 100 | AN44: 100 | AO44: 100 | AP44: 100 | AQ44: 100 | AR44: 100 | AS44: 100 | AT44: 100 | AU44: 100 | AV44: 100 | AW44: 100 | AX44: 100 | AY44: 100 | AZ44: 100 | BA44: 100 | BB44: 100 | BC44: 100 | BD44: 100 | BE44: 100 | BF44: 100 | BG44: 100 | BH44: 100 | BI44: 100
A45: Cost of Fulfilled Redemptions | B45: =B44*XAUconfig!B3 | C45: =C44*XAUconfig!C3 | D45: =D44*XAUconfig!D3 | E45: =E44*XAUconfig!E3 | F45: =F44*XAUconfig!F3 | G45: =G44*XAUconfig!G3 | H45: =H44*XAUconfig!H3 | I45: =I44*XAUconfig!I3 | ... BI45: =BI44*XAUconfig!BI3
P54: =('Mine Inventory'!W2-'Resource Supply (5yr)'!S10)*'Mine Inventory'!AF2

Sheet Token Demand (5yr)
A1: Token Demand (5yr) | B1: =XAUconfig!B4 | C1: =XAUconfig!C4 | D1: =XAUconfig!D4 | E1: =XAUconfig!E4 | F1: =XAUconfig!F4 | G1: =XAUconfig!G4 | H1: =XAUconfig!H4 | I1: =XAUconfig!I4 | ... BI1: =XAUconfig!BI4
A2: RealGold Token Supply
A3: Total Unlocked Supply - Cumulative (oz) | B3: 0 | C3: 0 | D3: 0 | E3: 0 | F3: 0 | G3: ='Resource Supply (5yr)'!G34 | H3: ='Resource Supply (5yr)'!G34 | I3: ='Resource Supply (5yr)'!I34 | J3: ='Resource Supply (5yr)'!J34 | K3: ='Resource Supply (5yr)'!K34 | L3: 0 | M3: 0 | N3: ='Resource Supply (5yr)'!N34 | O3: ='Resource Supply (5yr)'!O34 | P3: ='Resource Supply (5yr)'!P34 | Q3: ='Resource Supply (5yr)'!Q34 | R3: ='Resource Supply (5yr)'!R34 | S3: ='Resource Supply (5yr)'!S34 | T3: ='Resource Supply (5yr)'!T34 | U3: ='Resource Supply (5yr)'!U34 | ... BI3: ='Resource Supply (5yr)'!BI34
A4: Total Circulating Supply - Cumulative (oz) | B4: 0 | C4: 0 | D4: 0 | E4: 0 | F4: 0 | G4: ='Token Supply (5yr)'!G36 | H4: ='Token Supply (5yr)'!H36 | I4: ='Token Supply (5yr)'!I36 | J4: ='Token Supply (5yr)'!J36 | K4: ='Token Supply (5yr)'!K36 | L4: ='Token Supply (5yr)'!L36 | M4: ='Token Supply (5yr)'!M36 | N4: ='Token Supply (5yr)'!N36 | ... BI4: ='Token Supply (5yr)'!BI36
A5: Total Unlocked Supply - Cumulative ($) | B5: 0 | C5: 0 | D5: 0 | E5: 0 | F5: 0 | G5: =G3*XAUconfig!G3 | H5: =H3*XAUconfig!H3 | I5: =I3*XAUconfig!I3 | J5: =J3*XAUconfig!J3 | K5: =K3*XAUconfig!K3 | L5: =L3*XAUconfig!L3 | M5: =M3*XAUconfig!M3 | N5: =N3*XAUconfig!N3 | ... BI5: =BI3*XAUconfig!BI3
A6: Total Circulating Supply - Cumulative ($) | B6: 0 | C6: 0 | D6: 0 | E6: 0 | F6: 0 | G6: 0 | H6: 0 | I6: 0 | J6: 0 | K6: =K4*XAUconfig!K3 | L6: =L4*XAUconfig!L3 | M6: =M4*XAUconfig!M3 | N6: =N4*XAUconfig!N3 | O6: =O4*XAUconfig!O3 | P6: =P4*XAUconfig!P3 | Q6: =Q4*XAUconfig!Q3 | R6: =R4*XAUconfig!R3 | ... BI6: =BI4*XAUconfig!BI3
A8: RealGold Liquidity Supply
A9: RealGold "Leased" Liquidity Supply (oz) | B9: 0 | C9: 0 | D9: 0 | E9: 0 | F9: 0 | G9: 0 | H9: 0 | I9: 0 | J9: ='Mine Inventory'!W2 | K9: =J9 | L9: =J9+'Mine Inventory'!W3 | M9: =J9+'Mine Inventory'!W3 | N9: =M9+'Mine Inventory'!W4 | O9: =M9+'Mine Inventory'!W4 | P9: =M9+'Mine Inventory'!W4 | Q9: =P9+'Mine Inventory'!W5 | R9: =P9+'Mine Inventory'!W5 | S9: =P9+'Mine Inventory'!W5 | T9: =S9+'Mine Inventory'!W6 | U9: =S9+'Mine Inventory'!W6 | V9: =S9+'Mine Inventory'!W6 | W9: =S9+'Mine Inventory'!W6 | X9: =S9+'Mine Inventory'!W6 | Y9: =X9+'Mine Inventory'!W7 | Z9: =X9+'Mine Inventory'!W7 | AA9: =X9+'Mine Inventory'!W7 | AB9: =AA9+'Mine Inventory'!W8 | AC9: =AA9+'Mine Inventory'!W8 | AD9: =AA9+'Mine Inventory'!W8 | AE9: =AA9+'Mine Inventory'!W8 | AF9: =AA9+'Mine Inventory'!W8 | AG9: =AF9+'Mine Inventory'!W10 | AH9: =AF9+'Mine Inventory'!W10 | AI9: =AF9+'Mine Inventory'!W10 | AJ9: =AI9+'Mine Inventory'!W9 | AK9: =AI9+'Mine Inventory'!W9 | AL9: =AI9+'Mine Inventory'!W9 | AM9: =AL9+'Mine Inventory'!W11 | AN9: =AL9+'Mine Inventory'!W11 | AO9: =AL9+'Mine Inventory'!W11 | AP9: =AO9+'Mine Inventory'!W12 | AQ9: =AO9+'Mine Inventory'!W12 | AR9: =AO9+'Mine Inventory'!W12 | AS9: =AO9+'Mine Inventory'!W12 | AT9: =AO9+'Mine Inventory'!W12 | AU9: =AT9+'Mine Inventory'!W13 | AV9: =AT9+'Mine Inventory'!W13 | AW9: =AT9+'Mine Inventory'!W13 | AX9: =AT9+'Mine Inventory'!W13 | AY9: =AT9+'Mine Inventory'!W13 | AZ9: =AT9+'Mine Inventory'!W13 | BA9: =AT9+'Mine Inventory'!W13 | BB9: =AT9+'Mine Inventory'!W13 | BC9: =AT9+'Mine Inventory'!W13 | BD9: =AT9+'Mine Inventory'!W13 | BE9: =AT9+'Mine Inventory'!W13 | BF9: =AT9+'Mine Inventory'!W13 | BG9: =AT9+'Mine Inventory'!W13 | BH9: =AT9+'Mine Inventory'!W13 | BI9: =AT9+'Mine Inventory'!W13
A10: Total RealGold Liquidity Locked (oz) | B10: 0 | C10: 0 | D10: 0 | E10: 0 | F10: 0 | G10: 0 | H10: 0 | I10: 0 | J10: 0 | K10: 0 | L10: 0 | M10: 0 | N10: =N12/XAUconfig!N3 | O10: =O12/XAUconfig!O3 | P10: =P12/XAUconfig!P3 | Q10: =Q12/XAUconfig!Q3 | R10: =R12/XAUconfig!R3 | S10: =S12/XAUconfig!S3 | T10: =T12/XAUconfig!T3 | U10: =U12/XAUconfig!U3 | ... BI10: =BI12/XAUconfig!BI3
A11: RealGold "Leased" Liquidity Supply ($) | B11: 0 | C11: 0 | D11: 0 | E11: 0 | F11: 0 | G11: 0 | H11: 0 | I11: 0 | J11: 0 | K11: 0 | L11: 0 | M11: 0 | N11: =N9*XAUconfig!N3 | O11: =O9*XAUconfig!O3 | P11: =P9*XAUconfig!P3 | Q11: =Q9*XAUconfig!Q3 | R11: =R9*XAUconfig!R3 | S11: =S9*XAUconfig!S3 | T11: =T9*XAUconfig!T3 | U11: =U9*XAUconfig!U3 | ... BI11: =BI9*XAUconfig!BI3
A12: RealGold TVL Liquidity Locked ($) | B12: 0 | C12: 0 | D12: 0 | E12: 0 | F12: 0 | G12: 0 | H12: 0 | I12: 0 | J12: 0 | K12: 0 | L12: 0 | M12: 0 | N12: 2500000 | O12: 2500000 | P12: 2500000 | Q12: 2500000 | R12: 2500000 | S12: 2500000 | T12: 5000000 | U12: 5000000 | V12: 5000000 | W12: 5000000 | X12: 5000000 | Y12: 5000000 | Z12: 10000000 | AA12: 10000000 | AB12: 10000000 | AC12: 10000000 | AD12: 10000000 | AE12: 10000000 | AF12: 10000000 | AG12: 10000000 | AH12: 10000000 | AI12: 10000000 | AJ12: 10000000 | AK12: 10000000 | AL12: 15000000 | AM12: 15000000 | AN12: 15000000 | AO12: 15000000 | AP12: 15000000 | AQ12: 15000000 | AR12: 15000000 | AS12: 15000000 | AT12: 15000000 | AU12: 15000000 | AV12: 15000000 | AW12: 15000000 | AX12: 15000000 | AY12: 15000000 | AZ12: 15000000 | BA12: 15000000 | BB12: 15000000 | BC12: 15000000 | BD12: 15000000 | BE12: 15000000 | BF12: 15000000 | BG12: 15000000 | BH12: 15000000 | BI12: 15000000
A13: Trading Pairs TVL Liquidity for LPs ($) | B13: 0 | C13: 0 | D13: 0 | E13: 0 | F13: 0 | G13: 0 | H13: 0 | I13: 0 | J13: 0 | K13: 0 | L13: 0 | M13: 0 | N13: 2500000 | O13: 2500000 | P13: 2500000 | Q13: 2500000 | R13: 2500000 | S13: 2500000 | T13: 5000000 | U13: 5000000 | V13: 5000000 | W13: 5000000 | X13: 5000000 | Y13: 5000000 | Z13: 10000000 | AA13: 10000000 | AB13: 10000000 | AC13: 10000000 | AD13: 10000000 | AE13: 10000000 | AF13: 10000000 | AG13: 10000000 | AH13: 10000000 | AI13: 10000000 | AJ13: 10000000 | AK13: 10000000 | AL13: 15000000 | AM13: 15000000 | AN13: 15000000 | AO13: 15000000 | AP13: 15000000 | AQ13: 15000000 | AR13: 15000000 | AS13: 15000000 | AT13: 15000000 | AU13: 15000000 | AV13: 15000000 | AW13: 15000000 | AX13: 15000000 | AY13: 15000000 | AZ13: 15000000 | BA13: 15000000 | BB13: 15000000 | BC13: 15000000 | BD13: 15000000 | BE13: 15000000 | BF13: 15000000 | BG13: 15000000 | BH13: 15000000 | BI13: 15000000
A14: Total % Liquidity Provided by RealGold | B14: N/A | C14: N/A | D14: N/A | E14: N/A | F14: N/A | G14: N/A | H14: N/A | I14: N/A | J14: N/A | K14: N/A | L14: N/A | M14: N/A | N14: 0.5 | O14: 0.5 | P14: 0.5 | Q14: 0.5 | R14: 0.5 | S14: 0.5 | T14: 0.5 | U14: 0.5 | V14: 0.5 | W14: 0.5 | X14: 0.5 | Y14: 0.5 | Z14: 0.6 | AA14: 0.6 | AB14: 0.6 | AC14: 0.6 | AD14: 0.6 | AE14: 0.6 | AF14: 0.6 | AG14: 0.6 | AH14: 0.6 | AI14: 0.6 | AJ14: 0.6 | AK14: 0.6 | AL14: 0.7 | AM14: 0.7 | AN14: 0.7 | AO14: 0.7 | AP14: 0.7 | AQ14: 0.7 | AR14: 0.7 | AS14: 0.7 | AT14: 0.7 | AU14: 0.7 | AV14: 0.7 | AW14: 0.7 | AX14: 0.8 | AY14: 0.8 | AZ14: 0.8 | BA14: 0.8 | BB14: 0.8 | BC14: 0.8 | BD14: 0.8 | BE14: 0.8 | BF14: 0.8 | BG14: 0.8 | BH14: 0.8 | BI14: 0.8
A16: DEX Markets
A17: Circulating Marketcap to DEX Volume Ratio (monthly) | B17: 0 | C17: 0 | D17: 0 | E17: 0 | F17: 0 | G17: 0 | H17: 0 | I17: 0 | J17: 0 | K17: 0 | L17: 0 | M17: 0 | N17: 0.3 | O17: 0.3 | P17: 0.3 | Q17: 0.3 | R17: 0.3 | S17: 0.3 | T17: 0.3 | U17: 0.3 | V17: 0.3 | W17: 0.3 | X17: 0.3 | Y17: 0.3 | Z17: 0.3 | AA17: 0.3 | AB17: 0.3 | AC17: 0.3 | AD17: 0.3 | AE17: 0.3 | AF17: 0.3 | AG17: 0.3 | AH17: 0.3 | AI17: 0.3 | AJ17: 0.3 | AK17: 0.3 | AL17: 0.3 | AM17: 0.3 | AN17: 0.3 | AO17: 0.3 | AP17: 0.3 | AQ17: 0.3 | AR17: 0.3 | AS17: 0.3 | AT17: 0.3 | AU17: 0.3 | AV17: 0.3 | AW17: 0.3 | AX17: 0.3 | AY17: 0.3 | AZ17: 0.3 | BA17: 0.3 | BB17: 0.3 | BC17: 0.3 | BD17: 0.3 | BE17: 0.3 | BF17: 0.3 | BG17: 0.3 | BH17: 0.3 | BI17: 0.3
A18: DEX Trading Volume (oz) | B18: 0 | C18: 0 | D18: 0 | E18: 0 | F18: 0 | G18: 0 | H18: 0 | I18: 0 | J18: 0 | K18: 0 | L18: 0 | M18: 0 | N18: =N4*N17 | O18: =O4*O17 | P18: =P4*P17 | Q18: =Q4*Q17 | R18: =R4*R17 | S18: =S4*S17 | T18: =T4*T17 | U18: =U4*U17 | ... BI18: =BI4*BI17
A19: DEX Trading Volume ($) | B19: =B18*XAUconfig!B3 | C19: =C18*XAUconfig!C3 | D19: =D18*XAUconfig!D3 | E19: =E18*XAUconfig!E3 | F19: =F18*XAUconfig!F3 | G19: =G18*XAUconfig!G3 | H19: =H18*XAUconfig!H3 | I19: =I18*XAUconfig!I3 | ... BI19: =BI18*XAUconfig!BI3
A20: Inter-wallet Transfer Volume (oz) | B20: 0 | C20: 0 | D20: 0 | E20: 0 | F20: 0 | G20: 0 | H20: 0 | I20: 0 | J20: 0 | K20: 0 | L20: 0 | M20: 0 | N20: ='Token Supply (5yr)'!N32 | O20: ='Token Supply (5yr)'!O32 | P20: ='Token Supply (5yr)'!P32 | Q20: ='Token Supply (5yr)'!Q32 | R20: ='Token Supply (5yr)'!R32 | S20: ='Token Supply (5yr)'!S32 | T20: ='Token Supply (5yr)'!T32 | U20: ='Token Supply (5yr)'!U32 | ... BI20: ='Token Supply (5yr)'!BI32
A21: Total Token Transfer Volume (oz) | B21: 0 | C21: 0 | D21: 0 | E21: 0 | F21: 0 | G21: 0 | H21: 0 | I21: 0 | J21: 0 | K21: 0 | L21: 0 | M21: 0 | N21: =N18+N20 | O21: =O18+O20 | P21: =P18+P20 | Q21: =Q18+Q20 | R21: =R18+R20 | S21: =S18+S20 | T21: =T18+T20 | U21: =U18+U20 | ... BI21: =BI18+BI20
A22: Token Transfer Fee Gross Revenue (oz) | B22: 0 | C22: 0 | D22: 0 | E22: 0 | F22: 0 | G22: 0 | H22: 0 | I22: 0 | J22: 0 | K22: 0 | L22: 0 | M22: 0 | N22: =N21*Inputs!B29 | O22: =O21*Inputs!B29 | P22: =P21*Inputs!B29 | Q22: =Q21*Inputs!B29 | R22: =R21*Inputs!B29 | S22: =S21*Inputs!B29 | T22: =T21*Inputs!B29 | U22: =U21*Inputs!B29 | V22: =V21*Inputs!B29 | W22: =W21*Inputs!B29 | X22: =X21*Inputs!B29 | Y22: =Y21*Inputs!B29 | Z22: =Z21*Inputs!B29 | AA22: =AA21*Inputs!B29 | AB22: =AB21*Inputs!B29 | AC22: =AC21*Inputs!B29 | AD22: =AD21*Inputs!B29 | AE22: =AE21*Inputs!B29 | AF22: =AF21*Inputs!B29 | AG22: =AG21*Inputs!B29 | AH22: =AH21*Inputs!B29 | AI22: =AI21*Inputs!B29 | AJ22: =AJ21*Inputs!B29 | AK22: =AK21*Inputs!B29 | AL22: =AL21*Inputs!B29 | AM22: =AM21*Inputs!B29 | AN22: =AN21*Inputs!B29 | AO22: =AO21*Inputs!B29 | AP22: =AP21*Inputs!B29 | AQ22: =AQ21*Inputs!B29 | AR22: =AR21*Inputs!B29 | AS22: =AS21*Inputs!B29 | AT22: =AT21*Inputs!B29 | AU22: =AU21*Inputs!B29 | AV22: =AV21*Inputs!B29 | AW22: =AW21*Inputs!B29 | AX22: =AX21*Inputs!B29 | AY22: =AY21*Inputs!B29 | AZ22: =AZ21*Inputs!B29 | BA22: =BA21*Inputs!B29 | BB22: =BB21*Inputs!B29 | BC22: =BC21*Inputs!B29 | BD22: =BD21*Inputs!B29 | BE22: =BE21*Inputs!B29 | BF22: =BF21*Inputs!B29 | BG22: =BG21*Inputs!B29 | BH22: =BH21*Inputs!B29 | BI22: =BI21*Inputs!B29
A23: Token Transfer Fee Net Revenue to RAF (oz) | B23: 0 | C23: 0 | D23: 0 | E23: 0 | F23: 0 | G23: 0 | H23: 0 | I23: 0 | J23: 0 | K23: 0 | L23: 0 | M23: 0 | N23: =N22*RevShare!B9 | O23: =O22*RevShare!B9 | P23: =P22*RevShare!B9 | Q23: =Q22*RevShare!B9 | R23: =R22*RevShare!B9 | S23: =S22*RevShare!B9 | T23: =T22*RevShare!B9 | U23: =U22*RevShare!B9 | V23: =V22*RevShare!B9 | W23: =W22*RevShare!B9 | X23: =X22*RevShare!B9 | Y23: =Y22*RevShare!B9 | Z23: =Z22*RevShare!B9 | AA23: =AA22*RevShare!B9 | AB23: =AB22*RevShare!B9 | AC23: =AC22*RevShare!B9 | AD23: =AD22*RevShare!B9 | AE23: =AE22*RevShare!B9 | AF23: =AF22*RevShare!B9 | AG23: =AG22*RevShare!B9 | AH23: =AH22*RevShare!B9 | AI23: =AI22*RevShare!B9 | AJ23: =AJ22*RevShare!B9 | AK23: =AK22*RevShare!B9 | AL23: =AL22*RevShare!B9 | AM23: =AM22*RevShare!B9 | AN23: =AN22*RevShare!B9 | AO23: =AO22*RevShare!B9 | AP23: =AP22*RevShare!B9 | AQ23: =AQ22*RevShare!B9 | AR23: =AR22*RevShare!B9 | AS23: =AS22*RevShare!B9 | AT23: =AT22*RevShare!B9 | AU23: =AU22*RevShare!B9 | AV23: =AV22*RevShare!B9 | AW23: =AW22*RevShare!B9 | AX23: =AX22*RevShare!B9 | AY23: =AY22*RevShare!B9 | AZ23: =AZ22*RevShare!B9 | BA23: =BA22*RevShare!B9 | BB23: =BB22*RevShare!B9 | BC23: =BC22*RevShare!B9 | BD23: =BD22*RevShare!B9 | BE23: =BE22*RevShare!B9 | BF23: =BF22*RevShare!B9 | BG23: =BG22*RevShare!B9 | BH23: =BH22*RevShare!B9 | BI23: =BI22*RevShare!B9
A24: Token Transfer Fee Net Revenue to RGT (oz) | B24: 0 | C24: 0 | D24: 0 | E24: 0 | F24: 0 | G24: 0 | H24: 0 | I24: 0 | J24: 0 | K24: 0 | L24: 0 | M24: 0 | N24: =N22*RevShare!B10 | O24: =O22*RevShare!B10 | P24: =P22*RevShare!B10 | Q24: =Q22*RevShare!B10 | R24: =R22*RevShare!B10 | S24: =S22*RevShare!B10 | T24: =T22*RevShare!B10 | U24: =U22*RevShare!B10 | V24: =V22*RevShare!B10 | W24: =W22*RevShare!B10 | X24: =X22*RevShare!B10 | Y24: =Y22*RevShare!B10 | Z24: =Z22*RevShare!B10 | AA24: =AA22*RevShare!B10 | AB24: =AB22*RevShare!B10 | AC24: =AC22*RevShare!B10 | AD24: =AD22*RevShare!B10 | AE24: =AE22*RevShare!B10 | AF24: =AF22*RevShare!B10 | AG24: =AG22*RevShare!B10 | AH24: =AH22*RevShare!B10 | AI24: =AI22*RevShare!B10 | AJ24: =AJ22*RevShare!B10 | AK24: =AK22*RevShare!B10 | AL24: =AL22*RevShare!B10 | AM24: =AM22*RevShare!B10 | AN24: =AN22*RevShare!B10 | AO24: =AO22*RevShare!B10 | AP24: =AP22*RevShare!B10 | AQ24: =AQ22*RevShare!B10 | AR24: =AR22*RevShare!B10 | AS24: =AS22*RevShare!B10 | AT24: =AT22*RevShare!B10 | AU24: =AU22*RevShare!B10 | AV24: =AV22*RevShare!B10 | AW24: =AW22*RevShare!B10 | AX24: =AX22*RevShare!B10 | AY24: =AY22*RevShare!B10 | AZ24: =AZ22*RevShare!B10 | BA24: =BA22*RevShare!B10 | BB24: =BB22*RevShare!B10 | BC24: =BC22*RevShare!B10 | BD24: =BD22*RevShare!B10 | BE24: =BE22*RevShare!B10 | BF24: =BF22*RevShare!B10 | BG24: =BG22*RevShare!B10 | BH24: =BH22*RevShare!B10 | BI24: =BI22*RevShare!B10
A25: Swap Fee Gross Revenue (oz) | B25: 0 | C25: 0 | D25: 0 | E25: 0 | F25: 0 | G25: 0 | H25: 0 | I25: 0 | J25: 0 | K25: 0 | L25: 0 | M25: 0 | N25: =N21*Inputs!B38 | O25: =O21*Inputs!B38 | P25: =P21*Inputs!B38 | Q25: =Q21*Inputs!B38 | R25: =R21*Inputs!B38 | S25: =S21*Inputs!B38 | T25: =T21*Inputs!B38 | U25: =U21*Inputs!B38 | V25: =V21*Inputs!B38 | W25: =W21*Inputs!B38 | X25: =X21*Inputs!B38 | Y25: =Y21*Inputs!B38 | Z25: =Z21*Inputs!B38 | AA25: =AA21*Inputs!B38 | AB25: =AB21*Inputs!B38 | AC25: =AC21*Inputs!B38 | AD25: =AD21*Inputs!B38 | AE25: =AE21*Inputs!B38 | AF25: =AF21*Inputs!B38 | AG25: =AG21*Inputs!B38 | AH25: =AH21*Inputs!B38 | AI25: =AI21*Inputs!B38 | AJ25: =AJ21*Inputs!B38 | AK25: =AK21*Inputs!B38 | AL25: =AL21*Inputs!B38 | AM25: =AM21*Inputs!B38 | AN25: =AN21*Inputs!B38 | AO25: =AO21*Inputs!B38 | AP25: =AP21*Inputs!B38 | AQ25: =AQ21*Inputs!B38 | AR25: =AR21*Inputs!B38 | AS25: =AS21*Inputs!B38 | AT25: =AT21*Inputs!B38 | AU25: =AU21*Inputs!B38 | AV25: =AV21*Inputs!B38 | AW25: =AW21*Inputs!B38 | AX25: =AX21*Inputs!B38 | AY25: =AY21*Inputs!B38 | AZ25: =AZ21*Inputs!B38 | BA25: =BA21*Inputs!B38 | BB25: =BB21*Inputs!B38 | BC25: =BC21*Inputs!B38 | BD25: =BD21*Inputs!B38 | BE25: =BE21*Inputs!B38 | BF25: =BF21*Inputs!B38 | BG25: =BG21*Inputs!B38 | BH25: =BH21*Inputs!B38 | BI25: =BI21*Inputs!B38
A26: Swap Fee Net Revenue to RGT (oz) | B26: 0 | C26: 0 | D26: 0 | E26: 0 | F26: 0 | G26: 0 | H26: 0 | I26: 0 | J26: 0 | K26: 0 | L26: 0 | M26: 0 | N26: =N25*N14 | O26: =O25*O14 | P26: =P25*P14 | Q26: =Q25*Q14 | R26: =R25*R14 | S26: =S25*S14 | T26: =T25*T14 | U26: =U25*U14 | ... BI26: =BI25*BI14
A27: MRR from Token Taxes & Swap Fees (oz) | B27: 0 | C27: 0 | D27: 0 | E27: 0 | F27: 0 | G27: 0 | H27: 0 | I27: 0 | J27: 0 | K27: 0 | L27: 0 | M27: 0 | N27: =N22+N26 | O27: =O22+O26 | P27: =P22+P26 | Q27: =Q22+Q26 | R27: =R22+R26 | S27: =S22+S26 | T27: =T22+T26 | U27: =U22+U26 | ... BI27: =BI22+BI26
A29: Token Transfer Fee Gross Revenue ($) | B29: 0 | C29: 0 | D29: 0 | E29: 0 | F29: 0 | G29: 0 | H29: 0 | I29: 0 | J29: 0 | K29: =K22*XAUconfig!K3 | L29: =L22*XAUconfig!L3 | M29: =M22*XAUconfig!M3 | N29: =N22*XAUconfig!N3 | O29: =O22*XAUconfig!O3 | P29: =P22*XAUconfig!P3 | Q29: =Q22*XAUconfig!Q3 | R29: =R22*XAUconfig!R3 | ... BI29: =BI22*XAUconfig!BI3
A30: Token Transfer Fee Net Revenue to RAF ($) | B30: 0 | C30: 0 | D30: 0 | E30: 0 | F30: 0 | G30: 0 | H30: 0 | I30: 0 | J30: 0 | K30: =K23*XAUconfig!K3 | L30: =L23*XAUconfig!L3 | M30: =M23*XAUconfig!M3 | N30: =N23*XAUconfig!N3 | O30: =O23*XAUconfig!O3 | P30: =P23*XAUconfig!P3 | Q30: =Q23*XAUconfig!Q3 | R30: =R23*XAUconfig!R3 | ... BI30: =BI23*XAUconfig!BI3
A31: Token Transfer Fee Net Revenue to RGT ($) | B31: 0 | C31: 0 | D31: 0 | E31: 0 | F31: 0 | G31: 0 | H31: 0 | I31: 0 | J31: 0 | K31: =K24*XAUconfig!K3 | L31: =L24*XAUconfig!L3 | M31: =M24*XAUconfig!M3 | N31: =N24*XAUconfig!N3 | O31: =O24*XAUconfig!O3 | P31: =P24*XAUconfig!P3 | Q31: =Q24*XAUconfig!Q3 | R31: =R24*XAUconfig!R3 | ... BI31: =BI24*XAUconfig!BI3
A32: Swap Fee Gross Revenue ($) | B32: 0 | C32: 0 | D32: 0 | E32: 0 | F32: 0 | G32: 0 | H32: 0 | I32: 0 | J32: 0 | K32: =K25*XAUconfig!K3 | L32: =L25*XAUconfig!L3 | M32: =M25*XAUconfig!M3 | N32: =N25*XAUconfig!N3 | O32: =O25*XAUconfig!O3 | P32: =P25*XAUconfig!P3 | Q32: =Q25*XAUconfig!Q3 | R32: =R25*XAUconfig!R3 | ... BI32: =BI25*XAUconfig!BI3
A33: Swap Fee Net Revenue to RGT ($) | B33: 0 | C33: 0 | D33: 0 | E33: 0 | F33: 0 | G33: 0 | H33: 0 | I33: 0 | J33: 0 | K33: =K26*XAUconfig!K3 | L33: =L26*XAUconfig!L3 | M33: =M26*XAUconfig!M3 | N33: =N26*XAUconfig!N3 | O33: =O26*XAUconfig!O3 | P33: =P26*XAUconfig!P3 | Q33: =Q26*XAUconfig!Q3 | R33: =R26*XAUconfig!R3 | ... BI33: =BI26*XAUconfig!BI3
A34: Gross MRR from Token Taxes & Swap Fees ($) | B34: 0 | C34: 0 | D34: 0 | E34: 0 | F34: 0 | G34: 0 | H34: 0 | I34: 0 | J34: 0 | K34: =K27*XAUconfig!K3 | L34: =L27*XAUconfig!L3 | M34: =M27*XAUconfig!M3 | N34: =N27*XAUconfig!N3 | O34: =O27*XAUconfig!O3 | P34: =P27*XAUconfig!P3 | Q34: =Q27*XAUconfig!Q3 | R34: =R27*XAUconfig!R3 | ... BI34: =BI27*XAUconfig!BI3
A36: CEX Markets
A37: Circulating Marketcap to CEX Volume Ratio | AF37: 3 | AG37: 1 | AH37: 1 | AI37: 2 | AJ37: 2 | AK37: 2 | AL37: 3 | AM37: 3 | AN37: 3 | AO37: 4 | AP37: 4 | AQ37: 4 | AR37: 5 | AS37: 5 | AT37: 5 | AU37: 6 | AV37: 6 | AW37: 6 | AX37: 7 | AY37: 7 | AZ37: 7 | BA37: 8 | BB37: 8 | BC37: 8 | BD37: 9 | BE37: 9 | BF37: 9 | BG37: 10 | BH37: 10 | BI37: 10
A38: CEX Trading Volume ($) | B38: 0 | C38: 0 | D38: 0 | E38: 0 | F38: 0 | G38: 0 | H38: 0 | I38: 0 | J38: 0 | K38: 0 | L38: 0 | M38: 0 | N38: 0 | O38: 0 | P38: 0 | Q38: 0 | R38: 0 | S38: 0 | T38: 0 | U38: 0 | V38: 0 | W38: 0 | X38: 0 | Y38: 0 | Z38: 0 | AA38: 0 | AB38: 0 | AC38: 0 | AD38: 0 | AE38: 0 | AF38: =AF19*AF37 | AG38: =AG19*AG37 | AH38: =AH19*AH37 | AI38: =AI19*AI37 | AJ38: =AJ19*AJ37 | AK38: =AK19*AK37 | AL38: =AL19*AL37 | AM38: =AM19*AM37 | ... BI38: =BI19*BI37
A39: CEX Trading Volume (oz) | B39: 0 | C39: 0 | D39: 0 | E39: 0 | F39: 0 | G39: 0 | H39: 0 | I39: 0 | J39: 0 | K39: 0 | L39: 0 | M39: 0 | N39: 0 | O39: 0 | P39: 0 | Q39: 0 | R39: 0 | S39: 0 | T39: 0 | U39: 0 | V39: 0 | W39: 0 | X39: 0 | Y39: 0 | Z39: 0 | AA39: 0 | AB39: 0 | AC39: 0 | AD39: 0 | AE39: 0 | AF39: =AF38/XAUconfig!AF3 | AG39: =AG38/XAUconfig!AG3 | AH39: =AH38/XAUconfig!AH3 | AI39: =AI38/XAUconfig!AI3 | AJ39: =AJ38/XAUconfig!AJ3 | AK39: =AK38/XAUconfig!AK3 | AL39: =AL38/XAUconfig!AL3 | AM39: =AM38/XAUconfig!AM3 | ... BI39: =BI38/XAUconfig!BI3
A40: Inventory Size | B40: 0 | C40: 0 | D40: 0 | E40: 0 | F40: 0 | G40: 0 | H40: 0 | I40: 0 | J40: 0 | K40: 0 | L40: 0 | M40: 0 | N40: 0 | O40: 0 | P40: 0 | Q40: 0 | R40: 0 | S40: 0 | T40: 0 | U40: 0 | V40: 0 | W40: 0 | X40: 0 | Y40: 0 | Z40: 0 | AA40: 0 | AB40: 0 | AC40: 0 | AD40: 0 | AE40: 0
A41: Holding Costs | B41: 0 | C41: 0 | D41: 0 | E41: 0 | F41: 0 | G41: 0 | H41: 0 | I41: 0 | J41: 0 | K41: 0 | L41: 0 | M41: 0 | N41: 0 | O41: 0 | P41: 0 | Q41: 0 | R41: 0 | S41: 0 | T41: 0 | U41: 0 | V41: 0 | W41: 0 | X41: 0 | Y41: 0 | Z41: 0 | AA41: 0 | AB41: 0 | AC41: 0 | AD41: 0 | AE41: 0
A42: Volatility | B42: 0 | C42: 0 | D42: 0 | E42: 0 | F42: 0 | G42: 0 | H42: 0 | I42: 0 | J42: 0 | K42: 0 | L42: 0 | M42: 0 | N42: 0 | O42: 0 | P42: 0 | Q42: 0 | R42: 0 | S42: 0 | T42: 0 | U42: 0 | V42: 0 | W42: 0 | X42: 0 | Y42: 0 | Z42: 0 | AA42: 0 | AB42: 0 | AC42: 0 | AD42: 0 | AE42: 0
A43: Rebates | B43: 0 | C43: 0 | D43: 0 | E43: 0 | F43: 0 | G43: 0 | H43: 0 | I43: 0 | J43: 0 | K43: 0 | L43: 0 | M43: 0 | N43: 0 | O43: 0 | P43: 0 | Q43: 0 | R43: 0 | S43: 0 | T43: 0 | U43: 0 | V43: 0 | W43: 0 | X43: 0 | Y43: 0 | Z43: 0 | AA43: 0 | AB43: 0 | AC43: 0 | AD43: 0 | AE43: 0
A45: Market Making
A46: % of DEX Volume Captured | B46: 0 | C46: 0 | D46: 0 | E46: 0 | F46: 0 | G46: 0 | H46: 0 | I46: 0 | J46: 0 | K46: 0.1 | L46: 0.1 | M46: 0.1 | N46: 0.1 | O46: 0.1 | P46: 0.1 | Q46: 0.1 | R46: 0.1 | S46: 0.1 | T46: 0.1 | U46: 0.1 | V46: 0.1 | W46: 0.1 | X46: 0.1 | Y46: 0.1 | Z46: 0.1 | AA46: 0.1 | AB46: 0.1 | AC46: 0.1 | AD46: 0.1 | AE46: 0.1 | AF46: 0.1 | AG46: 0.1 | AH46: 0.1 | AI46: 0.1 | AJ46: 0.1 | AK46: 0.1 | AL46: 0.1 | AM46: 0.1 | AN46: 0.1 | AO46: 0.1 | AP46: 0.1 | AQ46: 0.1 | AR46: 0.1 | AS46: 0.1 | AT46: 0.1 | AU46: 0.1 | AV46: 0.1 | AW46: 0.1 | AX46: 0.1 | AY46: 0.1 | AZ46: 0.1 | BA46: 0.1 | BB46: 0.1 | BC46: 0.1 | BD46: 0.1 | BE46: 0.1 | BF46: 0.1 | BG46: 0.1 | BH46: 0.1 | BI46: 0.1
A47: DEX MM Bot Trading Volume (oz) | B47: 0 | C47: 0 | D47: 0 | E47: 0 | F47: 0 | G47: 0 | H47: 0 | I47: 0 | J47: 0 | K47: =K18*K46 | L47: =L18*L46 | M47: =M18*M46 | N47: =N18*N46 | O47: =O18*O46 | P47: =P18*P46 | Q47: =Q18*Q46 | R47: =R18*R46 | ... BI47: =BI18*BI46
A48: % of CEX Volume Captured | B48: 0 | C48: 0 | D48: 0 | E48: 0 | F48: 0 | G48: 0 | H48: 0 | I48: 0 | J48: 0 | K48: 0 | L48: 0 | M48: 0 | N48: 0 | O48: 0 | P48: 0 | Q48: 0 | R48: 0 | S48: 0 | T48: 0 | U48: 0 | V48: 0 | W48: 0 | X48: 0 | Y48: 0 | Z48: 0 | AA48: 0 | AB48: 0 | AC48: 0 | AD48: 0 | AE48: 0 | AF48: 0.05 | AG48: 0.05 | AH48: 0.05 | AI48: 0.05 | AJ48: 0.05 | AK48: 0.05 | AL48: 0.05 | AM48: 0.05 | AN48: 0.05 | AO48: 0.05 | AP48: 0.05 | AQ48: 0.025 | AR48: 0.025 | AS48: 0.025 | AT48: 0.025 | AU48: 0.025 | AV48: 0.025 | AW48: 0.025 | AX48: 0.025 | AY48: 0.025 | AZ48: 0.025 | BA48: 0.025 | BB48: 0.025 | BC48: 0.025 | BD48: 0.025 | BE48: 0.025 | BF48: 0.025 | BG48: 0.025 | BH48: 0.025 | BI48: 0.025
A49: CEX MM Bot Trading Volume (oz) | B49: 0 | C49: 0 | D49: 0 | E49: 0 | F49: 0 | G49: 0 | H49: 0 | I49: 0 | J49: 0 | K49: 0 | L49: 0 | M49: 0 | N49: 0 | O49: 0 | P49: 0 | Q49: 0 | R49: 0 | S49: 0 | T49: 0 | U49: 0 | V49: 0 | W49: 0 | X49: 0 | Y49: 0 | Z49: 0 | AA49: 0 | AB49: 0 | AC49: 0 | AD49: 0 | AE49: 0 | AF49: =AF39*AF48 | AG49: =AG39*AG48 | AH49: =AH39*AH48 | AI49: =AI39*AI48 | AJ49: =AJ39*AJ48 | AK49: =AK39*AK48 | AL49: =AL39*AL48 | AM49: =AM39*AM48 | ... BI49: =BI39*BI48
A50: Total MM Bot Trading Volume (oz) | B50: =B47+B49 | C50: =C47+C49 | D50: =D47+D49 | E50: =E47+E49 | F50: =F47+F49 | G50: =G47+G49 | H50: =H47+H49 | I50: =I47+I49 | ... BI50: =BI47+BI49
A51: Spread per Ounce | B51: =B48+B50 | C51: =C48+C50 | D51: =D48+D50 | E51: =E48+E50 | F51: =F48+F50 | G51: =G48+G50 | H51: =H48+H50 | I51: =I48+I50 | J51: =J48+J50 | K51: =1+(1*Inputs!B42)-(1*Inputs!B41)-(1*Inputs!B29)-(1*Inputs!B38) | L51: =1+(1*Inputs!B42)-(1*Inputs!B41)-(1*Inputs!B29)-(1*Inputs!B38) | M51: =1+(1*Inputs!B42)-(1*Inputs!B41)-(1*Inputs!B29)-(1*Inputs!B38) | N51: =1+(1*Inputs!B42)-(1*Inputs!B41)-(1*Inputs!B29)-(1*Inputs!B38) | O51: =1+(1*Inputs!B42)-(1*Inputs!B41)-(1*Inputs!B29)-(1*Inputs!B38) | P51: =1+(1*Inputs!B42)-(1*Inputs!B41)-(1*Inputs!B29)-(1*Inputs!B38) | Q51: =1+(1*Inputs!B42)-(1*Inputs!B41)-(1*Inputs!B29)-(1*Inputs!B38) | R51: =1+(1*Inputs!B42)-(1*Inputs!B41)-(1*Inputs!B29)-(1*Inputs!B38) | S51: =1+(1*Inputs!B42)-(1*Inputs!B41)-(1*Inputs!B29)-(1*Inputs!B38) | T51: =1+(1*Inputs!B42)-(1*Inputs!B41)-(1*Inputs!B29)-(1*Inputs!B38) | U51: =1+(1*Inputs!B42)-(1*Inputs!B41)-(1*Inputs!B29)-(1*Inputs!B38) | V51: =1+(1*Inputs!B42)-(1*Inputs!B41)-(1*Inputs!B29)-(1*Inputs!B38) | W51: =Inputs!B43 | X51: =Inputs!B43 | Y51: =Inputs!B43 | Z51: =Inputs!B43 | AA51: =Inputs!B43 | AB51: =Inputs!B43 | AC51: =Inputs!B43 | AD51: =Inputs!B43 | AE51: =Inputs!B43 | AF51: =Inputs!B43 | AG51: =Inputs!B43 | AH51: =Inputs!B43 | AI51: =Inputs!B43 | AJ51: =Inputs!B43 | AK51: =Inputs!B43 | AL51: =Inputs!B43 | AM51: =Inputs!B43 | AN51: =Inputs!B43 | AO51: =Inputs!B43 | AP51: =Inputs!B43 | AQ51: =Inputs!B43 | AR51: =Inputs!B43 | AS51: =Inputs!B43 | AT51: =Inputs!B43 | AU51: =Inputs!B43 | AV51: =Inputs!B43 | AW51: =Inputs!B43 | AX51: =Inputs!B43 | AY51: =Inputs!B43 | AZ51: =Inputs!B43 | BA51: =Inputs!B43 | BB51: =Inputs!B43 | BC51: =Inputs!B43 | BD51: =Inputs!B43 | BE51: =Inputs!B43 | BF51: =Inputs!B43 | BG51: =Inputs!B43 | BH51: =Inputs!B43 | BI51: =Inputs!B43
A52: Gross Market Making Profit (oz) | B52: =B49+B51 | C52: =C49+C51 | D52: =D49+D51 | E52: =E49+E51 | F52: =F49+F51 | G52: =G49+G51 | H52: =H49+H51 | I52: =I49+I51 | J52: =J49+J51 | K52: =(K50*K51)-K50 | L52: =(L50*L51)-L50 | M52: =(M50*M51)-M50 | N52: =(N50*N51)-N50 | O52: =(O50*O51)-O50 | P52: =(P50*P51)-P50 | Q52: =(Q50*Q51)-Q50 | R52: =(R50*R51)-R50 | ... BI52: =(BI50*BI51)-BI50
A53: Gross Market Making Profit ($) | B53: =B50+B52 | C53: =C50+C52 | D53: =D50+D52 | E53: =E50+E52 | F53: =F50+F52 | G53: =G50+G52 | H53: =H50+H52 | I53: =I50+I52 | J53: =J50+J52 | K53: =K52*XAUconfig!K3 | L53: =L52*XAUconfig!L3 | M53: =M52*XAUconfig!M3 | N53: =N52*XAUconfig!N3 | O53: =O52*XAUconfig!O3 | P53: =P52*XAUconfig!P3 | Q53: =Q52*XAUconfig!Q3 | R53: =R52*XAUconfig!R3 | ... BI53: =BI52*XAUconfig!BI3
A89: New Wallets Added | B89: 0 | C89: 0 | D89: 0 | E89: 0 | F89: 0
A90: Active Wallets (monthly)
A91: Active Transactions per Wallet (Monthly)
A92: RealGold Holders (Cumulative)

Sheet RA LLC Cashflow
A1: Regen Assets Cashflow (5yr) | B1: =XAUconfig!B4 | C1: =XAUconfig!C4 | D1: =XAUconfig!D4 | E1: =XAUconfig!E4 | F1: =XAUconfig!F4 | G1: =XAUconfig!G4 | H1: =XAUconfig!H4 | I1: =XAUconfig!I4 | ... BI1: =XAUconfig!BI4
A2: Personnel Expenditures
A3: Exec / Tech Director | B3: 0 | C3: 0 | D3: 0 | E3: 0 | F3: 0 | G3: 0 | H3: 0 | I3: 0 | J3: 0 | K3: 0 | L3: 0 | M3: =Personnel!D21 | N3: =Personnel!D21 | O3: =Personnel!D21 | P3: =Personnel!D21 | Q3: =Personnel!D21 | R3: =Personnel!D21 | S3: =Personnel!D21 | T3: =Personnel!D21 | U3: =Personnel!D21 | V3: =Personnel!D21 | W3: =Personnel!D21 | X3: =Personnel!D21 | Y3: =Personnel!D21 | Z3: =Personnel!D21 | AA3: =Personnel!D21 | AB3: =Personnel!D21 | AC3: =Personnel!D21 | AD3: =Personnel!D21 | AE3: =Personnel!D21 | AF3: 0 | AG3: 0 | AH3: 0 | AI3: 0 | AJ3: 0 | AK3: 0 | AL3: 0 | AM3: 0 | AN3: 0 | AO3: 0 | AP3: 0 | AQ3: 0 | AR3: 0 | AS3: 0 | AT3: 0 | AU3: 0 | AV3: 0 | AW3: 0 | AX3: 0 | AY3: 0 | AZ3: 0 | BA3: 0 | BB3: 0 | BC3: 0 | BD3: 0 | BE3: 0 | BF3: 0 | BG3: 0 | BH3: 0 | BI3: 0
A4: Brand Director (RealGold) | B4: 6000 | C4: 3000 | D4: 3000 | E4: 3000 | F4: 3000 | G4: 3000 | H4: 3000 | I4: 3000 | J4: 6000 | K4: 6000 | L4: 3000 | M4: 6000 | N4: 0 | O4: 0 | P4: 0 | Q4: 0 | R4: 0 | S4: 0 | T4: 0 | U4: 0 | V4: 0 | W4: 0 | X4: 0 | Y4: 0 | Z4: 0 | AA4: 0 | AB4: 0 | AC4: 0 | AD4: 0 | AE4: 0 | AF4: 0 | AG4: 0 | AH4: 0 | AI4: 0 | AJ4: 0 | AK4: 0 | AL4: 0 | AM4: 0 | AN4: 0 | AO4: 0 | AP4: 0 | AQ4: 0 | AR4: 0 | AS4: 0 | AT4: 0 | AU4: 0 | AV4: 0 | AW4: 0 | AX4: 0 | AY4: 0 | AZ4: 0 | BA4: 0 | BB4: 0 | BC4: 0 | BD4: 0 | BE4: 0 | BF4: 0 | BG4: 0 | BH4: 0 | BI4: 0
A5: Fundraising Director (RealGold) | B5: 0 | C5: 0 | D5: 0 | E5: 0 | F5: 0 | G5: 0 | H5: 0 | I5: 1000 | J5: 5000 | K5: 5000 | L5: 3000 | M5: 5000 | N5: 0 | O5: 0 | P5: 0 | Q5: 0 | R5: 0 | S5: 0 | T5: 0 | U5: 0 | V5: 0 | W5: 0 | X5: 0 | Y5: 0 | Z5: 0 | AA5: 0 | AB5: 0 | AC5: 0 | AD5: 0 | AE5: 0 | AF5: 0 | AG5: 0 | AH5: 0 | AI5: 0 | AJ5: 0 | AK5: 0 | AL5: 0 | AM5: 0 | AN5: 0 | AO5: 0 | AP5: 0 | AQ5: 0 | AR5: 0 | AS5: 0 | AT5: 0 | AU5: 0 | AV5: 0 | AW5: 0 | AX5: 0 | AY5: 0 | AZ5: 0 | BA5: 0 | BB5: 0 | BC5: 0 | BD5: 0 | BE5: 0 | BF5: 0 | BG5: 0 | BH5: 0 | BI5: 0
A6: Prospecting Director (RealGold) | B6: 0 | C6: 0 | D6: 0 | E6: 0 | F6: 0 | G6: 0 | H6: 0 | I6: 0 | J6: 2500 | K6: 2500 | L6: 1250 | M6: 5000
A7: Front-end Developer | B7: 0 | C7: 0 | D7: 0 | E7: 0 | F7: 0 | G7: 0 | H7: 0 | I7: 0 | J7: 0 | K7: 0 | L7: 0 | M7: 0 | N7: 0 | O7: 0 | P7: 0 | Q7: 0 | R7: 0 | S7: 0 | T7: 0 | U7: 0 | V7: 0 | W7: =Personnel!D24 | X7: =Personnel!D24 | Y7: =Personnel!D24 | Z7: 0 | AA7: 0 | AB7: 0 | AC7: 0 | AD7: 0 | AE7: 0 | AF7: 0 | AG7: 0 | AH7: 0 | AI7: 0 | AJ7: 0 | AK7: 0 | AL7: 0 | AM7: 0 | AN7: 0 | AO7: 0 | AP7: 0 | AQ7: 0 | AR7: 0 | AS7: 0 | AT7: 0 | AU7: 0 | AV7: 0 | AW7: 0 | AX7: 0 | AY7: 0 | AZ7: 0 | BA7: 0 | BB7: 0 | BC7: 0 | BD7: 0 | BE7: 0 | BF7: 0 | BG7: 0 | BH7: 0 | BI7: 0
A8: Rust Developer (Registry) | B8: 0 | C8: 0 | D8: 0 | E8: 0 | F8: 0 | G8: 0 | H8: 0 | I8: 0 | J8: 0 | K8: 0 | L8: 0 | M8: 0 | N8: 0 | O8: =Personnel!D22 | P8: =Personnel!D22 | Q8: =Personnel!D22 | R8: =Personnel!D22 | S8: =Personnel!D22 | T8: =Personnel!D22 | U8: =Personnel!D22 | V8: =Personnel!D22 | W8: =Personnel!D22 | X8: =Personnel!D22 | Y8: =Personnel!D22 | Z8: =Personnel!D22 | AA8: =Personnel!D22 | AB8: =Personnel!D22 | AC8: =Personnel!D22 | AD8: =Personnel!D22 | AE8: =Personnel!D22 | AF8: =Personnel!D22 | AG8: =Personnel!D22 | AH8: =Personnel!D22 | AI8: =Personnel!D22 | AJ8: =Personnel!D22 | AK8: =Personnel!D22 | AL8: =Personnel!D22 | AM8: =Personnel!D22 | AN8: =Personnel!D22 | AO8: =Personnel!D22 | AP8: =Personnel!D22 | AQ8: =Personnel!D22 | AR8: =Personnel!D22 | AS8: =Personnel!D22 | AT8: =Personnel!D22 | AU8: =Personnel!D22 | AV8: =Personnel!D22 | AW8: =Personnel!D22 | AX8: =Personnel!D22 | AY8: =Personnel!D22 | AZ8: =Personnel!D22 | BA8: =Personnel!D22 | BB8: =Personnel!D22 | BC8: =Personnel!D22 | BD8: =Personnel!D22 | BE8: =Personnel!D22 | BF8: =Personnel!D22 | BG8: =Personnel!D22 | BH8: =Personnel!D22 | BI8: =Personnel!D22
A9: Blockchain Developer (Smart Treasury) | B9: 0 | C9: 0 | D9: 0 | E9: 0 | F9: 0 | G9: 0 | H9: 0 | I9: 0 | J9: 0 | K9: 0 | L9: 0 | M9: 0 | N9: 0 | O9: =Personnel!D23 | P9: =Personnel!D23 | Q9: =Personnel!D23 | R9: =Personnel!D23 | S9: =Personnel!D23 | T9: =Personnel!D23 | U9: =Personnel!D23 | V9: =Personnel!D23 | W9: =Personnel!D23 | X9: =Personnel!D23 | Y9: =Personnel!D23 | Z9: 0 | AA9: 0 | AB9: 0 | AC9: 0 | AD9: 0 | AE9: 0 | AF9: 0 | AG9: 0 | AH9: 0 | AI9: 0 | AJ9: 0 | AK9: 0 | AL9: 0 | AM9: 0 | AN9: 0 | AO9: 0 | AP9: 0 | AQ9: 0 | AR9: 0 | AS9: 0 | AT9: 0 | AU9: 0 | AV9: 0 | AW9: 0 | AX9: 0 | AY9: 0 | AZ9: 0 | BA9: 0 | BB9: 0 | BC9: 0 | BD9: 0 | BE9: 0 | BF9: 0 | BG9: 0 | BH9: 0 | BI9: 0
A10: Total Personnel Stipends | B10: =SUM(B3:B9) | C10: =SUM(C3:C9) | D10: =SUM(D3:D9) | E10: =SUM(E3:E9) | F10: =SUM(F3:F9) | G10: =SUM(G3:G9) | H10: =SUM(H3:H9) | I10: =SUM(I3:I9) | ... BI10: =SUM(BI3:BI9)
A12: Expenditures
A13: January Retreat / Feb Travel | B13: 15000 | C13: 0 | D13: 0 | E13: 0 | F13: 0 | G13: 0 | H13: 0
A14: Registered Agent, State Filing Fees, Etc. | B14: 0 | C14: 0 | D14: 0 | E14: 0 | F14: 0 | G14: 0 | H14: 0 | I14: 349 | J14: 0 | K14: 0 | L14: 0 | M14: 0 | N14: 0 | O14: 0 | P14: 0 | Q14: 0 | R14: 0 | S14: 0 | T14: 0 | U14: 0 | V14: 0 | W14: 0 | X14: 0 | Y14: 0 | Z14: 0 | AA14: 0 | AB14: 0 | AC14: 0 | AD14: 0 | AE14: 0 | AF14: 0 | AG14: 0 | AH14: 0 | AI14: 0 | AJ14: 0 | AK14: 0 | AL14: 0 | AM14: 0 | AN14: 0 | AO14: 0 | AP14: 0 | AQ14: 0 | AR14: 0 | AS14: 0 | AT14: 0 | AU14: 0 | AV14: 0 | AW14: 0 | AX14: 0 | AY14: 0 | AZ14: 0 | BA14: 0 | BB14: 0 | BC14: 0 | BD14: 0 | BE14: 0 | BF14: 0 | BG14: 0 | BH14: 0 | BI14: 0
A15: Trademarks & Patents | B15: 0 | C15: 0 | D15: 0 | E15: 0 | F15: 0 | G15: 0 | H15: 0 | I15: 0 | J15: 4012 | K15: 0 | L15: 0 | M15: 0 | N15: 0 | O15: 0 | P15: 0 | Q15: 0 | R15: 0 | S15: 0 | T15: 0 | U15: 0 | V15: 0 | W15: 0 | X15: 0 | Y15: 0 | Z15: 0 | AA15: 0 | AB15: 0 | AC15: 0 | AD15: 0 | AE15: 0 | AF15: 0 | AG15: 0 | AH15: 0 | AI15: 0 | AJ15: 0 | AK15: 0 | AL15: 0 | AM15: 0 | AN15: 0 | AO15: 0 | AP15: 0 | AQ15: 0 | AR15: 0 | AS15: 0 | AT15: 0 | AU15: 0 | AV15: 0 | AW15: 0 | AX15: 0 | AY15: 0 | AZ15: 0 | BA15: 0 | BB15: 0 | BC15: 0 | BD15: 0 | BE15: 0 | BF15: 0 | BG15: 0 | BH15: 0 | BI15: 0
A16: Team Travel | B16: 5000 | C16: 3000 | D16: 0 | E16: 0 | F16: 0 | G16: 0 | H16: 0 | I16: 0 | J16: 942.37 | K16: 0 | L16: 0 | M16: 0 | N16: 0 | O16: 0 | P16: 0 | Q16: 0 | R16: 0 | S16: 0 | T16: 0 | U16: 0 | V16: 0 | W16: 0 | X16: 0 | Y16: 0 | Z16: 0 | AA16: 0 | AB16: 0 | AC16: 0 | AD16: 0 | AE16: 0 | AF16: 0 | AG16: 0 | AH16: 0 | AI16: 0 | AJ16: 0 | AK16: 0 | AL16: 0 | AM16: 0 | AN16: 0 | AO16: 0 | AP16: 0 | AQ16: 0 | AR16: 0 | AS16: 0 | AT16: 0 | AU16: 0 | AV16: 0 | AW16: 0 | AX16: 0 | AY16: 0 | AZ16: 0 | BA16: 0 | BB16: 0 | BC16: 0 | BD16: 0 | BE16: 0 | BF16: 0 | BG16: 0 | BH16: 0 | BI16: 0
A17: External Tech Contractors | B17: 0 | C17: 0 | D17: 0 | E17: 0 | F17: 0 | G17: 0 | H17: 0 | I17: 0 | J17: 0 | K17: 0 | L17: 0 | M17: 0 | N17: 0 | O17: 0 | P17: 0 | Q17: 0 | R17: 0 | S17: 0 | T17: 0 | U17: 0 | V17: 0 | W17: 0 | X17: 0 | Y17: 0 | Z17: 0 | AA17: 0 | AB17: 0 | AC17: 0 | AD17: 0 | AE17: 0 | AF17: 0 | AG17: 0 | AH17: 0 | AI17: 0 | AJ17: 0 | AK17: 0 | AL17: 0 | AM17: 0 | AN17: 0 | AO17: 0 | AP17: 0 | AQ17: 0 | AR17: 0 | AS17: 0 | AT17: 0 | AU17: 0 | AV17: 0 | AW17: 0 | AX17: 0 | AY17: 0 | AZ17: 0 | BA17: 0 | BB17: 0 | BC17: 0 | BD17: 0 | BE17: 0 | BF17: 0 | BG17: 0 | BH17: 0 | BI17: 0
A18: External Design Support | B18: 0 | C18: 0 | D18: 0 | E18: 0 | F18: 0 | G18: 0 | H18: 0 | I18: 0 | J18: 0 | K18: 0 | L18: 0 | M18: 0 | N18: 0 | O18: 0 | P18: 0 | Q18: 0 | R18: 0 | S18: 0 | T18: 0 | U18: 0 | V18: 0 | W18: 0 | X18: 0 | Y18: 0 | Z18: 0 | AA18: 0 | AB18: 0 | AC18: 0 | AD18: 0 | AE18: 0 | AF18: 0 | AG18: 0 | AH18: 0 | AI18: 0 | AJ18: 0 | AK18: 0 | AL18: 0 | AM18: 0 | AN18: 0 | AO18: 0 | AP18: 0 | AQ18: 0 | AR18: 0 | AS18: 0 | AT18: 0 | AU18: 0 | AV18: 0 | AW18: 0 | AX18: 0 | AY18: 0 | AZ18: 0 | BA18: 0 | BB18: 0 | BC18: 0 | BD18: 0 | BE18: 0 | BF18: 0 | BG18: 0 | BH18: 0 | BI18: 0
A19: External Legal Cousel | B19: 0 | C19: 0 | D19: 0 | E19: 0 | F19: 0 | G19: 0 | H19: 0 | I19: 5000 | J19: 0 | K19: 0 | L19: 2900 | M19: 0 | N19: 0 | O19: 0 | P19: 0 | Q19: 0 | R19: 0 | S19: 0 | T19: 0 | U19: 0 | V19: 0 | W19: 0 | X19: 0 | Y19: 0 | Z19: 0 | AA19: 0 | AB19: 0 | AC19: 0 | AD19: 0 | AE19: 0 | AF19: 0 | AG19: 0 | AH19: 0 | AI19: 0 | AJ19: 0 | AK19: 0 | AL19: 0 | AM19: 0 | AN19: 0 | AO19: 0 | AP19: 0 | AQ19: 0 | AR19: 0 | AS19: 0 | AT19: 0 | AU19: 0 | AV19: 0 | AW19: 0 | AX19: 0 | AY19: 0 | AZ19: 0 | BA19: 0 | BB19: 0 | BC19: 0 | BD19: 0 | BE19: 0 | BF19: 0 | BG19: 0 | BH19: 0 | BI19: 0
A20: Regulatory Filings & Compliance | B20: 0 | C20: 0 | D20: 0 | E20: 0 | F20: 0 | G20: 0 | H20: 0 | I20: 0 | J20: 0 | K20: 0 | L20: 0 | M20: 10000 | N20: 10000 | O20: 10000 | P20: 0 | Q20: 0 | R20: 0 | S20: 0 | T20: 0 | U20: 0 | V20: 0 | W20: 0 | X20: 0 | Y20: 0 | Z20: 0 | AA20: 0 | AB20: 0 | AC20: 0 | AD20: 0 | AE20: 0 | AF20: 0 | AG20: 0 | AH20: 0 | AI20: 0 | AJ20: 0 | AK20: 0 | AL20: 0 | AM20: 0 | AN20: 0 | AO20: 0 | AP20: 0 | AQ20: 0 | AR20: 0 | AS20: 0 | AT20: 0 | AU20: 0 | AV20: 0 | AW20: 0 | AX20: 0 | AY20: 0 | AZ20: 0 | BA20: 0 | BB20: 0 | BC20: 0 | BD20: 0 | BE20: 0 | BF20: 0 | BG20: 0 | BH20: 0 | BI20: 0
A21: Tech Infrastructure, Hardware, Software | B21: 0 | C21: 100 | D21: 100 | E21: 180 | F21: 200 | G21: 200 | H21: 200 | I21: 0 | J21: 0 | K21: 0 | L21: 0 | M21: 0 | N21: 0 | O21: 0 | P21: 0 | Q21: 0 | R21: 0 | S21: 0 | T21: 0 | U21: 0 | V21: 0 | W21: 0 | X21: 0 | Y21: 0 | Z21: 0 | AA21: 0 | AB21: 0 | AC21: 0 | AD21: 0 | AE21: 0 | AF21: 0 | AG21: 0 | AH21: 0 | AI21: 0 | AJ21: 0 | AK21: 0 | AL21: 0 | AM21: 0 | AN21: 0 | AO21: 0 | AP21: 0 | AQ21: 0 | AR21: 0 | AS21: 0 | AT21: 0 | AU21: 0 | AV21: 0 | AW21: 0 | AX21: 0 | AY21: 0 | AZ21: 0 | BA21: 0 | BB21: 0 | BC21: 0 | BD21: 0 | BE21: 0 | BF21: 0 | BG21: 0 | BH21: 0 | BI21: 0
A22: FEA Affiliate Membership | B22: 0 | C22: 0 | D22: 0 | E22: 0 | F22: 0 | G22: 0 | H22: 0 | I22: 2795 | J22: 0 | K22: 0 | L22: 0 | M22: 0 | N22: 0 | O22: 0 | P22: 0 | Q22: 0 | R22: 0 | S22: 0 | T22: 0 | U22: 0 | V22: 0 | W22: 0 | X22: 0 | Y22: 0 | Z22: 0 | AA22: 0 | AB22: 0 | AC22: 0 | AD22: 0 | AE22: 0 | AF22: 0 | AG22: 0 | AH22: 0 | AI22: 0 | AJ22: 0 | AK22: 0 | AL22: 0 | AM22: 0 | AN22: 0 | AO22: 0 | AP22: 0 | AQ22: 0 | AR22: 0 | AS22: 0 | AT22: 0 | AU22: 0 | AV22: 0 | AW22: 0 | AX22: 0 | AY22: 0 | AZ22: 0 | BA22: 0 | BB22: 0 | BC22: 0 | BD22: 0 | BE22: 0 | BF22: 0 | BG22: 0 | BH22: 0 | BI22: 0
A23: External Accounting Counsel | B23: 0 | C23: 0 | D23: 0 | E23: 0 | F23: 0 | G23: 0 | H23: 0 | I23: 0 | J23: 0 | K23: 0 | L23: 0 | M23: 0 | N23: 0 | O23: 0 | P23: 0 | Q23: 0 | R23: 0 | S23: 0 | T23: 0 | U23: 0 | V23: 0 | W23: 0 | X23: 0 | Y23: 0 | Z23: 0 | AA23: 0 | AB23: 0 | AC23: 0 | AD23: 0 | AE23: 0 | AF23: 0 | AG23: 0 | AH23: 0 | AI23: 0 | AJ23: 0 | AK23: 0 | AL23: 0 | AM23: 0 | AN23: 0 | AO23: 0 | AP23: 0 | AQ23: 0 | AR23: 0 | AS23: 0 | AT23: 0 | AU23: 0 | AV23: 0 | AW23: 0 | AX23: 0 | AY23: 0 | AZ23: 0 | BA23: 0 | BB23: 0 | BC23: 0 | BD23: 0 | BE23: 0 | BF23: 0 | BG23: 0 | BH23: 0 | BI23: 0
A24: Insurance (general, D&O) | B24: 0 | C24: 0 | D24: 0 | E24: 0 | F24: 0 | G24: 0 | H24: 0 | I24: 0 | J24: 200 | K24: 200 | L24: 200 | M24: 200 | N24: 200 | O24: 200 | P24: 200 | Q24: 200 | R24: 200 | S24: 200 | T24: 200 | U24: 200 | V24: 200 | W24: 200 | X24: 200 | Y24: 200 | Z24: 200 | AA24: 200 | AB24: 200 | AC24: 200 | AD24: 200 | AE24: 200 | AF24: 200 | AG24: 200 | AH24: 200 | AI24: 200 | AJ24: 200 | AK24: 200 | AL24: 200 | AM24: 200 | AN24: 200 | AO24: 200 | AP24: 200 | AQ24: 200 | AR24: 200 | AS24: 200 | AT24: 200 | AU24: 200 | AV24: 200 | AW24: 200 | AX24: 200 | AY24: 200 | AZ24: 200 | BA24: 200 | BB24: 200 | BC24: 200 | BD24: 200 | BE24: 200 | BF24: 200 | BG24: 200 | BH24: 200 | BI24: 200
A25: Contingency (10%) | B25: 0 | C25: 0 | D25: 0 | E25: 0 | F25: 0 | G25: 0 | H25: =sum(H14:H24)*0.1 | I25: 0 | J25: 0 | K25: =sum(K14:K24)*0.1 | L25: =sum(L14:L24)*0.1 | M25: =sum(M14:M24)*0.1 | N25: =sum(N14:N24)*0.1 | O25: =sum(O14:O24)*0.1 | P25: =sum(P14:P24)*0.1 | Q25: =sum(Q14:Q24)*0.1 | R25: =sum(R14:R24)*0.1 | ... BI25: =sum(BI14:BI24)*0.1
A26: Total Expenditures | B26: =SUM(B13:B25) | C26: =SUM(C13:C25) | D26: =SUM(D13:D25) | E26: =SUM(E13:E25) | F26: =SUM(F13:F25) | G26: =SUM(G13:G25) | H26: =SUM(H13:H25) | I26: =SUM(I14:I25) | J26: =SUM(J14:J25) | K26: =SUM(K14:K25) | L26: =SUM(L14:L25) | M26: =SUM(M14:M25) | N26: =SUM(N14:N25) | O26: =SUM(O14:O25) | P26: =SUM(P14:P25) | ... BI26: =SUM(BI14:BI25)
A28: Capital Activities
A29: Investment Tranches | B29: =Capital!C2 | C29: 0 | D29: 0 | E29: 0 | F29: 0 | G29: 0 | H29: 0 | I29: =sum(Capital!C3:C5) | J29: =sum(Capital!C6:Capital!C8) | K29: =Capital!C11 | L29: =Capital!C13 | M29: 100000 | N29: =Capital!C13 | O29: 0 | P29: 0 | Q29: 0 | R29: 0 | S29: 0 | T29: 0 | U29: 0 | V29: 0 | W29: 0 | X29: 0 | Y29: 0 | Z29: 0 | AA29: 0 | AB29: 0 | AC29: 0 | AD29: 0 | AE29: 0 | AF29: 0 | AG29: 0 | AH29: 0 | AI29: 0 | AJ29: 0 | AK29: 0 | AL29: 0 | AM29: 0 | AN29: 0 | AO29: 0 | AP29: 0 | AQ29: 0 | AR29: 0 | AS29: 0 | AT29: 0 | AU29: 0 | AV29: 0 | AW29: 0 | AX29: 0 | AY29: 0 | AZ29: 0 | BA29: 0 | BB29: 0 | BC29: 0 | BD29: 0 | BE29: 0 | BF29: 0 | BG29: 0 | BH29: 0 | BI29: 0
A30: Capitalization to Real Assets Foundation | B30: 0 | C30: 0 | D30: 0 | E30: 0 | F30: 0 | G30: 0 | H30: 0 | I30: 0 | J30: -30000 | K30: -100000 | L30: -100000 | M30: 0 | N30: 0 | O30: 0 | P30: 0 | Q30: 0 | R30: 0 | S30: 0 | T30: 0 | U30: 0 | V30: 0 | W30: 0 | X30: 0 | Y30: 0 | Z30: 0 | AA30: 0 | AB30: 0 | AC30: 0 | AD30: 0 | AE30: 0 | AF30: 0 | AG30: 0 | AH30: 0 | AI30: 0 | AJ30: 0 | AK30: 0 | AL30: 0 | AM30: 0 | AN30: 0 | AO30: 0 | AP30: 0 | AQ30: 0 | AR30: 0 | AS30: 0 | AT30: 0 | AU30: 0 | AV30: 0 | AW30: 0 | AX30: 0 | AY30: 0 | AZ30: 0 | BA30: 0 | BB30: 0 | BC30: 0 | BD30: 0 | BE30: 0 | BF30: 0 | BG30: 0 | BH30: 0 | BI30: 0
A31: Capitalization to RealGold Treasury | B31: 0 | C31: 0 | D31: 0 | E31: 0 | F31: 0 | G31: 0 | H31: 0 | I31: 0 | J31: 0 | K31: 0 | L31: -400000 | M31: -100000 | N31: -500000 | O31: 0 | P31: 0 | Q31: 0 | R31: 0 | S31: 0 | T31: 0 | U31: 0 | V31: 0 | W31: 0 | X31: 0 | Y31: 0 | Z31: 0 | AA31: 0 | AB31: 0 | AC31: 0 | AD31: 0 | AE31: 0 | AF31: 0 | AG31: 0 | AH31: 0 | AI31: 0 | AJ31: 0 | AK31: 0 | AL31: 0 | AM31: 0 | AN31: 0 | AO31: 0 | AP31: 0 | AQ31: 0 | AR31: 0 | AS31: 0 | AT31: 0 | AU31: 0 | AV31: 0 | AW31: 0 | AX31: 0 | AY31: 0 | AZ31: 0 | BA31: 0 | BB31: 0 | BC31: 0 | BD31: 0 | BE31: 0 | BF31: 0 | BG31: 0 | BH31: 0 | BI31: 0
A32: Total Capital Activities | B32: =SUM(B29:B31) | C32: =SUM(C30:C31) | D32: =SUM(D30:D31) | E32: =SUM(E29) | F32: =SUM(F29:F31) | G32: =SUM(G29:G31) | H32: =SUM(H29:H31) | I32: =SUM(I29:I31) | J32: =SUM(J29:J31) | K32: =SUM(K29:K31) | L32: =SUM(L29:L31) | M32: =SUM(M29:M31) | ... BI32: =SUM(BI29:BI31)
A34: Operating Expenses
A35: Personnel Stipends | B35: =B10 | C35: =C10 | D35: =D10 | E35: ='RA LLC Cashflow'!E10 | F35: ='RA LLC Cashflow'!F10 | G35: ='RA LLC Cashflow'!G10 | H35: ='RA LLC Cashflow'!H10 | I35: ='RA LLC Cashflow'!I10 | J35: ='RA LLC Cashflow'!J10 | K35: ='RA LLC Cashflow'!K10 | L35: ='RA LLC Cashflow'!L10 | ... BI35: ='RA LLC Cashflow'!BI10
A36: Expenditures | B36: =B26 | C36: =C26 | D36: =D26 | E36: =E26 | F36: =F26 | G36: =G26 | H36: =H26 | I36: =I26 | ... BI36: =BI26
A37: Total Operating Expenses | B37: =sum(B35:B36) | C37: =sum(C35:C36) | D37: =sum(D35:D36) | E37: =sum(E35:E36) | F37: =sum(F35:F36) | G37: =sum(G35:G36) | H37: =sum(H35:H36) | I37: =sum(I35:I36) | ... BI37: =sum(BI35:BI36)
A39: Revenue Streams
A40: Service Contract (RAF) | B40: ='Token Demand (5yr)'!B24 | C40: ='Token Demand (5yr)'!C24 | D40: ='Token Demand (5yr)'!D24 | E40: ='Token Demand (5yr)'!E24 | F40: ='Token Demand (5yr)'!F24 | G40: ='Token Demand (5yr)'!G24 | H40: ='Token Demand (5yr)'!H24 | I40: ='Token Demand (5yr)'!I24 | J40: ='Token Demand (5yr)'!J24 | K40: ='Token Demand (5yr)'!K31 | L40: ='Token Demand (5yr)'!L31 | M40: ='Token Demand (5yr)'!M31 | N40: ='RAF Cashflow (5yr)'!N23 | O40: ='RAF Cashflow (5yr)'!O23 | P40: ='RAF Cashflow (5yr)'!P23 | Q40: ='RAF Cashflow (5yr)'!Q23 | R40: ='RAF Cashflow (5yr)'!R23 | S40: ='RAF Cashflow (5yr)'!S23 | T40: ='RAF Cashflow (5yr)'!T23 | U40: ='RAF Cashflow (5yr)'!U23 | ... BI40: ='RAF Cashflow (5yr)'!BI23
A41: ??? | B41: 0 | C41: 0 | D41: 0 | E41: 0 | F41: 0 | G41: 0 | H41: 0 | I41: 0 | J41: 0 | K41: 0 | L41: 0 | M41: 0 | N41: 0 | O41: 0 | P41: 0 | Q41: 0 | R41: 0 | S41: 0 | T41: 0 | U41: 0 | V41: 0 | W41: 0 | X41: 0 | Y41: 0 | Z41: 0 | AA41: 0 | AB41: 0 | AC41: 0 | AD41: 0 | AE41: 0 | AF41: 0 | AG41: 0 | AH41: 0 | AI41: 0 | AJ41: 0 | AK41: 0 | AL41: 0 | AM41: 0 | AN41: 0 | AO41: 0 | AP41: 0 | AQ41: 0 | AR41: 0 | AS41: 0 | AT41: 0 | AU41: 0 | AV41: 0 | AW41: 0 | AX41: 0 | AY41: 0 | AZ41: 0 | BA41: 0 | BB41: 0 | BC41: 0 | BD41: 0 | BE41: 0 | BF41: 0 | BG41: 0 | BH41: 0 | BI41: 0
A42: ??? | B42: 0 | C42: 0 | D42: 0 | E42: 0 | F42: 0 | G42: 0 | H42: 0 | I42: 0 | J42: 0 | K42: 0 | L42: 0 | M42: 0 | N42: 0 | O42: 0 | P42: 0 | Q42: 0 | R42: 0 | S42: 0 | T42: 0 | U42: 0 | V42: 0 | W42: 0 | X42: 0 | Y42: 0 | Z42: 0 | AA42: 0 | AB42: 0 | AC42: 0 | AD42: 0 | AE42: 0 | AF42: 0 | AG42: 0 | AH42: 0 | AI42: 0 | AJ42: 0 | AK42: 0 | AL42: 0 | AM42: 0 | AN42: 0 | AO42: 0 | AP42: 0 | AQ42: 0 | AR42: 0 | AS42: 0 | AT42: 0 | AU42: 0 | AV42: 0 | AW42: 0 | AX42: 0 | AY42: 0 | AZ42: 0 | BA42: 0 | BB42: 0 | BC42: 0 | BD42: 0 | BE42: 0 | BF42: 0 | BG42: 0 | BH42: 0 | BI42: 0
A43: Total Revenue | B43: =SUM(B40:B42) | C43: =SUM(C40:C42) | D43: =SUM(D40:D42) | E43: =SUM(E40:E42) | F43: =SUM(F40:F42) | G43: =SUM(G40:G42) | H43: =SUM(H40:H42) | I43: =SUM(I40:I42) | ... BI43: =SUM(BI40:BI42)
A45: Summary
A46: Operating Expenses | B46: =-B37 | C46: =-C37 | D46: =-D37 | E46: =-E37 | F46: =-F37 | G46: =-G37 | H46: =-H37 | I46: =-I37 | ... BI46: =-BI37
A47: Capital Activities | B47: 50000 | C47: =C32 | D47: =D32 | E47: =E32 | F47: =F32 | G47: =G32 | H47: =H32 | I47: =I32 | J47: =J32 | ... BI47: =BI32
A48: Revenue | B48: =B43 | C48: =C43 | D48: =D43 | E48: =E43 | F48: =F43 | G48: =G43 | H48: =H43 | I48: =I43 | ... BI48: =BI43
A49: Net Cashflow | B49: =SUM(B46:B48) | C49: =SUM(C46:C48) | D49: =SUM(D46:D48) | E49: =SUM(E46:E48) | F49: =SUM(F46:F48) | G49: =SUM(G46:G48) | H49: =SUM(H46:H48) | I49: =SUM(I46:I48) | ... BI49: =SUM(BI46:BI48)
A50: Cash Position | B50: =B46+B32 | C50: =B50+C46+C32 | D50: =C50+D46+D32 | E50: =D50+E46+E32 | F50: =E50+F49 | G50: =F50+G49 | H50: =G50+H49 | I50: =H50+I49 | J50: =I50+J49 | K50: =J50+K49 | L50: =K50+L49 | M50: =L50+M49 | ... BI50: =BH50+BI49
A52: Annual Summaries | B52: 2025 | C52: 2026 | D52: 2027 | E52: 2028 | F52: 2029
A53: Revenue | B53: =sum(B43:M43) | C53: =sum(N43:Y43) | D53: =sum(Z43:AK43) | E53: =sum(AL43:AW43) | F53: =sum(AV43:BI43)
A54: Capital Activities | B54: =sum(B32:M32) | C54: =sum(N32:Y32) | D54: =sum(Z32:AK32) | E54: =sum(AL32:AW32) | F54: =sum(AV32:BI32)
A55: Personnel Stipends | B55: =-sum(B10:M10) | C55: =-sum(N10:Y10) | D55: =-sum(Z10:AK10) | E55: =-sum(AL10:AW10) | F55: =-sum(AV10:BI10)
A56: Expenditures | B56: =-sum(B26:M26) | C56: =-sum(N26:Y26) | D56: =-sum(Z26:AK26) | E56: =-sum(AL26:AW26) | F56: =-sum(AV26:BI26)
A57: Cash Position (EOY) | B57: =M50 | C57: =Y50 | D57: =AK50 | E57: =AW50 | F57: =BI50

Sheet RAF Cashflow (5yr)
A1: RAF Cashflow (5yr) | B1: =XAUconfig!B4 | C1: =XAUconfig!C4 | D1: =XAUconfig!D4 | E1: =XAUconfig!E4 | F1: =XAUconfig!F4 | G1: =XAUconfig!G4 | H1: =XAUconfig!H4 | I1: =XAUconfig!I4 | ... BI1: =XAUconfig!BI4
A2: Personnel Expenditures
A3: Executive Director | B3: 0 | C3: 0 | D3: 0 | E3: 0 | F3: 0 | G3: 0 | H3: 0 | I3: 0 | J3: 0 | K3: 0 | L3: =Personnel!D3 | M3: =Personnel!D3 | N3: =Personnel!D3 | O3: =Personnel!D3 | P3: =Personnel!D3 | Q3: =Personnel!D3 | R3: =Personnel!D3 | S3: =Personnel!D3 | T3: =Personnel!D3 | U3: =Personnel!D3 | V3: =Personnel!D3 | W3: =Personnel!D3 | X3: =Personnel!D3 | Y3: =Personnel!D3 | Z3: =Personnel!D3 | AA3: =Personnel!D3 | AB3: =Personnel!D3 | AC3: =Personnel!D3 | AD3: =Personnel!D3 | AE3: =Personnel!D3 | AF3: =Personnel!$E$3*1.25 | AG3: =Personnel!$E$3*1.25 | AH3: =Personnel!$E$3*1.25 | AI3: =Personnel!$E$3*1.25 | AJ3: =Personnel!$E$3*1.25 | AK3: =Personnel!$E$3*1.25 | AL3: =Personnel!D3*2 | AM3: =Personnel!D3*2 | AN3: =Personnel!D3*2 | AO3: =Personnel!D3*2 | AP3: =Personnel!D3*2 | AQ3: =Personnel!D3*2 | AR3: =Personnel!D3*2 | AS3: =Personnel!D3*2 | AT3: =Personnel!D3*2 | AU3: =Personnel!D3*2 | AV3: =Personnel!D3*2 | AW3: =Personnel!D3*2 | AX3: =Personnel!D3*2 | AY3: =Personnel!D3*2 | AZ3: =Personnel!D3*2 | BA3: =Personnel!D3*2 | BB3: =Personnel!D3*2 | BC3: =Personnel!D3*2 | BD3: =Personnel!D3*2 | BE3: =Personnel!D3*2 | BF3: =Personnel!D3*2 | BG3: =Personnel!D3*2 | BH3: =Personnel!D3*2 | BI3: =Personnel!D3*2
A4: Brand Director | B4: 0 | C4: 0 | D4: 0 | E4: 0 | F4: 0 | G4: 0 | H4: 0 | I4: 0 | J4: 0 | K4: =Personnel!D4 | L4: =Personnel!D4 | M4: =Personnel!D4 | N4: =Personnel!D4 | O4: =Personnel!D4 | P4: =Personnel!D4 | Q4: =Personnel!D4 | R4: =Personnel!D4 | S4: =Personnel!D4 | T4: =Personnel!D4 | U4: =Personnel!D4 | V4: =Personnel!D4 | W4: =Personnel!D4 | X4: =Personnel!D4 | Y4: =Personnel!D4 | Z4: =Personnel!D4 | AA4: =Personnel!D4 | AB4: =Personnel!D4 | AC4: =Personnel!D4 | AD4: =Personnel!D4 | AE4: =Personnel!D4 | AF4: =Personnel!$E$4*1.25 | AG4: =Personnel!$E$4*1.25 | AH4: =Personnel!$E$4*1.25 | AI4: =Personnel!$E$4*1.25 | AJ4: =Personnel!$E$4*1.25 | AK4: =Personnel!$E$4*1.25 | AL4: =Personnel!$E$4*1.25 | AM4: =Personnel!D4*2 | AN4: =Personnel!D4*2 | AO4: =Personnel!D4*2 | AP4: =Personnel!D4*2 | AQ4: =Personnel!D4*2 | AR4: =Personnel!D4*2 | AS4: =Personnel!D4*2 | AT4: =Personnel!D4*2 | AU4: =Personnel!D4*2 | AV4: =Personnel!D4*2 | AW4: =Personnel!D4*2 | AX4: =Personnel!D4*2 | AY4: =Personnel!D4*2 | AZ4: =Personnel!D4*2 | BA4: =Personnel!D4*2 | BB4: =Personnel!D4*2 | BC4: =Personnel!D4*2 | BD4: =Personnel!D4*2 | BE4: =Personnel!D4*2 | BF4: =Personnel!D4*2 | BG4: =Personnel!D4*2 | BH4: =Personnel!D4*2 | BI4: =Personnel!D4*2
A5: Culture / Ops Director | B5: 0 | C5: 0 | D5: 0 | E5: 0 | F5: 0 | G5: 0 | H5: 0 | I5: 0 | J5: 0 | K5: =Personnel!D5 | L5: =Personnel!D5 | M5: =Personnel!D5 | N5: =Personnel!D5 | O5: =Personnel!D5 | P5: =Personnel!D5 | Q5: =Personnel!D5 | R5: =Personnel!D5 | S5: =Personnel!D5 | T5: =Personnel!D5 | U5: =Personnel!D5 | V5: =Personnel!D5 | W5: =Personnel!D5 | X5: =Personnel!D5 | Y5: =Personnel!D5 | Z5: =Personnel!D5 | AA5: =Personnel!D5 | AB5: =Personnel!D5 | AC5: =Personnel!D5 | AD5: =Personnel!D5 | AE5: =Personnel!D5 | AF5: =Personnel!$E$5*1.25 | AG5: =Personnel!$E$5*1.25 | AH5: =Personnel!$E$5*1.25 | AI5: =Personnel!$E$5*1.25 | AJ5: =Personnel!$E$5*1.25 | AK5: =Personnel!$E$5*1.25 | AL5: =Personnel!D5*2 | AM5: =Personnel!D5*2 | AN5: =Personnel!D5*2 | AO5: =Personnel!D5*2 | AP5: =Personnel!D5*2 | AQ5: =Personnel!D5*2 | AR5: =Personnel!D5*2 | AS5: =Personnel!D5*2 | AT5: =Personnel!D5*2 | AU5: =Personnel!D5*2 | AV5: =Personnel!D5*2 | AW5: =Personnel!D5*2 | AX5: =Personnel!D5*2 | AY5: =Personnel!D5*2 | AZ5: =Personnel!D5*2 | BA5: =Personnel!D5*2 | BB5: =Personnel!D5*2 | BC5: =Personnel!D5*2 | BD5: =Personnel!D5*2 | BE5: =Personnel!D5*2 | BF5: =Personnel!D5*2 | BG5: =Personnel!D5*2 | BH5: =Personnel!D5*2 | BI5: =Personnel!D5*2
A6: Prospecting Director | B6: 0 | C6: 0 | D6: 0 | E6: 0 | F6: 0 | G6: 0 | H6: 0 | I6: 0 | J6: 0 | K6: =Personnel!D6 | L6: =Personnel!D6 | M6: =Personnel!D6 | N6: =Personnel!D6 | O6: =Personnel!D6 | P6: =Personnel!D6 | Q6: =Personnel!D6 | R6: =Personnel!D6 | S6: =Personnel!D6 | T6: =Personnel!D6 | U6: =Personnel!D6 | V6: =Personnel!D6 | W6: =Personnel!D6 | X6: =Personnel!D6 | Y6: =Personnel!D6 | Z6: =Personnel!D6 | AA6: =Personnel!D6 | AB6: =Personnel!D6 | AC6: =Personnel!D6 | AD6: =Personnel!D6 | AE6: =Personnel!D6 | AF6: =Personnel!$E$6*1.25 | AG6: =Personnel!$E$6*1.25 | AH6: =Personnel!$E$6*1.25 | AI6: =Personnel!$E$6*1.25 | AJ6: =Personnel!$E$6*1.25 | AK6: =Personnel!$E$6*1.25 | AL6: =Personnel!D6*2 | AM6: =Personnel!D6*2 | AN6: =Personnel!D6*2 | AO6: =Personnel!D6*2 | AP6: =Personnel!D6*2 | AQ6: =Personnel!D6*2 | AR6: =Personnel!D6*2 | AS6: =Personnel!D6*2 | AT6: =Personnel!D6*2 | AU6: =Personnel!D6*2 | AV6: =Personnel!D6*2 | AW6: =Personnel!D6*2 | AX6: =Personnel!D6*2 | AY6: =Personnel!D6*2 | AZ6: =Personnel!D6*2 | BA6: =Personnel!D6*2 | BB6: =Personnel!D6*2 | BC6: =Personnel!D6*2 | BD6: =Personnel!D6*2 | BE6: =Personnel!D6*2 | BF6: =Personnel!D6*2 | BG6: =Personnel!D6*2 | BH6: =Personnel!D6*2 | BI6: =Personnel!D6*2
A7: Director - CFO | B7: 0 | C7: 0 | D7: 0 | E7: 0 | F7: 0 | G7: 0 | H7: 0 | I7: 0 | J7: 0 | K7: 0 | L7: =Personnel!D7 | M7: =Personnel!D7 | N7: =Personnel!D7 | O7: =Personnel!D7 | P7: =Personnel!D7 | Q7: =Personnel!D7 | R7: =Personnel!D7 | S7: =Personnel!D7 | T7: =Personnel!D7 | U7: =Personnel!D7 | V7: =Personnel!D7 | W7: =Personnel!D7 | X7: =Personnel!D7 | Y7: =Personnel!D7 | Z7: =Personnel!D7 | AA7: =Personnel!D7 | AB7: =Personnel!D7 | AC7: =Personnel!D7 | AD7: =Personnel!D7 | AE7: =Personnel!D7 | AF7: =Personnel!$E$7*1.25 | AG7: =Personnel!$E$7*1.25 | AH7: =Personnel!$E$7*1.25 | AI7: =Personnel!$E$7*1.25 | AJ7: =Personnel!$E$7*1.25 | AK7: =Personnel!$E$7*1.25 | AL7: =Personnel!D7*2 | AM7: =Personnel!D7*2 | AN7: =Personnel!D7*2 | AO7: =Personnel!D7*2 | AP7: =Personnel!D7*2 | AQ7: =Personnel!D7*2 | AR7: =Personnel!D7*2 | AS7: =Personnel!D7*2 | AT7: =Personnel!D7*2 | AU7: =Personnel!D7*2 | AV7: =Personnel!D7*2 | AW7: =Personnel!D7*2 | AX7: =Personnel!D7*2 | AY7: =Personnel!D7*2 | AZ7: =Personnel!D7*2 | BA7: =Personnel!D7*2 | BB7: =Personnel!D7*2 | BC7: =Personnel!D7*2 | BD7: =Personnel!D7*2 | BE7: =Personnel!D7*2 | BF7: =Personnel!D7*2 | BG7: =Personnel!D7*2 | BH7: =Personnel!D7*2 | BI7: =Personnel!D7*2
A8: Director - QP | B8: 0 | C8: 0 | D8: 0 | E8: 0 | F8: 0 | G8: 0 | H8: 0 | I8: 0 | J8: 0 | K8: 0 | L8: =Personnel!D8 | M8: =Personnel!D8 | N8: =Personnel!D8 | O8: =Personnel!D8 | P8: =Personnel!D8 | Q8: =Personnel!D8 | R8: =Personnel!D8 | S8: =Personnel!D8 | T8: =Personnel!D8 | U8: =Personnel!D8 | V8: =Personnel!D8 | W8: =Personnel!D8 | X8: =Personnel!D8 | Y8: =Personnel!D8 | Z8: =Personnel!D8 | AA8: =Personnel!D8 | AB8: =Personnel!D8 | AC8: =Personnel!D8 | AD8: =Personnel!D8 | AE8: =Personnel!D8 | AF8: =Personnel!$E$8*1.25 | AG8: =Personnel!$E$8*1.25 | AH8: =Personnel!$E$8*1.25 | AI8: =Personnel!$E$8*1.25 | AJ8: =Personnel!$E$8*1.25 | AK8: =Personnel!$E$8*1.25 | AL8: =Personnel!D8*2 | AM8: =Personnel!D8*2 | AN8: =Personnel!D8*2 | AO8: =Personnel!D8*2 | AP8: =Personnel!D8*2 | AQ8: =Personnel!D8*2 | AR8: =Personnel!D8*2 | AS8: =Personnel!D8*2 | AT8: =Personnel!D8*2 | AU8: =Personnel!D8*2 | AV8: =Personnel!D8*2 | AW8: =Personnel!D8*2 | AX8: =Personnel!D8*2 | AY8: =Personnel!D8*2 | AZ8: =Personnel!D8*2 | BA8: =Personnel!D8*2 | BB8: =Personnel!D8*2 | BC8: =Personnel!D8*2 | BD8: =Personnel!D8*2 | BE8: =Personnel!D8*2 | BF8: =Personnel!D8*2 | BG8: =Personnel!D8*2 | BH8: =Personnel!D8*2 | BI8: =Personnel!D8*2
A9: Legal Counsel Coordinator | B9: 0 | C9: 0 | D9: 0 | E9: 0 | F9: 0 | G9: 0 | H9: 0 | I9: 0 | J9: 0 | K9: =Personnel!D9 | L9: =Personnel!D9 | M9: =Personnel!D9 | N9: =Personnel!D9 | O9: =Personnel!D9 | P9: =Personnel!D9 | Q9: =Personnel!D9 | R9: =Personnel!D9 | S9: =Personnel!D9 | T9: =Personnel!D9 | U9: =Personnel!D9 | V9: =Personnel!D9 | W9: =Personnel!D9 | X9: =Personnel!D9 | Y9: =Personnel!D9 | Z9: =Personnel!D9 | AA9: =Personnel!D9 | AB9: =Personnel!D9 | AC9: =Personnel!D9 | AD9: =Personnel!D9 | AE9: =Personnel!D9 | AF9: =Personnel!$E$9*1.25 | AG9: =Personnel!$E$9*1.25 | AH9: =Personnel!$E$9*1.25 | AI9: =Personnel!$E$9*1.25 | AJ9: =Personnel!$E$9*1.25 | AK9: =Personnel!$E$9*1.25 | AL9: =Personnel!D9*2 | AM9: =Personnel!D9*2 | AN9: =Personnel!D9*2 | AO9: =Personnel!D9*2 | AP9: =Personnel!D9*2 | AQ9: =Personnel!D9*2 | AR9: =Personnel!D9*2 | AS9: =Personnel!D9*2 | AT9: =Personnel!D9*2 | AU9: =Personnel!D9*2 | AV9: =Personnel!D9*2 | AW9: =Personnel!D9*2 | AX9: =Personnel!D9*2 | AY9: =Personnel!D9*2 | AZ9: =Personnel!D9*2 | BA9: =Personnel!D9*2 | BB9: =Personnel!D9*2 | BC9: =Personnel!D9*2 | BD9: =Personnel!D9*2 | BE9: =Personnel!D9*2 | BF9: =Personnel!D9*2 | BG9: =Personnel!D9*2 | BH9: =Personnel!D9*2 | BI9: =Personnel!D9*2
A10: Brand Designer / Product Designer | B10: 0 | C10: 0 | D10: 0 | E10: 0 | F10: 0 | G10: 0 | H10: 0 | I10: 0 | J10: 0 | K10: =Personnel!D10 | L10: =Personnel!D10 | M10: =Personnel!D10 | N10: =Personnel!D10 | O10: =Personnel!D10 | P10: =Personnel!D10 | Q10: =Personnel!D10 | R10: =Personnel!D10 | S10: =Personnel!D10 | T10: =Personnel!D10 | U10: =Personnel!D10 | V10: =Personnel!D10 | W10: =Personnel!D10 | X10: =Personnel!D10 | Y10: =Personnel!D10 | Z10: =Personnel!D10 | AA10: =Personnel!D10 | AB10: =Personnel!D10 | AC10: =Personnel!D10 | AD10: =Personnel!D10 | AE10: =Personnel!D10 | AF10: =Personnel!$E$10*1.25 | AG10: =Personnel!$E$10*1.25 | AH10: =Personnel!$E$10*1.25 | AI10: =Personnel!$E$10*1.25 | AJ10: =Personnel!$E$10*1.25 | AK10: =Personnel!$E$10*1.25 | AL10: =Personnel!D10*2 | AM10: =Personnel!D10*2 | AN10: =Personnel!D10*2 | AO10: =Personnel!D10*2 | AP10: =Personnel!D10*2 | AQ10: =Personnel!D10*2 | AR10: =Personnel!D10*2 | AS10: =Personnel!D10*2 | AT10: =Personnel!D10*2 | AU10: =Personnel!D10*2 | AV10: =Personnel!D10*2 | AW10: =Personnel!D10*2 | AX10: =Personnel!D10*2 | AY10: =Personnel!D10*2 | AZ10: =Personnel!D10*2 | BA10: =Personnel!D10*2 | BB10: =Personnel!D10*2 | BC10: =Personnel!D10*2 | BD10: =Personnel!D10*2 | BE10: =Personnel!D10*2 | BF10: =Personnel!D10*2 | BG10: =Personnel!D10*2 | BH10: =Personnel!D10*2 | BI10: =Personnel!D10*2
A11: Regenerative Compliance Specialist | B11: 0 | C11: 0 | D11: 0 | E11: 0 | F11: 0 | G11: 0 | H11: 0 | I11: 0 | J11: 0 | K11: =Personnel!D11 | L11: =Personnel!D11 | M11: =Personnel!D11 | N11: =Personnel!D11 | O11: =Personnel!D11 | P11: =Personnel!D11 | Q11: =Personnel!D11 | R11: =Personnel!D11 | S11: =Personnel!D11 | T11: =Personnel!D11 | U11: =Personnel!D11 | V11: =Personnel!D11 | W11: =Personnel!D11 | X11: =Personnel!D11 | Y11: =Personnel!D11 | Z11: =Personnel!D11 | AA11: =Personnel!D11 | AB11: =Personnel!D11 | AC11: =Personnel!D11 | AD11: =Personnel!D11 | AE11: =Personnel!D11 | AF11: =Personnel!$E$11*1.25 | AG11: =Personnel!$E$11*1.25 | AH11: =Personnel!$E$11*1.25 | AI11: =Personnel!$E$11*1.25 | AJ11: =Personnel!$E$11*1.25 | AK11: =Personnel!$E$11*1.25 | AL11: =Personnel!D11*2 | AM11: =Personnel!D11*2 | AN11: =Personnel!D11*2 | AO11: =Personnel!D11*2 | AP11: =Personnel!D11*2 | AQ11: =Personnel!D11*2 | AR11: =Personnel!D11*2 | AS11: =Personnel!D11*2 | AT11: =Personnel!D11*2 | AU11: =Personnel!D11*2 | AV11: =Personnel!D11*2 | AW11: =Personnel!D11*2 | AX11: =Personnel!D11*2 | AY11: =Personnel!D11*2 | AZ11: =Personnel!D11*2 | BA11: =Personnel!D11*2 | BB11: =Personnel!D11*2 | BC11: =Personnel!D11*2 | BD11: =Personnel!D11*2 | BE11: =Personnel!D11*2 | BF11: =Personnel!D11*2 | BG11: =Personnel!D11*2 | BH11: =Personnel!D11*2 | BI11: =Personnel!D11*2
A12: Board Directors (x4) | B12: 0 | C12: 0 | D12: 0 | E12: 0 | F12: 0 | G12: 0 | H12: 0 | I12: 0 | J12: 0 | K12: =Personnel!D12 | L12: =Personnel!D12 | M12: =Personnel!D12 | N12: =Personnel!D12 | O12: =Personnel!D12 | P12: =Personnel!D12 | Q12: =Personnel!D12 | R12: =Personnel!D12 | S12: =Personnel!D12 | T12: =Personnel!D12 | U12: =Personnel!D12 | V12: =Personnel!D12 | W12: =Personnel!D12 | X12: =Personnel!D12 | Y12: =Personnel!D12 | Z12: =Personnel!D12 | AA12: =Personnel!D12 | AB12: =Personnel!D12 | AC12: =Personnel!D12 | AD12: =Personnel!D12 | AE12: =Personnel!D12 | AF12: =Personnel!$D$12*1.25 | AG12: =Personnel!$D$12*1.25 | AH12: =Personnel!$D$12*1.25 | AI12: =Personnel!$D$12*1.25 | AJ12: =Personnel!$D$12*1.25 | AK12: =Personnel!$D$12*1.25 | AL12: =Personnel!D11*2 | AM12: =Personnel!D11*2 | AN12: =Personnel!D11*2 | AO12: =Personnel!D11*2 | AP12: =Personnel!D11*2 | AQ12: =Personnel!D11*2 | AR12: =Personnel!D11*2 | AS12: =Personnel!D11*2 | AT12: =Personnel!D11*2 | AU12: =Personnel!D11*2 | AV12: =Personnel!D11*2 | AW12: =Personnel!D11*2 | AX12: =Personnel!D11*2 | AY12: =Personnel!D11*2 | AZ12: =Personnel!D11*2 | BA12: =Personnel!D11*2 | BB12: =Personnel!D11*2 | BC12: =Personnel!D11*2 | BD12: =Personnel!D11*2 | BE12: =Personnel!D11*2 | BF12: =Personnel!D11*2 | BG12: =Personnel!D11*2 | BH12: =Personnel!D11*2 | BI12: =Personnel!D11*2
A13: Total Personnel Stipends | B13: =SUM(B3:B12) | C13: =SUM(C3:C12) | D13: =SUM(D3:D12) | E13: =SUM(E3:E12) | F13: =SUM(F3:F12) | G13: =SUM(G3:G12) | H13: =SUM(H3:H12) | I13: =SUM(I3:I12) | ... BI13: =SUM(BI3:BI12)
A14: Total Personnel Deferred Comp | B14: =sum('Deferred Comp'!B35:J35) | C14: ='Deferred Comp'!K35 | D14: ='Deferred Comp'!L35 | E14: ='Deferred Comp'!M35 | F14: ='Deferred Comp'!N35 | G14: ='Deferred Comp'!O35 | H14: ='Deferred Comp'!P35 | I14: ='Deferred Comp'!Q35 | J14: ='Deferred Comp'!R35 | ... BI14: ='Deferred Comp'!BQ35
A16: Expenditures
A17: Retreat Costs | B17: 0 | C17: 0 | D17: 0 | E17: 0 | F17: 0 | G17: 0 | H17: 0 | I17: 0 | J17: 0 | K17: 0 | L17: 0 | M17: 25000 | N17: 0 | O17: 0 | P17: 0 | Q17: 0 | R17: 0 | S17: 25000 | T17: 0 | U17: 0 | V17: 0 | W17: 25000 | X17: 0 | Y17: 0 | Z17: 25000 | AA17: 0 | AB17: 0 | AC17: 25000 | AD17: 0 | AE17: 0 | AF17: 25000 | AG17: 0 | AH17: 0 | AI17: 25000 | AJ17: 0 | AK17: 0 | AL17: 25000 | AM17: 0 | AN17: 0 | AO17: 25000 | AP17: 0 | AQ17: 0 | AR17: 25000 | AS17: 0 | AT17: 0 | AU17: 25000 | AV17: 0 | AW17: 0 | AX17: 25000 | AY17: 0 | AZ17: 0 | BA17: 25000 | BB17: 0 | BC17: 0 | BD17: 25000 | BE17: 0 | BF17: 0 | BG17: 25000 | BH17: 0 | BI17: 0
A18: Registered Agent, State Filing Fees, Etc. | B18: 0 | C18: 0 | D18: 0 | E18: 0 | F18: 0 | G18: 0 | H18: 0 | I18: 0 | J18: 0 | K18: 0 | L18: 0 | M18: 0 | N18: 0 | O18: 0 | P18: 500 | Q18: 0 | R18: 0 | S18: 0 | T18: 0 | U18: 0 | V18: 0 | W18: 0 | X18: 0 | Y18: 0 | Z18: 0 | AA18: 0 | AB18: 0 | AC18: 0 | AD18: 0 | AE18: 0 | AF18: 0 | AG18: 0 | AH18: 0 | AI18: 0 | AJ18: 0 | AK18: 0 | AL18: 0 | AM18: 0 | AN18: 0 | AO18: 0 | AP18: 0 | AQ18: 0 | AR18: 0 | AS18: 0 | AT18: 0 | AU18: 0 | AV18: 0 | AW18: 0 | AX18: 0 | AY18: 0 | AZ18: 0 | BA18: 0 | BB18: 0 | BC18: 0 | BD18: 0 | BE18: 0 | BF18: 0 | BG18: 0 | BH18: 0 | BI18: 0
A19: Trademarks & Patents | B19: 0 | C19: 0 | D19: 0 | E19: 0 | F19: 0 | G19: 0 | H19: 0 | I19: 0 | J19: 0 | K19: 0 | L19: 0 | M19: 0 | N19: 0 | O19: 0 | P19: 0 | Q19: 0 | R19: 0 | S19: 0 | T19: 0 | U19: 0 | V19: 0 | W19: 0 | X19: 0 | Y19: 0 | Z19: 0 | AA19: 0 | AB19: 0 | AC19: 0 | AD19: 0 | AE19: 0 | AF19: 0 | AG19: 0 | AH19: 0 | AI19: 0 | AJ19: 0 | AK19: 0 | AL19: 0 | AM19: 0 | AN19: 0 | AO19: 0 | AP19: 0 | AQ19: 0 | AR19: 0 | AS19: 0 | AT19: 0 | AU19: 0 | AV19: 0 | AW19: 0 | AX19: 0 | AY19: 0 | AZ19: 0 | BA19: 0 | BB19: 0 | BC19: 0 | BD19: 0 | BE19: 0 | BF19: 0 | BG19: 0 | BH19: 0 | BI19: 0
A20: Team Travel (marketing, prospecting) | B20: 0 | C20: 0 | D20: 0 | E20: 0 | F20: 0 | G20: 0 | H20: 0 | I20: 0 | J20: 0 | K20: 2500 | L20: 10000 | M20: 10000 | N20: 10000 | O20: 10000 | P20: 10000 | Q20: 10000 | R20: 10000 | S20: 10000 | T20: 10000 | U20: 10000 | V20: 10000 | W20: 10000 | X20: 10000 | Y20: 10000 | Z20: 10000 | AA20: 10000 | AB20: 10000 | AC20: 10000 | AD20: 10000 | AE20: 10000 | AF20: 10000 | AG20: 10000 | AH20: 10000 | AI20: 10000 | AJ20: 10000 | AK20: 10000 | AL20: 10000 | AM20: 10000 | AN20: 10000 | AO20: 10000 | AP20: 10000 | AQ20: 10000 | AR20: 10000 | AS20: 10000 | AT20: 10000 | AU20: 10000 | AV20: 10000 | AW20: 10000 | AX20: 10000 | AY20: 10000 | AZ20: 10000 | BA20: 10000 | BB20: 10000 | BC20: 10000 | BD20: 10000 | BE20: 10000 | BF20: 10000 | BG20: 10000 | BH20: 10000 | BI20: 10000
A21: External Legal Cousel - 1031 | B21: 0 | C21: 0 | D21: 0 | E21: 0 | F21: 0 | G21: 0 | H21: 0 | I21: 0 | J21: 5000 | K21: 10000 | L21: 0 | M21: 0 | N21: 10000 | O21: 0 | P21: 0 | Q21: 10000 | R21: 0 | S21: 0 | T21: 10000 | U21: 0 | V21: 0 | W21: 0 | X21: 0 | Y21: 10000 | Z21: 0 | AA21: 0 | AB21: 10000 | AC21: 0 | AD21: 0 | AE21: 0 | AF21: 0 | AG21: 10000 | AH21: 0 | AI21: 0 | AJ21: 10000 | AK21: 0 | AL21: 0 | AM21: 10000 | AN21: 0 | AO21: 0 | AP21: 10000 | AQ21: 0 | AR21: 0 | AS21: 0 | AT21: 0 | AU21: 10000 | AV21: 0 | AW21: 0 | AX21: 0 | AY21: 0 | AZ21: 0 | BA21: 0 | BB21: 0 | BC21: 0 | BD21: 0 | BE21: 0 | BF21: 0 | BG21: 0 | BH21: 0 | BI21: 0
A22: External Legal Counsel - Trusts | B22: 0 | C22: 0 | D22: 0 | E22: 0 | F22: 0 | G22: 0 | H22: 0 | I22: 0 | J22: 5000 | K22: 2500 | L22: 0 | M22: 0 | N22: 2500 | O22: 0 | P22: 0 | Q22: 2500 | R22: 0 | S22: 0 | T22: 2500 | U22: 0 | V22: 0 | W22: 0 | X22: 0 | Y22: 2500 | Z22: 0 | AA22: 0 | AB22: 2500 | AC22: 0 | AD22: 0 | AE22: 0 | AF22: 0 | AG22: 2500 | AH22: 0 | AI22: 0 | AJ22: 2500 | AK22: 0 | AL22: 0 | AM22: 2500 | AN22: 0 | AO22: 0 | AP22: 2500 | AQ22: 0 | AR22: 0 | AS22: 0 | AT22: 0 | AU22: 2500 | AV22: 0 | AW22: 0 | AX22: 0 | AY22: 0 | AZ22: 0 | BA22: 0 | BB22: 0 | BC22: 0 | BD22: 0 | BE22: 0 | BF22: 0 | BG22: 0 | BH22: 0 | BI22: 0
A23: External Tech Dev Vendor (RA LLC) | B23: 0 | C23: 0 | D23: 0 | E23: 0 | F23: 0 | G23: 0 | H23: 0 | I23: 0 | J23: 0 | K23: 0 | L23: 0 | M23: 0 | N23: 20000 | O23: 20000 | P23: 20000 | Q23: 20000 | R23: 20000 | S23: 20000 | T23: 20000 | U23: 20000 | V23: 20000 | W23: 20000 | X23: 20000 | Y23: 20000 | Z23: 5000 | AA23: 5000 | AB23: 5000 | AC23: 5000 | AD23: 5000 | AE23: 5000 | AF23: 5000 | AG23: 5000 | AH23: 5000 | AI23: 5000 | AJ23: 5000 | AK23: 5000 | AL23: 5000 | AM23: 5000 | AN23: 5000 | AO23: 5000 | AP23: 5000 | AQ23: 5000 | AR23: 5000 | AS23: 5000 | AT23: 5000 | AU23: 5000 | AV23: 5000 | AW23: 5000 | AX23: 5000 | AY23: 5000 | AZ23: 5000 | BA23: 5000 | BB23: 5000 | BC23: 5000 | BD23: 5000 | BE23: 5000 | BF23: 5000 | BG23: 5000 | BH23: 5000 | BI23: 5000
A24: KYC / AML Provider | B24: 0 | C24: 0 | D24: 0 | E24: 0 | F24: 0 | G24: 0 | H24: 0 | I24: 0 | J24: 0 | K24: 2500 | L24: 5000 | M24: 5000 | N24: 5000 | O24: 5000 | P24: 5000 | Q24: 5000 | R24: 5000 | S24: 5000 | T24: 5000 | U24: 5000 | V24: 5000 | W24: 5000 | X24: 5000 | Y24: 5000 | Z24: 5000 | AA24: 5000 | AB24: 5000 | AC24: 5000 | AD24: 5000 | AE24: 5000 | AF24: 5000 | AG24: 5000 | AH24: 5000 | AI24: 5000 | AJ24: 5000 | AK24: 5000 | AL24: 5000 | AM24: 5000 | AN24: 5000 | AO24: 5000 | AP24: 5000 | AQ24: 5000 | AR24: 5000 | AS24: 5000 | AT24: 5000 | AU24: 5000 | AV24: 5000 | AW24: 5000 | AX24: 5000 | AY24: 5000 | AZ24: 5000 | BA24: 5000 | BB24: 5000 | BC24: 5000 | BD24: 5000 | BE24: 5000 | BF24: 5000 | BG24: 5000 | BH24: 5000 | BI24: 5000
A25: Event Participation & Sponsorship | B25: 0 | C25: 0 | D25: 0 | E25: 0 | F25: 0 | G25: 0 | H25: 0 | I25: 0 | J25: 0 | K25: 0 | L25: 10000 | M25: 10000 | N25: 10000 | O25: 10000 | P25: 10000 | Q25: 10000 | R25: 10000 | S25: 10000 | T25: 10000 | U25: 10000 | V25: 10000 | W25: 10000 | X25: 10000 | Y25: 10000 | Z25: 25000 | AA25: 25000 | AB25: 25000 | AC25: 25000 | AD25: 25000 | AE25: 25000 | AF25: 25000 | AG25: 25000 | AH25: 25000 | AI25: 25000 | AJ25: 25000 | AK25: 25000 | AL25: 25000 | AM25: 25000 | AN25: 25000 | AO25: 25000 | AP25: 25000 | AQ25: 25000 | AR25: 25000 | AS25: 25000 | AT25: 25000 | AU25: 25000 | AV25: 25000 | AW25: 25000 | AX25: 25000 | AY25: 25000 | AZ25: 25000 | BA25: 25000 | BB25: 25000 | BC25: 25000 | BD25: 25000 | BE25: 25000 | BF25: 25000 | BG25: 25000 | BH25: 25000 | BI25: 25000
A26: Video + Motion Graphics Production | B26: 0 | C26: 0 | D26: 0 | E26: 0 | F26: 0 | G26: 0 | H26: 0 | I26: 0 | J26: 0 | K26: 5000 | L26: 10000 | M26: 10000 | N26: 5000 | O26: 10000 | P26: 10000 | Q26: 10000 | R26: 10000 | S26: 10000 | T26: 10000 | U26: 10000 | V26: 10000 | W26: 10000 | X26: 10000 | Y26: 10000 | Z26: 10000 | AA26: 10000 | AB26: 10000 | AC26: 10000 | AD26: 10000 | AE26: 10000 | AF26: 10000 | AG26: 10000 | AH26: 10000 | AI26: 10000 | AJ26: 10000 | AK26: 10000 | AL26: 10000 | AM26: 10000 | AN26: 10000 | AO26: 10000 | AP26: 10000 | AQ26: 10000 | AR26: 10000 | AS26: 10000 | AT26: 10000 | AU26: 10000 | AV26: 10000 | AW26: 10000 | AX26: 10000 | AY26: 10000 | AZ26: 10000 | BA26: 10000 | BB26: 10000 | BC26: 10000 | BD26: 10000 | BE26: 10000 | BF26: 10000 | BG26: 10000 | BH26: 10000 | BI26: 10000
A27: Shwag (handouts, t-shirts, etc) | B27: 0 | C27: 0 | D27: 0 | E27: 0 | F27: 0 | G27: 0 | H27: 0 | I27: 0 | J27: 1000 | K27: 0 | L27: 0 | M27: 0 | N27: 2500 | O27: 0 | P27: 0 | Q27: 2500 | R27: 0 | S27: 0 | T27: 2500 | U27: 0 | V27: 0 | W27: 2500 | X27: 0 | Y27: 0 | Z27: 2500 | AA27: 0 | AB27: 0 | AC27: 2500 | AD27: 0 | AE27: 0 | AF27: 2500 | AG27: 0 | AH27: 0 | AI27: 2500 | AJ27: 0 | AK27: 0 | AL27: 5000 | AM27: 0 | AN27: 0 | AO27: 5000 | AP27: 0 | AQ27: 0 | AR27: 5000 | AS27: 0 | AT27: 0 | AU27: 5000 | AV27: 0 | AW27: 0 | AX27: 5000 | AY27: 0 | AZ27: 0 | BA27: 5000 | BB27: 0 | BC27: 0 | BD27: 5000 | BE27: 0 | BF27: 0 | BG27: 5000 | BH27: 0 | BI27: 0
A28: Tech Infrastructure, Hardware, Software | B28: 0 | C28: 0 | D28: 0 | E28: 0 | F28: 0 | G28: 0 | H28: 0 | I28: 0 | J28: 750 | K28: 1000 | L28: 2500 | M28: 2500 | N28: 5000 | O28: 5000 | P28: 5000 | Q28: 5000 | R28: 5000 | S28: 5000 | T28: 5000 | U28: 5000 | V28: 5000 | W28: 5000 | X28: 5000 | Y28: 5000 | Z28: 5000 | AA28: 5000 | AB28: 5000 | AC28: 5000 | AD28: 5000 | AE28: 5000 | AF28: 5000 | AG28: 5000 | AH28: 5000 | AI28: 5000 | AJ28: 5000 | AK28: 5000 | AL28: 5000 | AM28: 5000 | AN28: 5000 | AO28: 5000 | AP28: 5000 | AQ28: 5000 | AR28: 5000 | AS28: 5000 | AT28: 5000 | AU28: 5000 | AV28: 5000 | AW28: 5000 | AX28: 5000 | AY28: 5000 | AZ28: 5000 | BA28: 5000 | BB28: 5000 | BC28: 5000 | BD28: 5000 | BE28: 5000 | BF28: 5000 | BG28: 5000 | BH28: 5000 | BI28: 5000
... A32: Grants Program | B32: 0 | C32: 0 | D32: 0 | E32: 0 | F32: 0 | G32: 0 | H32: 0 | I32: 0 | J32: 0 | K32: 0 | L32: 0 | M32: 0 | N32: 0 | O32: 0 | P32: 0 | Q32: 0 | R32: 0 | S32: 0 | T32: 0 | U32: 0 | V32: 0 | W32: 0 | X32: 0 | Y32: 0 | Z32: 0 | AA32: 0 | AB32: 0 | AC32: 0 | AD32: 0 | AE32: 0 | AF32: 0 | AG32: 0 | AH32: 0 | AI32: 0 | AJ32: 0 | AK32: 0 | AL32: 0 | AM32: 0 | AN32: 0 | AO32: 0 | AP32: 0 | AQ32: 0 | AR32: 0 | AS32: 0 | AT32: 0 | AU32: 0 | AV32: 0 | AW32: 0 | AX32: 0 | AY32: 0 | AZ32: 0 | BA32: 0 | BB32: 0 | BC32: 0 | BD32: 0 | BE32: 0 | BF32: 0 | BG32: 0 | BH32: 0 | BI32: 0
A33: Health + Payroll + Taxes | B33: 0 | C33: 0 | D33: 0 | E33: 0 | F33: 0 | G33: 0 | H33: 0 | I33: =I13*0.25 | J33: 0 | K33: =K13*0.25 | L33: =L13*0.25 | M33: =M13*0.25 | N33: =N13*0.25 | O33: =O13*0.25 | P33: =P13*0.25 | Q33: =Q13*0.25 | R33: =R13*0.25 | ... BI33: =BI13*0.25
A34: Contingency (10%) | B34: 0 | C34: 0 | D34: =sum(D17:D28)*0.1 | E34: =sum(E17:E33)*0.1 | F34: =sum(F17:F33)*0.1 | G34: =sum(G17:G33)*0.1 | H34: =sum(H17:H33)*0.1 | I34: 0 | J34: =sum(J17:J33)*0.1 | K34: =sum(K17:K33)*0.1 | L34: =sum(L17:L33)*0.1 | M34: =sum(M17:M33)*0.1 | N34: =sum(N17:N33)*0.1 | O34: =sum(O17:O33)*0.1 | P34: =sum(P17:P33)*0.1 | Q34: =sum(Q17:Q33)*0.1 | ... BI34: =sum(BI17:BI33)*0.1
A35: Total Expenditures | B35: =SUM(B17:B34) | C35: =SUM(C17:C34) | D35: =SUM(D17:D34) | E35: =SUM(E17:E34) | F35: =SUM(F17:F34) | G35: =SUM(G17:G34) | H35: =SUM(H17:H34) | I35: =SUM(I17:I34) | ... BI35: =SUM(BI17:BI34)
A37: Capital Activities
A38: Capital Infusion from RA LLC | B38: 0 | C38: 0 | D38: 0 | E38: 0 | F38: 0 | G38: 0 | H38: 0 | I38: =-'RA LLC Cashflow'!I30 | J38: =-'RA LLC Cashflow'!J30 | K38: =-'RA LLC Cashflow'!K30 | L38: =-'RA LLC Cashflow'!L30 | M38: 0 | N38: =-'RA LLC Cashflow'!N30 | O38: 0 | P38: 0 | Q38: 0 | R38: 0 | S38: 0 | T38: 0 | U38: 0 | V38: 0 | W38: 0 | X38: 0 | Y38: 0 | Z38: 0 | AA38: 0 | AB38: 0 | AC38: 0 | AD38: 0 | AE38: 0 | AF38: 0 | AG38: 0 | AH38: 0 | AI38: 0 | AJ38: 0 | AK38: 0 | AL38: 0 | AM38: 0 | AN38: 0 | AO38: 0 | AP38: 0 | AQ38: 0 | AR38: 0 | AS38: 0 | AT38: 0 | AU38: 0 | AV38: 0 | AW38: 0 | AX38: 0 | AY38: 0 | AZ38: 0 | BA38: 0 | BB38: 0 | BC38: 0 | BD38: 0 | BE38: 0 | BF38: 0 | BG38: 0 | BH38: 0 | BI38: 0
A39: Investment Tranch Keepons due | B39: 0 | C39: 0 | D39: 0 | E39: 0 | F39: 0 | G39: 0 | H39: 0 | I39: 0 | J39: 0 | K39: 0 | L39: 0 | M39: 0 | N39: 0 | O39: 0 | P39: 0 | Q39: 0 | R39: 0 | S39: 0 | T39: 0 | U39: 0 | V39: 0 | W39: 0 | X39: 0 | Y39: 0 | Z39: 0 | AA39: 0 | AB39: 0 | AC39: 0 | AD39: 0 | AE39: 0 | AF39: 0 | AG39: 0 | AH39: 0 | AI39: 0 | AJ39: 0 | AK39: 0 | AL39: 0 | AM39: 0 | AN39: 0 | AO39: 0 | AP39: 0 | AQ39: 0 | AR39: 0 | AS39: 0 | AT39: 0 | AU39: 0 | AV39: 0 | AW39: 0 | AX39: 0 | AY39: 0 | AZ39: 0 | BA39: 0 | BB39: 0 | BC39: 0 | BD39: 0 | BE39: 0 | BF39: 0 | BG39: 0 | BH39: 0 | BI39: =-sum(Capital!I2:I11)
A40: Personnel Deferred Comp Due | B40: 0 | C40: 0 | D40: 0 | E40: 0 | F40: 0 | G40: 0 | H40: 0 | I40: 0 | J40: 0 | K40: 0 | L40: 0 | M40: 0 | N40: 0 | O40: 0 | P40: 0 | Q40: 0 | R40: 0 | S40: 0 | T40: 0 | U40: 0 | V40: 0 | W40: 0 | X40: 0 | Y40: 0 | Z40: 0 | AA40: 0 | AB40: 0 | AC40: 0 | AD40: 0 | AE40: 0 | AF40: =-sum('Deferred Comp'!B35:J35) | AG40: =-'Deferred Comp'!K35 | AH40: =-'Deferred Comp'!L35 | AI40: =-'Deferred Comp'!M35 | AJ40: =-'Deferred Comp'!N35 | AK40: =-'Deferred Comp'!O35 | AL40: =-'Deferred Comp'!P35 | AM40: =-'Deferred Comp'!Q35 | AN40: =-'Deferred Comp'!R35 | ... BI40: =-'Deferred Comp'!AM35
A41: Total Capital Activities | B41: =SUM(B39:B40) | C41: =SUM(C39:C40) | D41: =SUM(D39:D40) | E41: =SUM(E38) | F41: =SUM(F38:F40) | G41: =SUM(G38:G40) | H41: =SUM(H38:H40) | I41: =SUM(I38:I40) | J41: =SUM(J38:J40) | K41: =SUM(K38:K40) | L41: =SUM(L38:L40) | M41: =SUM(M38:M40) | ... BI41: =SUM(BI38:BI40)
A43: Operating Expenses
A44: Personnel Stipends | B44: 0 | C44: 0 | D44: 0 | E44: ='RAF Cashflow (5yr)'!E13 | F44: ='RAF Cashflow (5yr)'!F13 | G44: ='RAF Cashflow (5yr)'!G13 | H44: ='RAF Cashflow (5yr)'!H13 | I44: ='RAF Cashflow (5yr)'!I13 | J44: ='RAF Cashflow (5yr)'!J13 | K44: ='RAF Cashflow (5yr)'!K13 | L44: ='RAF Cashflow (5yr)'!L13 | ... BI44: ='RAF Cashflow (5yr)'!BI13
A45: Expenditures | B45: =B35 | C45: =C35 | D45: =D35 | E45: =E35 | F45: =F35 | G45: =G35 | H45: =H35 | I45: =I35 | ... BI45: =BI35
A46: Total Operating Expenses | B46: =sum(B44:B45) | C46: =sum(C44:C45) | D46: =sum(D44:D45) | E46: =sum(E44:E45) | F46: =sum(F44:F45) | G46: =sum(G44:G45) | H46: =sum(H44:H45) | I46: =sum(I44:I45) | ... BI46: =sum(BI44:BI45)
A48: Revenue Streams
A49: Registration Fees | B49: ='Resource Supply (5yr)'!B22 | C49: ='Resource Supply (5yr)'!C22 | D49: ='Resource Supply (5yr)'!D22 | E49: ='Resource Supply (5yr)'!E22 | F49: ='Resource Supply (5yr)'!F22 | G49: 0 | H49: ='Resource Supply (5yr)'!G22/2 | I49: ='Resource Supply (5yr)'!I25 | J49: 0 | K49: ='Resource Supply (5yr)'!J22 | L49: ='Resource Supply (5yr)'!L22 | M49: ='Resource Supply (5yr)'!M22 | N49: ='Resource Supply (5yr)'!N22 | O49: ='Resource Supply (5yr)'!O22 | P49: ='Resource Supply (5yr)'!P22 | Q49: ='Resource Supply (5yr)'!Q22 | R49: ='Resource Supply (5yr)'!R22 | S49: ='Resource Supply (5yr)'!S22 | ... BI49: ='Resource Supply (5yr)'!BI22
A50: Yearly Admin Fees | B50: ='Resource Supply (5yr)'!B23 | C50: ='Resource Supply (5yr)'!C23 | D50: ='Resource Supply (5yr)'!D23 | E50: ='Resource Supply (5yr)'!E23 | F50: ='Resource Supply (5yr)'!F23 | G50: 0 | H50: ='Resource Supply (5yr)'!G23/2 | I50: ='Resource Supply (5yr)'!I23 | J50: 0 | K50: ='Resource Supply (5yr)'!J23 | L50: ='Resource Supply (5yr)'!L23 | M50: ='Resource Supply (5yr)'!M23 | N50: ='Resource Supply (5yr)'!N23 | O50: ='Resource Supply (5yr)'!O23 | P50: ='Resource Supply (5yr)'!P23 | Q50: ='Resource Supply (5yr)'!Q23 | R50: ='Resource Supply (5yr)'!R23 | S50: ='Resource Supply (5yr)'!S23 | ... BI50: ='Resource Supply (5yr)'!BI23
A51: Token Minting Fees | B51: 0 | C51: 0 | D51: 0 | E51: 0 | F51: 0 | G51: 0 | H51: 0 | I51: 0 | J51: 0 | K51: 0 | L51: 0 | M51: ='Resource Supply (5yr)'!M24 | N51: ='Resource Supply (5yr)'!N24+'Resource Supply (5yr)'!L24 | O51: ='Resource Supply (5yr)'!O24 | P51: ='Resource Supply (5yr)'!P24 | Q51: ='Resource Supply (5yr)'!Q24 | R51: ='Resource Supply (5yr)'!R24 | S51: ='Resource Supply (5yr)'!S24 | T51: ='Resource Supply (5yr)'!T24 | U51: ='Resource Supply (5yr)'!U24 | V51: ='Resource Supply (5yr)'!V24 | ... BI51: ='Resource Supply (5yr)'!BI24
A52: Token Transfer Tax Revenue Share | B52: ='Token Demand (5yr)'!B30 | C52: ='Token Demand (5yr)'!C30 | D52: ='Token Demand (5yr)'!D30 | E52: ='Token Demand (5yr)'!E30 | F52: ='Token Demand (5yr)'!F30 | G52: ='Token Demand (5yr)'!G30 | H52: ='Token Demand (5yr)'!H30 | I52: ='Token Demand (5yr)'!I30 | ... BI52: ='Token Demand (5yr)'!BI30
A53: Total Revenue | B53: =SUM(B50) | C53: =SUM(C50) | D53: =SUM(D50) | E53: =SUM(E50) | F53: =SUM(F50) | G53: =SUM(G49:G50) | H53: =SUM(H49:H50) | I53: =SUM(I49:I51) | J53: =SUM(J49:J52) | K53: =SUM(K49:K52) | L53: =SUM(L49:L52) | M53: =SUM(M49:M52) | N53: =SUM(N49:N52) | O53: =SUM(O49:O52) | P53: =SUM(P49:P52) | Q53: =SUM(Q49:Q52) | ... BI53: =SUM(BI49:BI52)
A55: Summary
A56: Operating Expenses | B56: =-B46 | C56: =-C46 | D56: =-D46 | E56: =-E46 | F56: =-F46 | G56: =-G46 | H56: =-H46 | I56: =-I46 | ... BI56: =-BI46
A57: Capital Activities | B57: =B41 | C57: =C41 | D57: =D41 | E57: =E41 | F57: =F41 | G57: =G41 | H57: =H41 | I57: =I41 | ... BI57: =BI41
A58: Revenue | B58: =B53 | C58: =C53 | D58: =D53 | E58: =E53 | F58: =F53 | G58: =G53 | H58: =H53 | I58: =I53 | ... BI58: =BI53
A59: Net Cashflow | B59: =SUM(B56:B58) | C59: =SUM(C56:C58) | D59: =SUM(D56:D58) | E59: =SUM(E56:E58) | F59: =SUM(F56:F58) | G59: =SUM(G56:G58) | H59: =SUM(H56:H58) | I59: =SUM(I56:I58) | ... BI59: =SUM(BI56:BI58)
A60: Cash Position | B60: =B56+B41 | C60: =B60+C56+C41 | D60: =C60+D56+D41 | E60: =D60+E56+E41 | F60: =E60+F59 | G60: =F60+G59 | H60: =G60+H59 | I60: =H60+I59 | J60: =I60+J59 | K60: =J60+K59 | L60: =K60+L59 | M60: =L60+M59 | ... BI60: =BH60+BI59
A62: Sensitivity Analysis
A63: Revenue (if XAU = -15%) | B63: =B58*Inputs!B51 | C63: =C58*Inputs!B51 | D63: =D58*Inputs!B51 | E63: =E58*Inputs!B51 | F63: =F58*Inputs!B51 | G63: =G58*Inputs!B51 | H63: =H58*Inputs!B51 | I63: =I58*Inputs!B51 | J63: =J58*Inputs!B51 | K63: =K58*Inputs!B51 | L63: =L58*Inputs!B51 | M63: =M58*Inputs!B51 | N63: =N58*Inputs!B51 | O63: =O58*Inputs!B51 | P63: =P58*Inputs!B51 | Q63: =Q58*Inputs!B51 | R63: =R58*Inputs!B51 | S63: =S58*Inputs!B51 | T63: =T58*Inputs!B51 | U63: =U58*Inputs!B51 | V63: =V58*Inputs!B51 | W63: =W58*Inputs!B51 | X63: =X58*Inputs!B51 | Y63: =Y58*Inputs!B51 | Z63: =Z58*Inputs!B51 | AA63: =AA58*Inputs!B51 | AB63: =AB58*Inputs!B51 | AC63: =AC58*Inputs!B51 | AD63: =AD58*Inputs!B51 | AE63: =AE58*Inputs!B51 | AF63: =AF58*Inputs!B51 | AG63: =AG58*Inputs!B51 | AH63: =AH58*Inputs!B51 | AI63: =AI58*Inputs!B51 | AJ63: =AJ58*Inputs!B51 | AK63: =AK58*Inputs!B51 | AL63: =AL58*Inputs!B51 | AM63: =AM58*Inputs!B51 | AN63: =AN58*Inputs!B51 | AO63: =AO58*Inputs!B51 | AP63: =AP58*Inputs!B51 | AQ63: =AQ58*Inputs!B51 | AR63: =AR58*Inputs!B51 | AS63: =AS58*Inputs!B51 | AT63: =AT58*Inputs!B51 | AU63: =AU58*Inputs!B51 | AV63: =AV58*Inputs!B51 | AW63: =AW58*Inputs!B51 | AX63: =AX58*Inputs!B51 | AY63: =AY58*Inputs!B51 | AZ63: =AZ58*Inputs!B51 | BA63: =BA58*Inputs!B51 | BB63: =BB58*Inputs!B51 | BC63: =BC58*Inputs!B51 | BD63: =BD58*Inputs!B51 | BE63: =BE58*Inputs!B51 | BF63: =BF58*Inputs!B51 | BG63: =BG58*Inputs!B51 | BH63: =BH58*Inputs!B51 | BI63: =BI58*Inputs!B51
A64: Net Cashflow | B64: =B56+B63 | C64: =C56+C63 | D64: =D56+D63 | E64: =E56+E63+E57 | F64: =F56+F63 | G64: =G56+G63+G57 | H64: =H56+H63 | I64: =I56+I63 | J64: =J56+J63 | K64: =K56+K63 | L64: =L56+L63 | M64: =M56+M63 | N64: =N56+N63 | O64: =O56+O63 | ... BI64: =BI56+BI63
A65: Cash Position ( if XAU = -15%) | B65: =B63+B64 | C65: =B65+C63+C64 | D65: =C65+D63+D64 | E65: =E63+E64 | F65: =E65+F56+F63 | G65: =F65+G56+G57+G63 | H65: =G65+H56+H63 | I65: =H65+I56+I57+I63 | J65: =I65+J56+J57+J63 | K65: =J65+K56+K57+K63 | L65: =K65+L56+L57+L63 | M65: =L65+M56+M57+M63 | N65: =M65+N56+N57+N63 | O65: =N65+O56+O57+O63 | P65: =O65+P56+P57+P63 | ... BI65: =BH65+BI56+BI57+BI63
A67: Annual Summaries | B67: 2025 | C67: 2026 | D67: 2027 | E67: 2028 | F67: 2029
A68: Revenue | B68: =sum(B53:M53) | C68: =sum(N53:Y53) | D68: =sum(Z53:AK53) | E68: =sum(AL53:AW53) | F68: =sum(AV53:BI53)
A69: Capital Activities | B69: =sum(B41:M41) | C69: =sum(N41:Y41) | D69: =sum(Z41:AK41) | E69: =sum(AL41:AW41) | F69: =sum(AV41:BI41)
A70: Personnel Stipends | B70: =-sum(B13:M13) | C70: =-sum(N13:Y13) | D70: =-sum(Z13:AK13) | E70: =-sum(AL13:AW13) | F70: =-sum(AV13:BI13)
A71: Expenditures | B71: =-sum(B35:M35) | C71: =-sum(N35:Y35) | D71: =-sum(Z35:AK35) | E71: =-sum(AL35:AW35) | F71: =-sum(AV35:BI35)
A72: Cash Position (EOY) | B72: =M60 | C72: =Y60 | D72: =AK60 | E72: =AW60 | F72: =BI60

Sheet RGT Cashflow (5yr)
A1: RGT Cashflow (5yr) | B1: =XAUconfig!B4 | C1: =XAUconfig!C4 | D1: =XAUconfig!D4 | E1: =XAUconfig!E4 | F1: =XAUconfig!F4 | G1: =XAUconfig!G4 | H1: =XAUconfig!H4 | I1: =XAUconfig!I4 | ... BI1: =XAUconfig!BI4
A2: Personnel Expenditures
A3: Executive Director | B3: 0 | C3: 0 | D3: 0 | E3: 0 | F3: 0 | G3: 0 | H3: 0 | I3: 0 | J3: 0 | K3: 0 | L3: 0 | M3: 0 | N3: =Personnel!D15 | O3: =Personnel!D15 | P3: =Personnel!D15 | Q3: =Personnel!D15 | R3: =Personnel!D15 | S3: =Personnel!D15 | T3: =Personnel!D15 | U3: =Personnel!D15 | V3: =Personnel!D15 | W3: =Personnel!D15 | X3: =Personnel!D15 | Y3: =Personnel!D15 | Z3: =Personnel!D15 | AA3: =Personnel!D15 | AB3: =Personnel!D15 | AC3: =Personnel!D15 | AD3: =Personnel!D15 | AE3: =Personnel!D15 | AF3: =Personnel!D15 | AG3: =Personnel!$E$3 | AH3: =Personnel!$E$3 | AI3: =Personnel!$E$3 | AJ3: =Personnel!$E$3 | AK3: =Personnel!$E$3 | AL3: =Personnel!$E$15*1.25 | AM3: =Personnel!$E$15*1.25 | AN3: =Personnel!$E$15*1.25 | AO3: =Personnel!$E$15*1.25 | AP3: =Personnel!$E$15*1.25 | AQ3: =Personnel!$E$15*1.25 | AR3: =Personnel!$E$15*1.25 | AS3: =Personnel!$E$15*1.25 | ... AW3: =Personnel!$E$15*1.25 | AX3: =Personnel!$E$15*1.5 | AY3: =Personnel!$E$15*1.5 | AZ3: =Personnel!$E$15*1.5 | BA3: =Personnel!$E$15*1.5 | BB3: =Personnel!$E$15*1.5 | BC3: =Personnel!$E$15*1.5 | BD3: =Personnel!$E$15*1.5 | BE3: =Personnel!$E$15*1.5 | ... BI3: =Personnel!$E$15*1.5
A4: Director of Crypto Operations | B4: 0 | C4: 0 | D4: 0 | E4: 0 | F4: 0 | G4: 0 | H4: 0 | I4: 0 | J4: 0 | K4: 0 | L4: =Personnel!D16 | M4: =Personnel!D16 | N4: =Personnel!D16 | O4: =Personnel!D16 | P4: =Personnel!D16 | Q4: =Personnel!D16 | R4: =Personnel!D16 | S4: =Personnel!D16 | T4: =Personnel!D16 | U4: =Personnel!D16 | V4: =Personnel!D16 | W4: =Personnel!D16 | X4: =Personnel!D16 | Y4: =Personnel!D16 | Z4: =Personnel!D16 | AA4: =Personnel!D16 | AB4: =Personnel!D16 | AC4: =Personnel!D16 | AD4: =Personnel!D16 | AE4: =Personnel!D16 | AF4: =Personnel!D16 | AG4: =Personnel!$E$16 | AH4: =Personnel!$E$16 | AI4: =Personnel!$E$16 | AJ4: =Personnel!$E$16 | AK4: =Personnel!$E$16 | AL4: =Personnel!$E$16*1.25 | AM4: =Personnel!$E$16*1.25 | AN4: =Personnel!$E$16*1.25 | AO4: =Personnel!$E$16*1.25 | AP4: =Personnel!$E$16*1.25 | AQ4: =Personnel!$E$16*1.25 | AR4: =Personnel!$E$16*1.25 | AS4: =Personnel!$E$16*1.25 | ... AW4: =Personnel!$E$16*1.25 | AX4: =Personnel!$E$16*1.5 | AY4: =Personnel!$E$16*1.5 | AZ4: =Personnel!$E$16*1.5 | BA4: =Personnel!$E$16*1.5 | BB4: =Personnel!$E$16*1.5 | BC4: =Personnel!$E$16*1.5 | BD4: =Personnel!$E$16*1.5 | BE4: =Personnel!$E$16*1.5 | ... BI4: =Personnel!$E$16*1.5
A5: Supervising Legal Counsel - Crypto | B5: 0 | C5: 0 | D5: 0 | E5: 0 | F5: 0 | G5: 0 | H5: 0 | I5: 0 | J5: 0 | K5: 0 | L5: =Personnel!D17 | M5: =Personnel!D17 | N5: =Personnel!D17 | O5: =Personnel!D17 | P5: =Personnel!D17 | Q5: =Personnel!D17 | R5: =Personnel!D17 | S5: =Personnel!D17 | T5: =Personnel!D17 | U5: =Personnel!D17 | V5: =Personnel!D17 | W5: =Personnel!D17 | X5: =Personnel!D17 | Y5: =Personnel!D17 | Z5: =Personnel!D17 | AA5: =Personnel!D17 | AB5: =Personnel!D17 | AC5: =Personnel!D17 | AD5: =Personnel!D17 | AE5: =Personnel!D17 | AF5: =Personnel!D17 | AG5: =Personnel!$E$17 | AH5: =Personnel!$E$17 | AI5: =Personnel!$E$17 | AJ5: =Personnel!$E$17 | AK5: =Personnel!$E$17 | AL5: =Personnel!$E$17*1.25 | AM5: =Personnel!$E$17*1.25 | AN5: =Personnel!$E$17*1.25 | AO5: =Personnel!$E$17*1.25 | AP5: =Personnel!$E$17*1.25 | AQ5: =Personnel!$E$17*1.25 | AR5: =Personnel!$E$17*1.25 | AS5: =Personnel!$E$17*1.25 | ... AW5: =Personnel!$E$17*1.25 | AX5: =Personnel!$E$17*1.5 | AY5: =Personnel!$E$17*1.5 | AZ5: =Personnel!$E$17*1.5 | BA5: =Personnel!$E$17*1.5 | BB5: =Personnel!$E$17*1.5 | BC5: =Personnel!$E$17*1.5 | BD5: =Personnel!$E$17*1.5 | BE5: =Personnel!$E$17*1.5 | ... BI5: =Personnel!$E$17*1.5
A6: Marketing / Community Manager | B6: 0 | C6: 0 | D6: 0 | E6: 0 | F6: 0 | G6: 0 | H6: 0 | I6: 0 | J6: 0 | K6: 0 | L6: =Personnel!D18 | M6: =Personnel!D18 | N6: =Personnel!D18 | O6: =Personnel!D18 | P6: =Personnel!D18 | Q6: =Personnel!D18 | R6: =Personnel!D18 | S6: =Personnel!D18 | T6: =Personnel!D18 | U6: =Personnel!D18 | V6: =Personnel!D18 | W6: =Personnel!D18 | X6: =Personnel!D18 | Y6: =Personnel!D18 | Z6: =Personnel!D18 | AA6: =Personnel!D18 | AB6: =Personnel!D18 | AC6: =Personnel!D18 | AD6: =Personnel!D18 | AE6: =Personnel!D18 | AF6: =Personnel!D18 | AG6: =Personnel!$E$18 | AH6: =Personnel!$E$18 | AI6: =Personnel!$E$18 | AJ6: =Personnel!$E$18 | AK6: =Personnel!$E$18 | AL6: =Personnel!$E$18*1.25 | AM6: =Personnel!$E$18*1.25 | AN6: =Personnel!$E$18*1.25 | AO6: =Personnel!$E$18*1.25 | AP6: =Personnel!$E$18*1.25 | AQ6: =Personnel!$E$18*1.25 | AR6: =Personnel!$E$18*1.25 | AS6: =Personnel!$E$18*1.25 | ... AW6: =Personnel!$E$18*1.25 | AX6: =Personnel!$E$18*1.5 | AY6: =Personnel!$E$18*1.5 | AZ6: =Personnel!$E$18*1.5 | BA6: =Personnel!$E$18*1.5 | BB6: =Personnel!$E$18*1.5 | BC6: =Personnel!$E$18*1.5 | BD6: =Personnel!$E$18*1.5 | BE6: =Personnel!$E$18*1.5 | ... BI6: =Personnel!$E$18*1.5
A7: Business Development | B7: 0 | C7: 0 | D7: 0 | E7: 0 | F7: 0 | G7: 0 | H7: 0 | I7: 0 | J7: 0 | K7: 0 | L7: =Personnel!D19 | M7: =Personnel!D19 | N7: =Personnel!D19 | O7: =Personnel!D19 | P7: =Personnel!D19 | Q7: =Personnel!D19 | R7: =Personnel!D19 | S7: =Personnel!D19 | T7: =Personnel!D19 | U7: =Personnel!D19 | V7: =Personnel!D19 | W7: =Personnel!D19 | X7: =Personnel!D19 | Y7: =Personnel!D19 | Z7: =Personnel!D19 | AA7: =Personnel!D19 | AB7: =Personnel!D19 | AC7: =Personnel!D19 | AD7: =Personnel!D19 | AE7: =Personnel!D19 | AF7: =Personnel!D19 | AG7: =Personnel!$E$19 | AH7: =Personnel!$E$19 | AI7: =Personnel!$E$19 | AJ7: =Personnel!$E$19 | AK7: =Personnel!$E$19 | AL7: =Personnel!$E$19*1.25 | AM7: =Personnel!$E$19*1.25 | AN7: =Personnel!$E$19*1.25 | AO7: =Personnel!$E$19*1.25 | AP7: =Personnel!$E$19*1.25 | AQ7: =Personnel!$E$19*1.25 | AR7: =Personnel!$E$19*1.25 | AS7: =Personnel!$E$19*1.25 | ... AW7: =Personnel!$E$19*1.25 | AX7: =Personnel!$E$19*1.5 | AY7: =Personnel!$E$19*1.5 | AZ7: =Personnel!$E$19*1.5 | BA7: =Personnel!$E$19*1.5 | BB7: =Personnel!$E$19*1.5 | BC7: =Personnel!$E$19*1.5 | BD7: =Personnel!$E$19*1.5 | BE7: =Personnel!$E$19*1.5 | ... BI7: =Personnel!$E$19*1.5
A8: Total Personnel Stipends | B8: =SUM(B3:B7) | C8: =SUM(C3:C7) | D8: =SUM(D3:D7) | E8: =SUM(E3:E7) | F8: =SUM(F3:F7) | G8: =SUM(G3:G7) | H8: =SUM(H3:H7) | I8: =SUM(I3:I7) | ... BI8: =SUM(BI3:BI7)
A10: Expenditures
A11: Registered Agent, State Filing Fees, Etc. | B11: 0 | C11: 0 | D11: 0 | E11: 0 | F11: 0 | G11: 0 | H11: 0 | I11: 0 | J11: 0 | K11: 0 | L11: 0 | M11: 0 | N11: 0 | O11: 0 | P11: 500 | Q11: 0 | R11: 0 | S11: 0 | T11: 0 | U11: 0 | V11: 0 | W11: 0 | X11: 0 | Y11: 0 | Z11: 0 | AA11: 0 | AB11: 0 | AC11: 0 | AD11: 0 | AE11: 0 | AF11: 0 | AG11: 0 | AH11: 0 | AI11: 0 | AJ11: 0 | AK11: 0 | AL11: 0 | AM11: 0 | AN11: 0 | AO11: 0 | AP11: 0 | AQ11: 0 | AR11: 0 | AS11: 0 | AT11: 0 | AU11: 0 | AV11: 0 | AW11: 0 | AX11: 0 | AY11: 0 | AZ11: 0 | BA11: 0 | BB11: 0 | BC11: 0 | BD11: 0 | BE11: 0 | BF11: 0 | BG11: 0 | BH11: 0 | BI11: 0
A12: Trademarks & Patents | B12: 0 | C12: 0 | D12: 0 | E12: 0 | F12: 0 | G12: 0 | H12: 0 | I12: 0 | J12: 0 | K12: 0 | L12: 0 | M12: 0 | N12: 0 | O12: 0 | P12: 0 | Q12: 0 | R12: 0 | S12: 0 | T12: 0 | U12: 0 | V12: 0 | W12: 0 | X12: 0 | Y12: 0 | Z12: 0 | AA12: 0 | AB12: 0 | AC12: 0 | AD12: 0 | AE12: 0 | AF12: 0 | AG12: 0 | AH12: 0 | AI12: 0 | AJ12: 0 | AK12: 0 | AL12: 0 | AM12: 0 | AN12: 0 | AO12: 0 | AP12: 0 | AQ12: 0 | AR12: 0 | AS12: 0 | AT12: 0 | AU12: 0 | AV12: 0 | AW12: 0 | AX12: 0 | AY12: 0 | AZ12: 0 | BA12: 0 | BB12: 0 | BC12: 0 | BD12: 0 | BE12: 0 | BF12: 0 | BG12: 0 | BH12: 0 | BI12: 0
A13: Team Travel | B13: 0 | C13: 0 | D13: 0 | E13: 0 | F13: 0 | G13: 0 | H13: 0 | I13: 0 | J13: 0 | K13: 0 | L13: 0 | M13: 0 | N13: 5000 | O13: 5000 | P13: 5000 | Q13: 10000 | R13: 10000 | S13: 10000 | T13: 10000 | U13: 10000 | V13: 10000 | W13: 10000 | X13: 10000 | Y13: 10000 | Z13: 10000 | AA13: 10000 | AB13: 10000 | AC13: 10000 | AD13: 10000 | AE13: 10000 | AF13: 10000 | AG13: 10000 | AH13: 10000 | AI13: 10000 | AJ13: 10000 | AK13: 10000 | AL13: 10000 | AM13: 10000 | AN13: 10000 | AO13: 10000 | AP13: 10000 | AQ13: 10000 | AR13: 10000 | AS13: 10000 | AT13: 10000 | AU13: 10000 | AV13: 10000 | AW13: 10000 | AX13: 10000 | AY13: 10000 | AZ13: 10000 | BA13: 10000 | BB13: 10000 | BC13: 10000 | BD13: 10000 | BE13: 10000 | BF13: 10000 | BG13: 10000 | BH13: 10000 | BI13: 10000
A14: External Design Support | B14: 0 | C14: 0 | D14: 0 | E14: 0 | F14: 0 | G14: 0 | H14: 0 | I14: 0 | J14: 0 | K14: 0 | L14: 2500 | M14: 2500 | N14: 2500 | O14: 2500 | P14: 2500 | Q14: 2500 | R14: 2500 | S14: 2500 | T14: 2500 | U14: 2500 | V14: 2500 | W14: 2500 | X14: 2500 | Y14: 2500 | Z14: 5000 | AA14: 5000 | AB14: 5000 | AC14: 5000 | AD14: 5000 | AE14: 5000 | AF14: 5000 | AG14: 5000 | AH14: 5000 | AI14: 5000 | AJ14: 5000 | AK14: 5000 | AL14: 5000 | AM14: 5000 | AN14: 5000 | AO14: 5000 | AP14: 5000 | AQ14: 5000 | AR14: 5000 | AS14: 5000 | AT14: 5000 | AU14: 5000 | AV14: 5000 | AW14: 5000 | AX14: 5000 | AY14: 5000 | AZ14: 5000 | BA14: 5000 | BB14: 5000 | BC14: 5000 | BD14: 5000 | BE14: 5000 | BF14: 5000 | BG14: 5000 | BH14: 5000 | BI14: 5000
A15: External Legal Cousel | B15: 0 | C15: 0 | D15: 0 | E15: 0 | F15: 0 | G15: 0 | H15: 0 | I15: 0 | J15: 0 | K15: 0 | L15: 0 | M15: 0 | N15: 5000 | O15: 0 | P15: 0 | Q15: 5000 | R15: 0 | S15: 0 | T15: 5000 | U15: 0 | V15: 0 | W15: 5000 | X15: 0 | Y15: 0 | Z15: 5000 | AA15: 0 | AB15: 0 | AC15: 5000 | AD15: 0 | AE15: 0 | AF15: 5000 | AG15: 0 | AH15: 0 | AI15: 5000 | AJ15: 0 | AK15: 0 | AL15: 5000 | AM15: 0 | AN15: 0 | AO15: 5000 | AP15: 0 | AQ15: 0 | AR15: 5000 | AS15: 0 | AT15: 0 | AU15: 5000 | AV15: 0 | AW15: 0 | AX15: 5000 | AY15: 0 | AZ15: 0 | BA15: 5000 | BB15: 0 | BC15: 0 | BD15: 5000 | BE15: 0 | BF15: 0 | BG15: 5000 | BH15: 0 | BI15: 0
A16: Event Participation & Sponsorship | B16: 0 | C16: 0 | D16: 0 | E16: 0 | F16: 0 | G16: 0 | H16: 0 | I16: 0 | J16: 0 | K16: 0 | L16: 0 | M16: 5000 | N16: 10000 | O16: 10000 | P16: 10000 | Q16: 10000 | R16: 10000 | S16: 10000 | T16: 10000 | U16: 10000 | V16: 10000 | W16: 10000 | X16: 10000 | Y16: 10000 | Z16: 10000 | AA16: 10000 | AB16: 10000 | AC16: 10000 | AD16: 10000 | AE16: 10000 | AF16: 10000 | AG16: 10000 | AH16: 25000 | AI16: 25000 | AJ16: 25000 | AK16: 25000 | AL16: 25000 | AM16: 25000 | AN16: 25000 | AO16: 25000 | AP16: 25000 | AQ16: 25000 | AR16: 25000 | AS16: 25000 | AT16: 25000 | AU16: 25000 | AV16: 25000 | AW16: 25000 | AX16: 25000 | AY16: 25000 | AZ16: 25000 | BA16: 25000 | BB16: 25000 | BC16: 25000 | BD16: 25000 | BE16: 25000 | BF16: 25000 | BG16: 25000 | BH16: 25000 | BI16: 25000
A17: Paid Media Buying | B17: 0 | C17: 0 | D17: 0 | E17: 0 | F17: 0 | G17: 0 | H17: 0 | I17: 0 | J17: 0 | K17: 0 | L17: 5000 | M17: 5000 | N17: 10000 | O17: 10000 | P17: 10000 | Q17: 10000 | R17: 10000 | S17: 10000 | T17: 10000 | U17: 10000 | V17: 10000 | W17: 10000 | X17: 10000 | Y17: 10000 | Z17: 10000 | AA17: 10000 | AB17: 10000 | AC17: 10000 | AD17: 10000 | AE17: 10000 | AF17: 20000 | AG17: 20000 | AH17: 20000 | AI17: 20000 | AJ17: 20000 | AK17: 20000 | AL17: 40000 | AM17: 40000 | AN17: 40000 | AO17: 40000 | AP17: 40000 | AQ17: 40000 | AR17: 40000 | AS17: 40000 | AT17: 40000 | AU17: 40000 | AV17: 40000 | AW17: 40000 | AX17: 50000 | AY17: 50000 | AZ17: 50000 | BA17: 50000 | BB17: 50000 | BC17: 50000 | BD17: 50000 | BE17: 50000 | BF17: 50000 | BG17: 50000 | BH17: 50000 | BI17: 50000
A18: Influencer / Creator Partnerships | B18: 0 | C18: 0 | D18: 0 | E18: 0 | F18: 0 | G18: 0 | H18: 0 | I18: 0 | J18: 0 | K18: 0 | L18: 0 | M18: 0 | N18: 5000 | O18: 5000 | P18: 5000 | Q18: 5000 | R18: 5000 | S18: 5000 | T18: 5000 | U18: 5000 | V18: 5000 | W18: 5000 | X18: 5000 | Y18: 5000 | Z18: 5000 | AA18: 5000 | AB18: 5000 | AC18: 5000 | AD18: 5000 | AE18: 5000 | AF18: 10000 | AG18: 10000 | AH18: 10000 | AI18: 10000 | AJ18: 10000 | AK18: 10000 | AL18: 10000 | AM18: 10000 | AN18: 10000 | AO18: 10000 | AP18: 10000 | AQ18: 10000 | AR18: 10000 | AS18: 10000 | AT18: 10000 | AU18: 10000 | AV18: 10000 | AW18: 10000 | AX18: 25000 | AY18: 25000 | AZ18: 25000 | BA18: 25000 | BB18: 25000 | BC18: 25000 | BD18: 25000 | BE18: 25000 | BF18: 25000 | BG18: 25000 | BH18: 25000 | BI18: 25000
A19: PR / Comms Agency | B19: 0 | C19: 0 | D19: 0 | E19: 0 | F19: 0 | G19: 0 | H19: 0 | I19: 0 | J19: 0 | K19: 0 | L19: 0 | M19: 0 | N19: 5000 | O19: 5000 | P19: 5000 | Q19: 5000 | R19: 5000 | S19: 5000 | T19: 5000 | U19: 5000 | V19: 5000 | W19: 5000 | X19: 5000 | Y19: 5000 | Z19: 10000 | AA19: 10000 | AB19: 10000 | AC19: 10000 | AD19: 10000 | AE19: 10000 | AF19: 10000 | AG19: 10000 | AH19: 10000 | AI19: 10000 | AJ19: 10000 | AK19: 10000 | AL19: 10000 | AM19: 10000 | AN19: 10000 | AO19: 10000 | AP19: 10000 | AQ19: 10000 | AR19: 10000 | AS19: 10000 | AT19: 10000 | AU19: 10000 | AV19: 10000 | AW19: 10000 | AX19: 10000 | AY19: 10000 | AZ19: 10000 | BA19: 10000 | BB19: 10000 | BC19: 10000 | BD19: 10000 | BE19: 10000 | BF19: 10000 | BG19: 10000 | BH19: 10000 | BI19: 10000
A20: KYC/AML Provider Costs | B20: 0 | C20: 0 | D20: 0 | E20: 0 | F20: 0 | G20: 0 | H20: 0 | I20: 0 | J20: 0 | K20: 0 | L20: 0 | M20: 2500 | N20: 5000 | O20: 5000 | P20: 5000 | Q20: 5000 | R20: 5000 | S20: 5000 | T20: 5000 | U20: 5000 | V20: 5000 | W20: 5000 | X20: 5000 | Y20: 5000 | Z20: 5000 | AA20: 5000 | AB20: 5000 | AC20: 5000 | AD20: 5000 | AE20: 5000 | AF20: 5000 | AG20: 5000 | AH20: 5000 | AI20: 5000 | AJ20: 5000 | AK20: 5000 | AL20: 5000 | AM20: 5000 | AN20: 5000 | AO20: 5000 | AP20: 5000 | AQ20: 5000 | AR20: 5000 | AS20: 5000 | AT20: 5000 | AU20: 5000 | AV20: 5000 | AW20: 5000 | AX20: 5000 | AY20: 5000 | AZ20: 5000 | BA20: 5000 | BB20: 5000 | BC20: 5000 | BD20: 5000 | BE20: 5000 | BF20: 5000 | BG20: 5000 | BH20: 5000 | BI20: 5000
A21: Regulatory Filings & Compliance | B21: 0 | C21: 0 | D21: 0 | E21: 0 | F21: 0 | G21: 0 | H21: 0 | I21: 0 | J21: 0 | K21: 0 | L21: 0 | M21: 0 | N21: 0 | O21: 0 | P21: 0 | Q21: 0 | R21: 0 | S21: 0 | T21: 0 | U21: 0 | V21: 0 | W21: 0 | X21: 0 | Y21: 0 | Z21: 10000 | AA21: 0 | AB21: 0 | AC21: 0 | AD21: 0 | AE21: 0 | AF21: 0 | AG21: 0 | AH21: 0 | AI21: 0 | AJ21: 0 | AK21: 0 | AL21: 10000 | AM21: 0 | AN21: 0 | AO21: 0 | AP21: 0 | AQ21: 0 | AR21: 0 | AS21: 0 | AT21: 0 | AU21: 0 | AV21: 0 | AW21: 0 | AX21: 10000 | AY21: 0 | AZ21: 0 | BA21: 0 | BB21: 0 | BC21: 0 | BD21: 0 | BE21: 0 | BF21: 0 | BG21: 0 | BH21: 0 | BI21: 0
A22: Crypto and Banking Fees | B22: 0 | C22: 0 | D22: 0 | E22: 0 | F22: 0 | G22: 0 | H22: 0 | I22: 0 | J22: 0 | K22: 0 | L22: 2000 | M22: 2000 | N22: 2000 | O22: 2000 | P22: 2000 | Q22: 2000 | R22: 2000 | S22: 2000 | T22: 2000 | U22: 2000 | V22: 2000 | W22: 2000 | X22: 2000 | Y22: 2000 | Z22: 2000 | AA22: 2000 | AB22: 2000 | AC22: 2000 | AD22: 2000 | AE22: 2000 | AF22: 2000 | AG22: 2000 | AH22: 2000 | AI22: 2000 | AJ22: 2000 | AK22: 2000 | AL22: 2000 | AM22: 2000 | AN22: 2000 | AO22: 2000 | AP22: 2000 | AQ22: 2000 | AR22: 2000 | AS22: 2000 | AT22: 2000 | AU22: 2000 | AV22: 2000 | AW22: 2000 | AX22: 2000 | AY22: 2000 | AZ22: 2000 | BA22: 2000 | BB22: 2000 | BC22: 2000 | BD22: 2000 | BE22: 2000 | BF22: 2000 | BG22: 2000 | BH22: 2000 | BI22: 2000
A23: Exchange Listings | B23: 0 | C23: 0 | D23: 0 | E23: 0 | F23: 0 | G23: 0 | H23: 0 | I23: 0 | J23: 0 | K23: 0 | L23: 0 | M23: 0 | N23: 0 | O23: 0 | P23: 0 | Q23: 0 | R23: 0 | S23: 0 | T23: 0 | U23: 0 | V23: 0 | W23: 0 | X23: 0 | Y23: 0 | Z23: 0 | AA23: 0 | AB23: 0 | AC23: 0 | AD23: 0 | AE23: 0 | AF23: 25000 | AI23: 25000 | AL23: 25000 | AO23: 25000
A24: Tech Infrastructure, Hardware, Software | B24: 0 | C24: 0 | D24: 0 | E24: 0 | F24: 0 | G24: 0 | H24: 0 | I24: 0 | J24: 0 | K24: 0 | L24: 0 | M24: 1000 | N24: 2500 | O24: 2500 | P24: 2500 | Q24: 2500 | R24: 2500 | S24: 2500 | T24: 5000 | U24: 5000 | V24: 5000 | W24: 5000 | X24: 5000 | Y24: 5000 | Z24: 5000 | AA24: 5000 | AB24: 5000 | AC24: 5000 | AD24: 5000 | AE24: 5000 | AF24: 5000 | AG24: 5000 | AH24: 5000 | AI24: 5000 | AJ24: 5000 | AK24: 5000 | AL24: 5000 | AM24: 5000 | AN24: 5000 | AO24: 5000 | AP24: 5000 | AQ24: 5000 | AR24: 5000 | AS24: 5000 | AT24: 5000 | AU24: 5000 | AV24: 5000 | AW24: 5000 | AX24: 5000 | AY24: 5000 | AZ24: 5000 | BA24: 5000 | BB24: 5000 | BC24: 5000 | BD24: 5000 | BE24: 5000 | BF24: 5000 | BG24: 5000 | BH24: 5000 | BI24: 5000
A25: External Accounting Counsel | B25: 0 | C25: 0 | D25: 0 | E25: 0 | F25: 0 | G25: 0 | H25: 0 | I25: 0 | J25: 0 | K25: 0 | L25: 0 | M25: 0 | N25: 10000 | O25: 0 | P25: 0 | Q25: 0 | R25: 0 | S25: 0 | T25: 0 | U25: 0 | V25: 0 | W25: 0 | X25: 0 | Y25: 0 | Z25: 10000 | AA25: 0 | AB25: 0 | AC25: 0 | AD25: 0 | AE25: 0 | AF25: 0 | AG25: 0 | AH25: 0 | AI25: 0 | AJ25: 0 | AK25: 0 | AL25: 10000 | AM25: 0 | AN25: 0 | AO25: 0 | AP25: 0 | AQ25: 0 | AR25: 0 | AS25: 0 | AT25: 0 | AU25: 0 | AV25: 0 | AW25: 0 | AX25: 10000 | AY25: 0 | AZ25: 0 | BA25: 0 | BB25: 0 | BC25: 0 | BD25: 0 | BE25: 0 | BF25: 0 | BG25: 0 | BH25: 0 | BI25: 0
A26: Insurance (general, D&O) | B26: 0 | C26: 0 | D26: 0 | E26: 0 | F26: 0 | G26: 0 | H26: 0 | I26: 0 | J26: 0 | K26: 0 | L26: 200 | M26: 200 | N26: 200 | O26: 200 | P26: 200 | Q26: 200 | R26: 200 | S26: 200 | T26: 200 | U26: 200 | V26: 200 | W26: 200 | X26: 200 | Y26: 200 | Z26: 200 | AA26: 200 | AB26: 200 | AC26: 200 | AD26: 200 | AE26: 200 | AF26: 200 | AG26: 200 | AH26: 200 | AI26: 200 | AJ26: 200 | AK26: 200 | AL26: 200 | AM26: 200 | AN26: 200 | AO26: 200 | AP26: 200 | AQ26: 200 | AR26: 200 | AS26: 200 | AT26: 200 | AU26: 200 | AV26: 200 | AW26: 200 | AX26: 200 | AY26: 200 | AZ26: 200 | BA26: 200 | BB26: 200 | BC26: 200 | BD26: 200 | BE26: 200 | BF26: 200 | BG26: 200 | BH26: 200 | BI26: 200
A27: Cybersec Monitoring, Audits, etc. | B27: 0 | C27: 0 | D27: 0 | E27: 0 | F27: 0 | G27: 0 | H27: 0 | I27: 0 | J27: 0 | K27: 0 | L27: 250 | M27: 250 | N27: 250 | O27: 250 | P27: 250 | Q27: 250 | R27: 250 | S27: 250 | T27: 250 | U27: 250 | V27: 250 | W27: 250 | X27: 250 | Y27: 250 | Z27: 5000 | AA27: 250 | AB27: 250 | AC27: 250 | AD27: 250 | AE27: 250 | AF27: 250 | AG27: 250 | AH27: 250 | AI27: 250 | AJ27: 250 | AK27: 250 | AL27: 5000 | AM27: 250 | AN27: 250 | AO27: 250 | AP27: 250 | AQ27: 250 | AR27: 250 | AS27: 250 | AT27: 250 | AU27: 250 | AV27: 250 | AW27: 250 | AX27: 5000 | AY27: 250 | AZ27: 250 | BA27: 250 | BB27: 250 | BC27: 250 | BD27: 250 | BE27: 250 | BF27: 250 | BG27: 250 | BH27: 250 | BI27: 250
A28: Redemption Costs (cash or bullion) | B28: 0 | C28: 0 | D28: 0 | E28: 0 | F28: 0 | G28: 0 | H28: 0 | I28: 0 | J28: 0 | K28: 0 | L28: 0 | M28: 0 | N28: ='Token Supply (5yr)'!N45 | O28: ='Token Supply (5yr)'!O45 | P28: ='Token Supply (5yr)'!P45 | Q28: ='Token Supply (5yr)'!Q45 | R28: ='Token Supply (5yr)'!R45 | S28: ='Token Supply (5yr)'!S45 | T28: ='Token Supply (5yr)'!T45 | U28: ='Token Supply (5yr)'!U45 | ... BI28: ='Token Supply (5yr)'!BI45
A29: Health + Payroll + Taxes | B29: 0 | C29: 0 | D29: 0 | E29: 0 | F29: 0 | G29: 0 | H29: =H8*0.25 | I29: =I8*0.25 | J29: =J8*0.25 | K29: =K8*0.25 | L29: =L8*0.25 | M29: =M8*0.25 | N29: =N8*0.25 | O29: =O8*0.25 | ... BI29: =BI8*0.25
A30: Contingency (10%) | B30: 0 | C30: 0 | D30: 0 | E30: 0 | F30: 0 | G30: 0 | H30: =sum(H11:H29)*0.1 | I30: =sum(I11:I29)*0.1 | J30: =sum(J11:J29)*0.1 | K30: =sum(K11:K29)*0.1 | L30: =sum(L11:L29)*0.1 | M30: =sum(M11:M29)*0.1 | N30: =sum(N11:N29)*0.1 | O30: =sum(O11:O29)*0.1 | ... BI30: =sum(BI11:BI29)*0.1
A31: Total Expenditures | B31: 0 | C31: 0 | D31: 0 | E31: 0 | F31: 0 | G31: 0 | H31: =SUM(H11:H30) | I31: =SUM(I11:I30) | J31: =SUM(J11:J30) | K31: =SUM(K11:K30) | L31: =SUM(L11:L30) | M31: =SUM(M11:M30) | N31: =SUM(N11:N30) | O31: =SUM(O11:O30) | ... BI31: =SUM(BI11:BI30)
A33: Capital Activities
A34: Investment Tranches (from RA LLC) | B34: 0 | C34: 0 | D34: 0 | E34: 0 | F34: 0 | G34: 0 | H34: 0 | I34: 0 | J34: 0 | K34: 0 | L34: =-'RA LLC Cashflow'!L31 | M34: =-'RA LLC Cashflow'!M31 | N34: =-'RA LLC Cashflow'!N31 | O34: 0 | P34: 0 | Q34: 0 | R34: 0 | S34: 0 | T34: 0 | U34: 0 | V34: 0 | W34: 0 | X34: 0 | Y34: 0 | Z34: 0 | AA34: 0 | AB34: 0 | AC34: 0 | AD34: 0 | AE34: 0 | AF34: 0 | AG34: 0 | AH34: 0 | AI34: 0 | AJ34: 0 | AK34: 0 | AL34: 0 | AM34: 0 | AN34: 0 | AO34: 0 | AP34: 0 | AQ34: 0 | AR34: 0 | AS34: 0 | AT34: 0 | AU34: 0 | AV34: 0 | AW34: 0 | AX34: 0 | AY34: 0 | AZ34: 0 | BA34: 0 | BB34: 0 | BC34: 0 | BD34: 0 | BE34: 0 | BF34: 0 | BG34: 0 | BH34: 0 | BI34: 0
A35: Investment Tranch Keepons due | B35: 0 | C35: 0 | D35: 0 | E35: 0 | F35: 0 | G35: 0 | H35: 0 | I35: 0 | J35: 0 | K35: 0 | L35: 0 | M35: 0 | N35: 0 | O35: 0 | P35: 0 | Q35: 0 | R35: 0 | S35: 0 | T35: 0 | U35: 0 | V35: 0 | W35: 0 | X35: 0 | Y35: 0 | Z35: 0 | AA35: 0 | AB35: 0 | AC35: 0 | AD35: 0 | AE35: 0 | AF35: 0 | AG35: 0 | AH35: 0 | AI35: 0 | AJ35: 0 | AK35: 0 | AL35: 0 | AM35: 0 | AN35: 0 | AO35: 0 | AP35: 0 | AQ35: 0 | AR35: 0 | AS35: 0 | AT35: 0 | AU35: 0 | AV35: 0 | AW35: 0 | AX35: 0 | AY35: 0 | AZ35: 0 | BA35: 0 | BB35: 0 | BC35: 0 | BD35: 0 | BE35: 0 | BF35: 0 | BG35: 0 | BH35: 0 | BI35: =-(Capital!I12+Capital!I13)
A36: Total Capital Activities | B36: =SUM(B35) | C36: =SUM(C35) | D36: =SUM(D35) | E36: =SUM(E34) | F36: =SUM(F34:F35) | G36: =SUM(G34:G35) | H36: =SUM(H34:H35) | I36: =SUM(I34:I35) | J36: =SUM(J34:J35) | K36: =SUM(K34:K35) | L36: =SUM(L34:L35) | M36: =SUM(M34:M35) | ... BI36: =SUM(BI34:BI35)
A38: Operating Expenses
A39: Personnel Stipends | B39: 0 | C39: 0 | D39: 0 | E39: ='RGT Cashflow (5yr)'!E8 | F39: ='RGT Cashflow (5yr)'!F8 | G39: ='RGT Cashflow (5yr)'!G8 | H39: ='RGT Cashflow (5yr)'!H8 | I39: ='RGT Cashflow (5yr)'!I8 | J39: ='RGT Cashflow (5yr)'!J8 | K39: ='RGT Cashflow (5yr)'!K8 | L39: ='RGT Cashflow (5yr)'!L8 | ... BI39: ='RGT Cashflow (5yr)'!BI8
A40: Expenditures | B40: =B31 | C40: =C31 | D40: =D31 | E40: =E31 | F40: =F31 | G40: =G31 | H40: =H31 | I40: =I31 | ... BI40: =BI31
A41: Total Operating Expenses | B41: =sum(B39:B40) | C41: =sum(C39:C40) | D41: =sum(D39:D40) | E41: =sum(E39:E40) | F41: =sum(F39:F40) | G41: =sum(G39:G40) | H41: =sum(H39:H40) | I41: =sum(I39:I40) | ... BI41: =sum(BI39:BI40)
A43: Revenue Streams
A44: Token Tax Revenue | B44: ='Token Demand (5yr)'!B24 | C44: ='Token Demand (5yr)'!C24 | D44: ='Token Demand (5yr)'!D24 | E44: ='Token Demand (5yr)'!E24 | F44: ='Token Demand (5yr)'!F24 | G44: ='Token Demand (5yr)'!G24 | H44: ='Token Demand (5yr)'!H24 | I44: ='Token Demand (5yr)'!I24 | J44: ='Token Demand (5yr)'!J24 | K44: ='Token Demand (5yr)'!K31 | L44: ='Token Demand (5yr)'!L31 | M44: ='Token Demand (5yr)'!M31 | N44: ='Token Demand (5yr)'!N31 | O44: ='Token Demand (5yr)'!O31 | P44: ='Token Demand (5yr)'!P31 | Q44: ='Token Demand (5yr)'!Q31 | R44: ='Token Demand (5yr)'!R31 | ... BI44: ='Token Demand (5yr)'!BI31
A45: Token Pool Swap Fee Revshare | B45: ='Token Demand (5yr)'!B26 | C45: ='Token Demand (5yr)'!C26 | D45: ='Token Demand (5yr)'!D26 | E45: ='Token Demand (5yr)'!E26 | F45: ='Token Demand (5yr)'!F26 | G45: ='Token Demand (5yr)'!G26 | H45: ='Token Demand (5yr)'!H26 | I45: ='Token Demand (5yr)'!I26 | J45: ='Token Demand (5yr)'!J26 | K45: ='Token Demand (5yr)'!K33 | L45: ='Token Demand (5yr)'!L33 | M45: ='Token Demand (5yr)'!M33 | N45: ='Token Demand (5yr)'!N33 | O45: ='Token Demand (5yr)'!O33 | P45: ='Token Demand (5yr)'!P33 | Q45: ='Token Demand (5yr)'!Q33 | R45: ='Token Demand (5yr)'!R33 | ... BI45: ='Token Demand (5yr)'!BI33
A46: Market Making Spread Revenue | B46: 0 | C46: 0 | D46: 0 | E46: 0 | F46: 0 | G46: 0 | H46: 0 | I46: 0 | J46: 0 | K46: ='Token Demand (5yr)'!K53 | L46: ='Token Demand (5yr)'!L53 | M46: ='Token Demand (5yr)'!M53 | N46: ='Token Demand (5yr)'!N53 | O46: ='Token Demand (5yr)'!O53 | P46: ='Token Demand (5yr)'!P53 | Q46: ='Token Demand (5yr)'!Q53 | R46: ='Token Demand (5yr)'!R53 | ... BI46: ='Token Demand (5yr)'!BI53
A47: Total Revenue | B47: =SUM(B44:B46) | C47: =SUM(C44:C46) | D47: =SUM(D44:D46) | E47: =SUM(E44:E46) | F47: =SUM(F44:F46) | G47: =SUM(G44:G46) | H47: =SUM(H44:H46) | I47: =SUM(I44:I46) | ... BI47: =SUM(BI44:BI46)
A49: Summary
A50: Operating Expenses | B50: =-B41 | C50: =-C41 | D50: =-D41 | E50: =-E41 | F50: =-F41 | G50: =-G41 | H50: =-H41 | I50: =-I41 | ... BI50: =-BI41
A51: Capital Activities | B51: =B36 | C51: =C36 | D51: =D36 | E51: =E36 | F51: =F36 | G51: =G36 | H51: =H36 | I51: =I36 | ... BI51: =BI36
A52: Revenue | B52: =B47 | C52: =C47 | D52: =D47 | E52: =E47 | F52: =F47 | G52: =G47 | H52: =H47 | I52: =I47 | ... BI52: =BI47
A53: Net Cashflow | B53: =SUM(B50:B52) | C53: =SUM(C50:C52) | D53: =SUM(D50:D52) | E53: =SUM(E50:E52) | F53: =SUM(F50:F52) | G53: =SUM(G50:G52) | H53: =SUM(H50:H52) | I53: =SUM(I50:I52) | ... BI53: =SUM(BI50:BI52)
A54: Cash Position | B54: =B50+B36 | C54: =B54+C50+C36 | D54: =C54+D50+D36 | E54: =D54+E50+E36 | F54: =E54+F53 | G54: =F54+G53 | H54: =G54+H53 | I54: =H54+I53 | J54: =I54+J53 | K54: =J54+K53 | L54: =K54+L53 | M54: =L54+M53 | ... BI54: =BH54+BI53
A56: Sensitivity Analysis
A57: Revenue (if XAU = -15%) | B57: =B52*Inputs!B51 | C57: =C52*Inputs!B51 | D57: =D52*Inputs!B51 | E57: =E52*Inputs!B51 | F57: =F52*Inputs!B51 | G57: =G52*Inputs!B51 | H57: =H52*Inputs!B51 | I57: =I52*Inputs!B51 | J57: =J52*Inputs!B51 | K57: =K52*Inputs!B51 | L57: =L52*Inputs!B51 | M57: =M52*Inputs!B51 | N57: =N52*Inputs!B51 | O57: =O52*Inputs!B51 | P57: =P52*Inputs!B51 | Q57: =Q52*Inputs!B51 | R57: =R52*Inputs!B51 | S57: =S52*Inputs!B51 | T57: =T52*Inputs!B51 | U57: =U52*Inputs!B51 | V57: =V52*Inputs!B51 | W57: =W52*Inputs!B51 | X57: =X52*Inputs!B51 | Y57: =Y52*Inputs!B51 | Z57: =Z52*Inputs!B51 | AA57: =AA52*Inputs!B51 | AB57: =AB52*Inputs!B51 | AC57: =AC52*Inputs!B51 | AD57: =AD52*Inputs!B51 | AE57: =AE52*Inputs!B51 | AF57: =AF52*Inputs!B51 | AG57: =AG52*Inputs!B51 | AH57: =AH52*Inputs!B51 | AI57: =AI52*Inputs!B51 | AJ57: =AJ52*Inputs!B51 | AK57: =AK52*Inputs!B51 | AL57: =AL52*Inputs!B51 | AM57: =AM52*Inputs!B51 | AN57: =AN52*Inputs!B51 | AO57: =AO52*Inputs!B51 | AP57: =AP52*Inputs!B51 | AQ57: =AQ52*Inputs!B51 | AR57: =AR52*Inputs!B51 | AS57: =AS52*Inputs!B51 | AT57: =AT52*Inputs!B51 | AU57: =AU52*Inputs!B51 | AV57: =AV52*Inputs!B51 | AW57: =AW52*Inputs!B51 | AX57: =AX52*Inputs!B51 | AY57: =AY52*Inputs!B51 | AZ57: =AZ52*Inputs!B51 | BA57: =BA52*Inputs!B51 | BB57: =BB52*Inputs!B51 | BC57: =BC52*Inputs!B51 | BD57: =BD52*Inputs!B51 | BE57: =BE52*Inputs!B51 | BF57: =BF52*Inputs!B51 | BG57: =BG52*Inputs!B51 | BH57: =BH52*Inputs!B51 | BI57: =BI52*Inputs!B51
A58: Net Cashflow | B58: =B50+B57 | C58: =C50+C57 | D58: =D50+D57 | E58: =E50+E57+E51 | F58: =F50+F57 | G58: =G50+G57+G51 | H58: =H50+H57 | I58: =I50+I57 | J58: =J50+J57 | K58: =K50+K57 | L58: =L50+L57 | M58: =M50+M57 | N58: =N50+N57 | O58: =O50+O57 | ... BI58: =BI50+BI57
A59: Cash Position ( if XAU = -15%) | B59: =B57+B58 | C59: =B59+C57+C58 | D59: =C59+D57+D58 | E59: =E57+E58 | F59: =E59+F50+F57 | G59: =F59+G50+G51+G57 | H59: =G59+H50+H57 | I59: =H59+I50+I51+I57 | J59: =I59+J50+J51+J57 | K59: =J59+K50+K51+K57 | L59: =K59+L50+L51+L57 | M59: =L59+M50+M51+M57 | N59: =M59+N50+N51+N57 | O59: =N59+O50+O51+O57 | P59: =O59+P50+P51+P57 | ... BI59: =BH59+BI50+BI51+BI57
A61: Annual Summaries | B61: 2025 | C61: 2026 | D61: 2027 | E61: 2028 | F61: 2029
A62: Revenue | B62: =sum(B47:M47) | C62: =sum(N47:Y47) | D62: =sum(Z47:AK47) | E62: =sum(AL47:AW47) | F62: =sum(AV47:BI47)
A63: Capital Activities | B63: =sum(B36:M36) | C63: =sum(N36:Y36) | D63: =sum(Z36:AK36) | E63: =sum(AL36:AW36) | F63: =sum(AV36:BI36)
A64: Personnel Stipends | B64: =-sum(B8:M8) | C64: =-sum(N8:Y8) | D64: =-sum(Z8:AK8) | E64: =-sum(AL8:AW8) | F64: =-sum(AV8:BI8)
A65: Expenditures | B65: =-sum(B31:M31) | C65: =-sum(N31:Y31) | D65: =-sum(Z31:AK31) | E65: =-sum(AL31:AW31) | F65: =-sum(AV31:BI31)
A66: Cash Position (EOY) | B66: =M54 | C66: =Y54 | D66: =AK54 | E66: =AW54 | F66: =BI54

Sheet Personnel
A1: Role/Title | B1: Name | C1: Time Committment (FTE) | D1: Monthly Stipend | E1: Market Salary (FTE) | F1: Market Salary (TC) | G1: Monthly Accrual Debt | H1: Yearly Accrual Debt | I1: Yearly Stipend
A2: Real Assets Foundation
